Workbook
Name A_DOM: inputoutput!$C$74:$W$94
Name a_dom_elec: electricity!$D$276:$M$296
Name A_IMP_SH: inputoutput!$C$97:$W$117
Name a_imp_sh_elec: electricity!$D$255:$M$275
Name Abruzzo_alpha: regions!$C$142:$I$142
Name Abruzzo_yd: regions!$C$119:$I$119
Name avg_hh_members: regions!$Q$154:$Q$173
Name Basilicata_alpha: regions!$C$146:$I$146
Name Basilicata_yd: regions!$C$123:$I$123
Name beta_q1: regions!$AZ$3:$BO$22
Name beta_q2: regions!$AZ$23:$BO$42
Name beta_q3: regions!$AZ$43:$BO$62
Name beta_q4: regions!$AZ$63:$BO$82
Name beta_q5: regions!$AZ$83:$BO$102
Name Calabria_alpha: regions!$C$147:$I$147
Name Calabria_yd: regions!$C$124:$I$124
Name Campania_alpha: regions!$C$144:$I$144
Name Campania_yd: regions!$C$121:$I$121
Name cap_const_init: electricity!$E$104:$E$112
Name cap_constr_init: electricity!$E$104:$E$112
Name cap_init: electricity!$E$95:$E$103
Name cap_prod_i: investments!#REF!
Name capwealth: finance!$E$7
Name cat_shares_q1: regions!$V$3:$AT$22
Name cat_shares_q2: regions!$V$23:$AT$42
Name cat_shares_q3: regions!$V$43:$AT$62
Name cat_shares_q4: regions!$V$63:$AT$82
Name cat_shares_q5: regions!$V$83:$AT$102
Name cf_final: electricity!$E$75:$E$83
Name child_shares_q1: regions!$AU$3:$AU$22
Name child_shares_q2: regions!$AU$23:$AU$42
Name child_shares_q3: regions!$AU$43:$AU$62
Name child_shares_q4: regions!$AU$63:$AU$82
Name child_shares_q5: regions!$AU$83:$AU$102
Name coeff_inc: prices!$Z$9:$Z$29
Name coeff_inc2: prices!$AA$9:$AA$29
Name coeff_prices: prices!$AB$9:$AV$29
Name coicop_to_ind: consumption!$B$27:$Q$47
Name cons_coicop_initial: consumption!$B$52:$Q$52
Name cons_p_initial: consumption!$B$150:$Q$150
Name cons_shocks: covid!$B$25:$O$25
Name constant: prices!$Y$9:$Y$29
Name conversion_eff: electricity!$U$192:$U$195
Name covid_cons_2020: covid!$B$9
Name covid_cons_2021: covid!$C$9
Name covid_cons_2022: covid!$D$9
Name covid_exp_2020: covid!$B$15
Name covid_exp_2021: covid!$C$15
Name covid_exp_2022: covid!$D$15
Name covid_gov_2020: covid!$B$12
Name covid_gov_2021: covid!$C$12
Name covid_gov_2022: covid!$D$12
Name covid_inv_2020: covid!$B$18
Name covid_inv_2021: covid!$C$18
Name covid_inv_2022: covid!$D$18
Name covid_lfpr_2020: covid!$B$5:$D$6
Name covid_lfpr_2021: covid!$E$5:$G$6
Name covid_lfpr_2022: covid!$H$5:$J$6
Name covid_rebound: covid!$C$29:$C$49
Name covid_shock: covid!$B$29:$B$49

Sheet Info
F4: INDEX OF DATA HERE
D9: Data country | E9: Italy
D11: Sheets
D13: Category | E13: Sheet link | F13: Description | H13: NOT FINISHED SHEET
D14: Economy | E14: =HYPERLINK("#'inputoutput'!A1", "inputoutput") -> inputoutput | F14: Input-output tables and sectoral data
D15: Economy | E15: =HYPERLINK("#'internationaltrade'!A1", "internationaltrade") -> internationaltrade | F15: Data on imports and exports
D16: Economy | E16: =HYPERLINK("#'prices'!A1", "prices") -> prices | F16: Inflation-related data
D17: Economy | E17: =HYPERLINK("#'consumption'!A1", "consumption") -> consumption | F17: Consumption expenditure related data
D18: Economy | E18: =HYPERLINK("#'beta_elasticities'!A1", "beta_elasticities") -> beta_elasticities | F18: Data on elasticity estimates
D19: Economy | E19: =HYPERLINK("#'investments'!A1", "investments") -> investments | F19: Data on capital formation and investments
D20: Economy | E20: regions | F20: Data specific to regions and relative quintiles
D21: Economy | E21: =HYPERLINK("#'finance'!A1", "finance") -> finance | F21: Wealth and interest rate
D22: Economy | E22: =HYPERLINK("#'labour'!A1", "labour") -> labour | F22: Labor market data including employment and wages
D23: Economy | E23: =HYPERLINK("#'government'!A1", "government") -> government | F23: Government spending and tax revenues | K23: Vensim code for referring to Excel data
D24: Economy | E24: =HYPERLINK("#'technology'!A1", "technology") -> technology | F24: Data on productivity | K24: GET_XLS_CONSTANTS('?InputData', 'inputoutput', 'A1')
D25: Demography | E25: =HYPERLINK("#'timeuse'!A1", "timeuse") -> timeuse | F25: Data on time use | K25: GET_XLS_CONSTANTS('?InputData', '', '')
D26: Demography | E26: =HYPERLINK("#'demography'!A1", "demography") -> demography | F26: Population, age, and demographic structure and trends
D27: Demography | E27: =HYPERLINK("#'migration'!A1", "migration") -> migration | F27: Data on migration patterns
D28: Environment | E28: =HYPERLINK("#'energy'!A1", "energy") -> energy | F28: Data on energy production, consumption, and efficiency
D29: Environment | E29: =HYPERLINK("#'electricity'!A1", "electricity") -> electricity | F29: Data on electricity generation, distribution, and consumption
D30: Environment | E30: =HYPERLINK("#'emissions'!A1", "emissions") -> emissions | F30: Data on greenhouse gas emissions from economic activity
D31: Environment | E31: =HYPERLINK("#'emissionstrading'!A1", "emissionstrading") -> emissionstrading | F31: Data on emissions trading systems and policies
D32: Environment | E32: =HYPERLINK("#'temperature'!A1", "temperature") -> temperature | F32: Climate change projections
D33: Environment | E33: =HYPERLINK("#'speciesrichness'!A1", "speciesrichness") -> speciesrichness | F33: Species richness related data
D34: Environment | E34: =HYPERLINK("#'ecosystemservices'!A1", "ecosystemservices") -> ecosystemservices | F34: Ecosystem services related data
D35: Environment | E35: =HYPERLINK("#'ecostressors'!A1", "ecostressors") -> ecostressors | F35: Data on the drivers of biodiversity loss and ecological degradation
B82: Consumption categories
C84: COICOP code | D84: Category | F84: Matching Cazcarro et al. 2022 categories | H84: Model abbreviation
B85: 1 | C85: CP01 | D85: Food and non-alcoholic beverages | F85: CP011, CP012
B86: 2 | C86: CP02 | D86: Alcoholic beverages, tobacco and narcotics | F86: CP021, CP022, CP023
B87: 3 | C87: CP03 | D87: Clothing and footwear | F87: CP031, CP032
B88: 4 | C88: CP041 – 043 | D88: Housing (actual and imputed rentals, maintenance and repair of the dwelling) | F88: CP041, CP042, CP043
B89: 5 | C89: CP044 | D89: Water supply and miscellaneous services relating to the dwelling | F89: CP044
B90: 6 | C90: CP045 | D90: Electricity, gas and other fuels | F90: CP045
B91: 7 | C91: CP05 | D91: Furnishings, household equipment and routine household maintenance | F91: CP051, CP052, CP053, CP054, CP055, CP056 (non-durable household goods)
B92: 8 | C92: CP06 | D92: Health | F92: CP061, CP062, CP063
B93: 9 | C93: CP071 – 072 | D93: Private transport | F93: CP071, CP072
B94: 10 | C94: CP073 | D94: Transport services | F94: CP073
B95: 11 | C95: CP08 | D95: Communications | F95: CP081, CP082, CP083
B96: 12 | C96: CP09 | D96: Recreation and culture | F96: CP091, CP092, CP093, CP094, CP095, CP096
... B100: 16 | C100: CP122 – 127 | D100: Other | F100: CP122, CP123, CP124, CP125, CP126, CP127

Sheet Indexes
A1: Index of ranges | B1: Description | C1: Sheet | D1: Original file
A2: A_DOM | B2: Domestic techinal coefficients matrix (not imported intermediate inputs) | C2: Inputoutput | D2: Inputoutput
A3: a_dom_elec | B3: A columns electricity | C3: Electricity | D3: electricity_module_data
A4: A_IMP_SH | B4: Import shares of input-output table | C4: Inputoutput | D4: Inputoutput
A5: a_imp_sh_elec | B5: A columns electricity import share | C5: Electricity | D5: electricity_module_data
A6: Abruzzo_alpha | B6: Abruzzo average propensity to consume | C6: regions | D6: elasticities
A7: Abruzzo_yd | B7: Abruzzo mean disposable income by quintile | C7: regions | D7: elasticities
A8: avg_hh_members | B8: average number of household members per region | C8: regions | D8: elasticities
A9: Basilicata_alpha | B9: Basilicata average propensity to consume | C9: regions | D9: elasticities
A10: Basilicata_yd | B10: Basilicata mean disposable income by quintile | C10: regions | D10: elasticities
A11: Calabria_alpha | B11: Calabria average propensity to consume | C11: regions | D11: elasticities
A12: Calabria_yd | B12: Calabria mean disposable income by quintile | C12: regions | D12: elasticities
... A17: cap_init | B17: capacity initial MW | C17: Electricity | D17: electricity_module_data
A18: cat_shares_q1 | B18: Region-quintile population shares per individual type, quintile 1 | C18: regions
A19: cat_shares_q2 | B19: Region-quintile population shares per individual type, quintile 2 | C19: regions
A20: cat_shares_q3 | B20: Region-quintile population shares per individual type, quintile 3 | C20: regions
A21: cat_shares_q4 | B21: Region-quintile population shares per individual type, quintile 4 | C21: regions
A22: cat_shares_q5 | B22: Region-quintile population shares per individual type, quintile 5 | C22: regions
A23: cf_final | B23: implicit final capacity factor techn | C23: Electricity | D23: electricity_module_data
A24: child_shares_q1 | B24: Region-quintile population shares for children, quintile 1 | C24: regions
A25: child_shares_q2 | B25: Region-quintile population shares for children, quintile 2 | C25: regions
A26: child_shares_q3 | B26: Region-quintile population shares for children, quintile 3 | C26: regions
A27: child_shares_q4 | B27: Region-quintile population shares for children, quintile 4 | C27: regions
A28: child_shares_q5 | B28: Region-quintile population shares for children, quintile 5 | C28: regions
A29: coeff_inc | B29: demand system coefficients of income | C29: prices | D29: aids
A30: coeff_prices | B30: demand system coefficients of prices | C30: prices | D30: aids
A31: coicop_to_ind | B31: Bridge matrix to convert consumption shares in coicop to consumption shares in industries | C31: consumption | D31: NACE_COICOP_bridge
A32: cons_coicop_initial | B32: Initial total consumption per coicop category | C32: consumption | D32: NACE_COICOP_bridge
A33: cons_shocks | B33: Covid shock on consumption | C33: covid | D33: elasticities
A34: constant | B34: intercept | C34: prices | D34: aids
A35: conversion_eff | B35: Fuel conversion intensities | C35: Electricity | D35: electricity_module_data
A36: covid_cons_2020 | B36: 2020 household consumption | C36: covid | D36: elasticities
A37: covid_cons_2021 | B37: 2021 household consumption | C37: covid | D37: elasticities
A38: covid_cons_2022 | B38: 2022 household consumption | C38: covid | D38: elasticities
A39: covid_exp_2020 | B39: 2020 Exports | C39: covid | D39: elasticities
A40: covid_exp_2021 | B40: 2021 Exports | C40: covid | D40: elasticities
... A179: SOU_SH_Z_IMP_OIL | B179: imported Share of oil in aggregate demand per industry | C179: Energy | D179: Energy_IO
A180: spread_italy | B180: RANGE NOT NAMED
A181: storage_final_cf | B181: final capacity factor storage | C181: Electricity | D181: electricity_module_data
A182: storage_init_cap_constr | B182: constructed initial capacity storage | C182: Electricity | D182: electricity_module_data
A183: storage_init_cf | B183: init capacity factor storage | C183: Electricity | D183: electricity_module_data
A184: techn_sh_bat | B184: NO REFERENCE IN ORIGINAL FILE | C184: Electricity | D184: electricity_module_data
A185: time | B185: time range for ets | C185: emissionstrading | D185: ETS
A186: time | B186: time axis for ETS look-up | C186: technology | D186: Technology trends
A187: time_p_ets | B187: Time for the lookup of the ETS price forecast | C187: emissionstrading | D187: ETS
A188: tls | B188: Tax rate less subsidy on products | C188: prices | D188: pp_bp
A189: Toscana_alpha | B189: Toscana average propensity to consume | C189: regions | D189: elasticities
A190: Toscana_yd | B190: Toscana mean disposable income by quintile | C190: regions | D190: elasticities
A191: total_allowances | B191: Total Allowances | C191: emissionstrading | D191: ETS
A192: trend_ereu_fd_nrg | B192: TRENDS Energy final demand by industry | C192: Energy | D192: EREU_int_new
... A235: znominit | B235: Input-Output table in euros(absolute values) | C235: inputoutput | D235: beta elasticities
A236: overall_initial_exp_trend | C236: technology | D236: Technology trends
A237: overall_initial_gov_c_trend | C237: technology | D237: Technology trends
A238: timet
A239: coeff_inc2 | B239: demand system coefficients of squared income | C239: prices | D239: aids
A240: beta_q1 | B240: Expenditure shares per COICOP category and region, quintile 1 | C240: regions | D240: betas
A241: beta_q2 | B241: Expenditure shares per COICOP category and region, quintile 2 | C241: regions | D241: betas
A242: beta_q3 | B242: Expenditure shares per COICOP category and region, quintile 3 | C242: regions | D242: betas
A243: beta_q4 | B243: Expenditure shares per COICOP category and region, quintile 4 | C243: regions | D243: betas
A244: beta_q5 | B244: Expenditure shares per COICOP category and region, quintile 5 | C244: regions | D244: betas
A245: distr_init_pop_gc | B245: Iniitial population per cohort and gender | C245: demography
A246: covid_shock | B246: Shock in 2020 for expected output, per industry | C246: covid
A247: covid_rebound | B247: Shock in 2021 for expected output, per industry | C247: covid
A248: tls_base | B248: Inital value of taxes-less-subsidies rates per industry | C248: initialrun
A249: post_debt_repayment_profits | B249: Initital value of profits after debt repayment per industry | C249: initialrun
A250: initial_unit_int_dem | B250: Initial unit intermediate costs per industry | C250: initialrun
A251: trans_use | B251: Initial transport use per output of electricity sector, per energy source | C251: initialrun
A252: yd_national_initial | B252: Initial disposable national income | C252: initialrun
A253: init_health_educ | B253: Initital government spending in health and education industries | C253: initialrun
A254: init_public | B254: Initital government spending in public industry | C254: initialrun
A255: d2_output_ratio | B255: Initial D2 to electricity output ratio | C255: initialrun
A256: emissions_output | B256: Initial emissions per output in electricity sector | C256: initialrun
... A258: yd_dynamic_share | B258: Initital share of dynamic components in household disposable income, per region and quintile | C258: initialrun

Sheet inputoutput
B1: FinDEm
D2: H | E2: G | F2: GFCF | G2: EXP
B3: dom | C3: A | D3: 1.4416841e+10 | E3: 4.7972462e+08 | F3: 4.0608227e+08 | G3: 5.2329747e+09
C4: B | D4: 1.164663e+09 | E4: 3288825.7 | F4: 1.6377672e+08 | G4: 9.5719296e+08
C5: C | D5: 9.5006733e+10 | E5: 2.1869734e+09 | F5: 4.5901407e+10 | G5: 2.5500605e+11
C6: C19 | D6: 1.4517121e+10 | E6: 10980248 | F6: 93374541 | G6: 1.1821832e+10
C7: C29 | D7: 1.0586266e+10 | E7: 59873342 | F7: 9.2033302e+09 | G7: 3.5156602e+10
C8: D1 | D8: 7.3176546e+09 | E8: 70756542 | F8: 8.9421805e+08 | G8: 4.7859998e+08
C9: D2 | D9: 8.4466889e+09 | E9: 14910176 | F9: 2.9239688e+08 | G9: 1.9708284e+08
C10: D3 | D10: 14044283 | E10: 15144529 | F10: 1.8463643e+08 | G10: 56104519
C11: E | D11: 1.0862805e+10 | E11: 3.03743e+08 | F11: 2.5860767e+08 | G11: 1.4250849e+09
C12: F | D12: 1.0850175e+10 | E12: 1.2946198e+09 | F12: 1.4143045e+11 | G12: 9.1158893e+08
C13: G | D13: 1.6414656e+11 | E13: 4.3692152e+09 | F13: 2.2544659e+10 | G13: 1.5634335e+10
C14: H | D14: 3.2267459e+10 | E14: 1.2654147e+09 | F14: 1.7775158e+09 | G14: 8.918932e+09
C15: I | D15: 7.7737627e+10 | E15: 8.5012791e+08 | F15: 1.0748647e+08 | G15: 47163108
... C23: T | D23: 1.80064e+10 | E23: 0 | F23: 0 | G23: 0
B24: imp | C24: A | D24: 3.8571939e+09 | E24: 8869778.8 | F24: 53508701
C25: B | D25: 7.5556145e+09 | E25: 5355273 | F25: 80203419
C26: C | D26: 5.114509e+10 | E26: 3.3490343e+09 | F26: 2.1619501e+10
C27: C19 | D27: 2.0777718e+09 | E27: 20799641 | F27: 19307961
C28: C29 | D28: 1.2135246e+10 | E28: 6441454.1 | F28: 7.7898918e+09
C29: D1 | D29: 1.0164527e+08 | E29: 1405739 | F29: 24526902
C30: D2 | D30: 3.1838339e+08 | E30: 4926155.2 | F30: 4621876.1
C31: D3 | D31: 8001390.9 | E31: 99246.537 | F31: 992552.88
C32: E | D32: 35242220 | E32: 2587522.4 | F32: 9728063.9
C33: F | D33: 1.0974863e+08 | E33: 8809900.8 | F33: 79085531
C34: G | D34: 8.1036708e+09 | E34: 5.7425589e+08 | F34: 2.1919856e+09
C35: H | D35: 4.3970601e+09 | E35: 1.0409825e+08 | F35: 2.0800501e+08
C36: I | D36: 1.1695584e+09 | E36: 15389552 | F36: 1589731.6
... C44: T | D44: 438497.15 | E44: 132081.35 | F44: 26290.697
B45: import shares | C45: A | D45: 0.21107511 | E45: 0.018153664 | F45: 0.11642679
C46: B | D46: 0.86644198 | E46: 0.61952937 | F46: 0.32872929
C47: C | D47: 0.34994493 | E47: 0.60495477 | F47: 0.32018973
C48: C19 | D48: 0.1252055 | E48: 0.65449067 | F48: 0.17134835
C49: C29 | D49: 0.5340862 | E49: 0.097134492 | F49: 0.4584117
C50: D1 | D50: 0.013700116 | E50: 0.019480246 | F50: 0.026696094
C51: D2 | D51: 0.036324103 | E51: 0.24834003 | F51: 0.01556089
C52: D3 | D52: 0.36294608 | E52: 0.006510627 | F52: 0.0053469714
C53: E | D53: 0.0032338106 | E53: 0.0084468318 | F53: 0.03625333
C54: F | D54: 0.010013631 | E54: 0.0067590147 | F54: 0.0005588707
C55: G | D55: 0.04704592 | E55: 0.11616451 | F55: 0.088612891
C56: H | D56: 0.11992685 | E56: 0.076011152 | F56: 0.10476093
C57: I | D57: 0.01482195 | E57: 0.017780753 | F57: 0.014574506
... C65: T | D65: 0 | E65: 0 | F65: 0
B71: A
B72: DOMESTIC
C73: A | D73: B | E73: C | F73: C19 | G73: C29 | H73: D1 | I73: D2 | J73: D3 | K73: E | L73: F | M73: G | N73: H | O73: I | P73: J_R_S | Q73: K | R73: L | S73: H_M_N | T73: O | U73: P | V73: Q | W73: T
B74: A | C74: 0.090738728 | D74: 0.00034008215 | E74: 0.027250587 | F74: 0.00010637551 | G74: 0.00027579493 | H74: 0.0010351962 | I74: 0.0020295322 | J74: 0.001688631 | K74: 0.00077185684 | L74: 0.00031538646 | M74: 0.0068093415 | N74: 0.001392886 | O74: 0.015361567 | P74: 0.00063886652 | Q74: 7.9399953e-05 | R74: 9.0913538e-05 | S74: 0.0021649374 | T74: 0.00036175801 | U74: 0.0002332266 | V74: 0.00056248482 | W74: 0
B75: B | C75: 0.00017284549 | D75: 0.0046302045 | E75: 0.0014720605 | F75: 0.055802347 | G75: 0.0005928664 | H75: 0.0045961515 | I75: 0.021506609 | J75: 0.00019305521 | K75: 0.0010159147 | L75: 0.0011539495 | M75: 0.0011327229 | N75: 0.00038080915 | O75: 0.00050511842 | P75: 0.00039664036 | Q75: 0.00012931229 | R75: 0.00018258423 | S75: 0.00055232471 | T75: 0.00023750469 | U75: 0.00018068532 | V75: 0.0003261903 | W75: 0
B76: C | C76: 0.12798976 | D76: 0.071442511 | E76: 0.286128 | F76: 0.057553595 | G76: 0.2546615 | H76: 0.016168083 | I76: 0.032942491 | J76: 0.11658925 | K76: 0.063598607 | L76: 0.12447843 | M76: 0.045545603 | N76: 0.042282203 | O76: 0.16198376 | P76: 0.056940779 | Q76: 0.016021938 | R76: 0.010286202 | S76: 0.054765987 | T76: 0.010123519 | U76: 0.008240131 | V76: 0.045372899 | W76: 0
B77: C19 | C77: 0.022887383 | D77: 0.017231733 | E77: 0.0098088375 | F77: 0.097716541 | G77: 0.0018706186 | H77: 0.033882622 | I77: 0.0044639839 | J77: 0.0047094138 | K77: 0.020084462 | L77: 0.0067980521 | M77: 0.0033081834 | N77: 0.061530166 | O77: 0.00068446459 | P77: 0.00062594659 | Q77: 0.0003215569 | R77: 3.4632635e-05 | S77: 0.0027646386 | T77: 0.0021375195 | U77: 0.00011765637 | V77: 0.00061952583 | W77: 0
B78: C29 | C78: 0.0015263455 | D78: 0.0063007686 | E78: 0.0059205066 | F78: 0.0019738464 | G78: 0.057688925 | H78: 0.0012644724 | I78: 0.0025025055 | J78: 0.0055972996 | K78: 0.00474354 | L78: 0.0038067171 | M78: 0.0067547008 | N78: 0.015266918 | O78: 0.0018518473 | P78: 0.0034604179 | Q78: 0.000977137 | R78: 0.00092707986 | S78: 0.0052524556 | T78: 0.001043678 | U78: 0.00058659427 | V78: 0.0012786118 | W78: 0
B79: D1 | C79: 0.016985394 | D79: 0.017553059 | E79: 0.018164758 | F79: 0.018504076 | G79: 0.0078636515 | H79: 0.34601685 | I79: 0.001150933 | J79: 0.0022396289 | K79: 0.02135617 | L79: 0.0026681427 | M79: 0.011409094 | N79: 0.010328953 | O79: 0.01425212 | P79: 0.0080510485 | Q79: 0.0034664205 | R79: 0.00053394951 | S79: 0.0070745102 | T79: 0.0120486 | U79: 0.004369038 | V79: 0.0059806602 | W79: 0
B80: D2 | C80: 0.00073541209 | D80: 0.0053019759 | E80: 0.0028748049 | F80: 0.0011828885 | G80: 0.00010149733 | H80: 0.084446391 | I80: 0.00013277628 | J80: 0.035535378 | K80: 0.0052797538 | L80: 0.00085778555 | M80: 0.00059747946 | N80: 0.0008964271 | O80: 0.003989204 | P80: 0.0021608588 | Q80: 0.0010334528 | R80: 0.000143817 | S80: 0.0012853554 | T80: 0.0037445732 | U80: 0.0014706751 | V80: 0.0021955083 | W80: 0
B81: D3 | C81: 2.5654968e-05 | D81: 3.1378409e-05 | E81: 3.1267157e-05 | F81: 7.0581638e-07 | G81: 4.4719292e-05 | H81: 3.2539861e-05 | I81: 0.00024562295 | J81: 0.00047783913 | K81: 8.4975329e-06 | L81: 0.00012457664 | M81: 1.7928602e-05 | N81: 1.6355642e-05 | O81: 6.6447179e-06 | P81: 2.1906851e-05 | Q81: 1.318002e-05 | R81: 4.9612931e-07 | S81: 1.064075e-05 | T81: 1.2458173e-05 | U81: 1.1797057e-05 | V81: 6.2883901e-06 | W81: 0
B82: E | C82: 0.0077044111 | D82: 0.028298525 | E82: 0.013122666 | F82: 0.0034312633 | G82: 0.0065112518 | H82: 0.01495689 | I82: 0.033816528 | J82: 0.016970328 | K82: 0.20471523 | L82: 0.0036336797 | M82: 0.002999502 | N82: 0.0047878432 | O82: 0.0030935379 | P82: 0.0075619105 | Q82: 0.0013281628 | R82: 0.00056240963 | S82: 0.0035009506 | T82: 0.0023552405 | U82: 0.0010547392 | V82: 0.0030141654 | W82: 0
B83: F | C83: 0.011564764 | D83: 0.0065540544 | E83: 0.0066455667 | F83: 0.0066240874 | G83: 0.0099950991 | H83: 0.0079447031 | I83: 0.0014149602 | J83: 0.0026570013 | K83: 0.010474882 | L83: 0.28921876 | M83: 0.0080209151 | N83: 0.01257485 | O83: 0.0073775677 | P83: 0.010597727 | Q83: 0.0050248629 | R83: 0.0078698925 | S83: 0.011768609 | T83: 0.019238064 | U83: 0.0061748904 | V83: 0.013427052 | W83: 0
B84: G | C84: 0.031291172 | D84: 0.027007588 | E84: 0.0593284 | F84: 0.063305961 | G84: 0.072939625 | H84: 0.027765343 | I84: 0.059011076 | J84: 0.35311008 | K84: 0.044917799 | L84: 0.023701206 | M84: 0.047631634 | N84: 0.041193143 | O84: 0.032521097 | P84: 0.026825693 | Q84: 0.012858711 | R84: 0.0035373476 | S84: 0.036297833 | T84: 0.0052976412 | U84: 0.0035920259 | V84: 0.01998399 | W84: 0
B85: H | C85: 0.017151602 | D85: 0.033221405 | E85: 0.025921956 | F85: 0.028617417 | G85: 0.018354654 | H85: 0.01725042 | I85: 0.10127098 | J85: 0.053482471 | K85: 0.016497811 | L85: 0.010894221 | M85: 0.032417763 | N85: 0.072956704 | O85: 0.0091154533 | P85: 0.0088707674 | Q85: 0.0055259416 | R85: 0.0007829387 | S85: 0.029647346 | T85: 0.010378785 | U85: 0.0040213204 | V85: 0.0045783079 | W85: 0
... B94: T | C94: 0 | D94: 0 | E94: 0 | F94: 0 | G94: 0 | H94: 0 | I94: 0 | J94: 0 | K94: 0 | L94: 0 | M94: 0 | N94: 0 | O94: 0 | P94: 0 | Q94: 0 | R94: 0 | S94: 0 | T94: 0 | U94: 0 | V94: 0 | W94: 0
B95: Import shares
C96: A | D96: B | E96: C | F96: C19 | G96: C29 | H96: D1 | I96: D2 | J96: D3 | K96: E | L96: F | M96: G | N96: H | O96: I | P96: J_R_S | Q96: K | R96: L | S96: H_M_N | T96: O | U96: P | V96: Q | W96: T
B97: A | C97: 0.20858998 | D97: 0.19090973 | E97: 0.21807365 | F97: 0.56555218 | G97: 0.31689932 | H97: 0.051206886 | I97: 0.02179743 | J97: 0.042601899 | K97: 0.13777467 | L97: 0.20994904 | M97: 0.20848991 | N97: 0.091650187 | O97: 0.16360434 | P97: 0.16622053 | Q97: 0.091959087 | R97: 0.13868105 | S97: 0.24227746 | T97: 0.098806126 | U97: 0.086983812 | V97: 0.11756674 | W97: 0
B98: B | C98: 2.5360162 | D98: 6.597334 | E98: 5.7017742 | F98: 7.1080155 | G98: 1.8631992 | H98: 4.2982984 | I98: 8.8186177 | J98: 289.9131 | K98: 5.6759886 | L98: 2.8679542 | M98: 5.3034129 | N98: 4.6214848 | O98: 3.4518176 | P98: 0.99672922 | Q98: 1.8427521 | R98: 0.85646112 | S98: 1.2923224 | T98: 5.6139403 | U98: 0.27566794 | V98: 1.7906624 | W98: 0
B99: C | C99: 0.24553013 | D99: 0.48420211 | E99: 0.37159472 | F99: 0.4675922 | G99: 0.32711817 | H99: 0.47080878 | I99: 0.59211861 | J99: 0.58714275 | K99: 0.17853918 | L99: 0.27223162 | M99: 0.28265539 | N99: 0.21720823 | O99: 0.10409284 | P99: 0.32340989 | Q99: 0.16785827 | R99: 0.27488309 | S99: 0.30324519 | T99: 0.23742441 | U99: 0.23665057 | V99: 0.72526444 | W99: 0
B100: C19 | C100: 0.30381467 | D100: 0.3299626 | E100: 0.36557864 | F100: 0.29199831 | G100: 0.44181808 | H100: 0.19989067 | I100: 1.3297816 | J100: 2.4389531 | K100: 0.27809981 | L100: 0.28192288 | M100: 0.2942394 | N100: 0.27609323 | O100: 0.23087504 | P100: 0.3471279 | Q100: 0.2360216 | R100: 0.4214359 | S100: 0.28904468 | T100: 0.26460475 | U100: 0.27172633 | V100: 0.73241906 | W100: 0
B101: C29 | C101: 0.321486 | D101: 0.78603643 | E101: 0.65342352 | F101: 0.60647571 | G101: 1.0413441 | H101: 0.38046098 | I101: 1.2437402 | J101: 0.28606406 | K101: 0.7620647 | L101: 0.63953925 | M101: 1.1314692 | N101: 0.7028261 | O101: 0.58267493 | P101: 0.46256803 | Q101: 0.59162872 | R101: 0.97790988 | S101: 0.7900368 | T101: 0.15880012 | U101: 0.15526968 | V101: 0.26070391 | W101: 0
B102: D1 | C102: 0.0054420808 | D102: 0.00017521139 | E102: 0.0027231693 | F102: 0.0006286055 | G102: 0.013538587 | H102: 0.0058235159 | I102: 0.10719605 | J102: 0.069386493 | K102: 0.00056963009 | L102: 0.018771514 | M102: 0.0098810178 | N102: 0.0036451619 | O102: 0.0010212535 | P102: 0.0028633081 | Q102: 0.0089741484 | R102: 0.0018518143 | S102: 0.0044739996 | T102: 0.0077902439 | U102: 0.006672569 | V102: 0.0017650194 | W102: 0
B103: D2 | C103: 0.8105905 | D103: 0.19609912 | E103: 0.28782945 | F103: 1.5591167 | G103: 2.4398103 | H103: 0.18071145 | I103: 0.29171447 | J103: 1.0714165 | K103: 0.23422366 | L103: 0.083419962 | M103: 0.56946388 | N103: 0.44890538 | O103: 0.17721798 | P103: 0.18658528 | Q103: 0.084445223 | R103: 0.21735026 | S103: 0.22788456 | T103: 0.14650283 | U103: 0.14488718 | V103: 0.14745195 | W103: 0
B104: D3 | C104: 0.25140579 | D104: 0.0061205726 | E104: 0.11703028 | F104: 1.434739 | G104: 0.11553884 | H104: 0.085720703 | I104: 0.02758999 | J104: 0.014864581 | K104: 0.079351572 | L104: 0.018810913 | M104: 0.37253201 | N104: 0.15814727 | O104: 0.14695985 | P104: 0.065143782 | Q104: 0.15206082 | R104: 0.13887756 | S104: 0.1615624 | T104: 0.38515031 | U104: 0.17742616 | V104: 0.11885475 | W104: 0
B105: E | C105: 0.058890726 | D105: 0.11657758 | E105: 0.12119543 | F105: 0.16300961 | G105: 0.11225879 | H105: 0.089725161 | I105: 0.07780098 | J105: 0.19179582 | K105: 0.12462565 | L105: 0.069019095 | M105: 0.067987606 | N105: 0.093261078 | O105: 0.035953143 | P105: 0.089513241 | Q105: 0.06808386 | R105: 0.031094378 | S105: 0.065342947 | T105: 0.024352459 | U105: 0.011933899 | V105: 0.073094213 | W105: 0
B106: F | C106: 0.0063251928 | D106: 0.025927605 | E106: 0.031337851 | F106: 0.082327627 | G106: 0.028020859 | H106: 0.015117397 | I106: 0.09341357 | J106: 0.077665223 | K106: 0.01281766 | L106: 0.0039033629 | M106: 0.00981235 | N106: 0.0090563994 | O106: 0.0085620217 | P106: 0.0080913124 | Q106: 0.0055706909 | R106: 0.0038725272 | S106: 0.006570607 | T106: 0.0040698921 | U106: 0.00396494 | V106: 0.0044997771 | W106: 0
B107: G | C107: 0.15796615 | D107: 0.24457108 | E107: 0.16093855 | F107: 0.61731273 | G107: 0.12977007 | H107: 0.22419119 | I107: 0.17873496 | J107: 0.16130135 | K107: 0.086707099 | L107: 0.14561042 | M107: 0.066788559 | N107: 0.06187094 | O107: 0.07690723 | P107: 0.086407323 | Q107: 0.052270136 | R107: 0.096068675 | S107: 0.068234212 | T107: 0.090847495 | U107: 0.077224861 | V107: 0.19530006 | W107: 0
B108: H | C108: 0.059175977 | D108: 0.16625433 | E108: 0.099935955 | F108: 1.1350064 | G108: 0.11268349 | H108: 0.51257146 | I108: 0.23748768 | J108: 0.25910808 | K108: 0.11309396 | L108: 0.092678354 | M108: 0.061328574 | N108: 0.10644985 | O108: 0.085307978 | P108: 0.13359315 | Q108: 0.46409116 | R108: 0.072765962 | S108: 0.095951355 | T108: 0.23224548 | U108: 0.10608524 | V108: 0.1378152 | W108: 0
... B117: T | C117: 0 | D117: 0 | E117: 0 | F117: 0 | G117: 0 | H117: 0 | I117: 0 | J117: 0 | K117: 0 | L117: 0 | M117: 0 | N117: 0 | O117: 0 | P117: 0 | Q117: 0 | R117: 0 | S117: 0 | T117: 0 | U117: 0 | V117: 0 | W117: 0
B118: Z Matrix
C119: A | D119: B | E119: C | F119: C19 | G119: C29 | H119: D1 | I119: D2 | J119: D3 | K119: E | L119: F | M119: G | N119: H | O119: I | P119: J_R_S | Q119: K | R119: L | S119: H_M_N | T119: O | U119: P | V119: Q | W119: T
B120: A | C120: 4.6149726e+09 | D120: 2870619.4 | E120: 2.0616422e+10 | F120: 5808319.4 | G120: 19938550 | H120: 63618292 | I120: 39708201 | J120: 605918.14 | K120: 31244552 | L120: 79973840 | M120: 2.1754305e+09 | N120: 1.5077337e+08 | O120: 1.5113841e+09 | P120: 1.3296353e+08 | Q120: 10492174 | R120: 19831269 | S120: 7.0122551e+08 | T120: 49389021 | U120: 17372275 | V120: 80363279 | W120: 0
B121: B | C121: 8790923.5 | D121: 39083365 | E121: 1.1136869e+09 | F121: 3.0469219e+09 | G121: 42861180 | H121: 2.8245787e+08 | I121: 4.2078108e+08 | J121: 69272.476 | K121: 41123948 | L121: 2.9261172e+08 | M121: 3.6187933e+08 | N121: 41220804 | O121: 49697272 | P121: 82550422 | Q121: 17087756 | R121: 39827699 | S121: 1.7889855e+08 | T121: 32425333 | U121: 13458649 | V121: 46603429 | W121: 0
B122: C | C122: 6.5095606e+09 | D122: 6.0304329e+08 | E122: 2.1647004e+11 | F122: 3.1425436e+09 | G122: 1.8410711e+10 | H122: 9.9361438e+08 | I122: 6.4452638e+08 | J122: 41834799 | K122: 2.574454e+09 | L122: 3.1564507e+10 | M122: 1.4550789e+10 | N122: 4.5768501e+09 | O122: 1.5937156e+10 | P122: 1.1850749e+10 | Q122: 2.1171921e+09 | R122: 2.243763e+09 | S122: 1.7738761e+10 | T122: 1.3821136e+09 | U122: 6.1377998e+08 | V122: 6.4825126e+09 | W122: 0
B123: C19 | C123: 1.1640526e+09 | D123: 1.4545235e+08 | E123: 7.4208727e+09 | F123: 5.3355222e+09 | G123: 1.3523607e+08 | H123: 2.0822667e+09 | I123: 87338732 | J123: 1689841.7 | K123: 8.1301349e+08 | L123: 1.72381e+09 | M123: 1.0568897e+09 | N123: 6.6603517e+09 | O123: 67342669 | P123: 1.3027458e+08 | Q123: 42491598 | R123: 7554530.4 | S123: 8.9546934e+08 | T123: 2.9182489e+08 | U123: 8763831.7 | V123: 88512836 | W123: 0
B124: C29 | C124: 77629951 | D124: 53184529 | E124: 4.4791573e+09 | F124: 1.0777603e+08 | G124: 4.1706115e+09 | H124: 77708529 | I124: 48962017 | J124: 2008434.8 | K124: 1.9201719e+08 | L124: 9.6528488e+08 | M124: 2.157974e+09 | N124: 1.6525723e+09 | O124: 1.8219839e+08 | P124: 7.2019641e+08 | Q124: 1.2912213e+08 | R124: 2.0222698e+08 | S124: 1.7012759e+09 | T124: 1.4248816e+08 | U124: 43693458 | V124: 1.826777e+08 | W124: 0
B125: D1 | C125: 8.6387734e+08 | D125: 1.4816465e+08 | E125: 1.3742541e+10 | F125: 1.0103602e+09 | G125: 5.6850141e+08 | H125: 2.1264569e+10 | I125: 22518234 | J125: 803628.34 | K125: 8.6449185e+08 | L125: 6.765719e+08 | M125: 3.6449472e+09 | N125: 1.1180607e+09 | O125: 1.4022285e+09 | P125: 1.6756173e+09 | Q125: 4.5806432e+08 | R125: 1.1647216e+08 | S125: 2.2914413e+09 | T125: 1.6449354e+09 | U125: 3.2543512e+08 | V125: 8.5446833e+08 | W125: 0
B126: D2 | C126: 37403067 | D126: 44753760 | E126: 2.1749327e+09 | F126: 64588125 | G126: 7337732.8 | H126: 5.1896782e+09 | I126: 2597794.3 | J126: 12750879 | K126: 2.1372297e+08 | L126: 2.1751221e+08 | M126: 1.9088117e+08 | N126: 97034028 | O126: 3.9248729e+08 | P126: 4.4972683e+08 | Q126: 1.3656389e+08 | R126: 31371275 | S126: 4.1632797e+08 | T126: 5.1122793e+08 | U126: 1.095457e+08 | V126: 3.1367645e+08 | W126: 0
B127: D3 | C127: 1304811.9 | D127: 264863.85 | E127: 23655157 | F127: 38539.013 | G127: 3232973.9 | H127: 1999746.9 | I127: 4805661.9 | J127: 171459.24 | K127: 343977.78 | L127: 31589410 | M127: 5727782.4 | N127: 1770421.5 | O127: 653756.31 | P127: 4559343.8 | Q127: 1741651.6 | R127: 108222.32 | S127: 3446550.2 | T127: 1700852.4 | U127: 878723.53 | V127: 898434.28 | W127: 0
B128: E | C128: 3.9184643e+08 | D128: 2.3886668e+08 | E128: 9.9279489e+09 | F128: 1.8735397e+08 | G128: 4.7072988e+08 | H128: 9.1918018e+08 | I128: 6.616271e+08 | J128: 6089328.9 | K128: 8.2868157e+09 | L128: 9.2140709e+08 | M128: 9.5827299e+08 | N128: 5.1826156e+08 | O128: 3.0436505e+08 | P128: 1.5738159e+09 | Q128: 1.7550785e+08 | R128: 1.2268026e+08 | S128: 1.1339616e+09 | T128: 3.2154926e+08 | U128: 78564015 | V128: 4.3063956e+08 | W128: 0
B129: F | C129: 5.8818401e+08 | D129: 55322503 | E129: 5.0277013e+09 | F129: 3.6168867e+08 | G129: 7.2259406e+08 | H129: 4.8824411e+08 | I129: 27683978 | J129: 953390.81 | K129: 4.2402031e+08 | L129: 7.3338389e+10 | M129: 2.5625008e+09 | N129: 1.3611686e+09 | O129: 7.2585947e+08 | P129: 2.2056425e+09 | Q129: 6.6400209e+08 | R129: 1.7166855e+09 | S129: 3.8118648e+09 | T129: 2.6264771e+09 | U129: 4.5994707e+08 | V129: 1.9183485e+09 | W129: 0
B130: G | C130: 1.5914693e+09 | D130: 2.2796994e+08 | E130: 4.4884881e+10 | F130: 3.4566345e+09 | G130: 5.2731583e+09 | H130: 1.7063275e+09 | I130: 1.1545634e+09 | J130: 1.267037e+08 | K130: 1.8182601e+09 | L130: 6.0100122e+09 | M130: 1.5217229e+10 | N130: 4.4589645e+09 | O130: 3.1996652e+09 | P130: 5.5830736e+09 | Q130: 1.6991929e+09 | R130: 7.7161326e+08 | S130: 1.1756906e+10 | T130: 7.2326059e+08 | U130: 2.6755807e+08 | V130: 2.8551508e+09 | W130: 0
B131: H | C131: 8.7233067e+08 | D131: 2.8042051e+08 | E131: 1.9611247e+10 | F131: 1.5625693e+09 | G131: 1.3269467e+09 | H131: 1.0601297e+09 | I131: 1.9813869e+09 | J131: 19190693 | K131: 6.6782681e+08 | L131: 2.7624923e+09 | M131: 1.0356742e+10 | N131: 7.8972209e+09 | O131: 8.9684546e+08 | P131: 1.8462206e+09 | Q131: 7.3021629e+08 | R131: 1.7078499e+08 | S131: 9.6028063e+09 | T131: 1.4169638e+09 | U131: 2.9953479e+08 | V131: 6.5411157e+08 | W131: 0
... B140: T | C140: 0 | D140: 0 | E140: 0 | F140: 0 | G140: 0 | H140: 0 | I140: 0 | J140: 0 | K140: 0 | L140: 0 | M140: 0 | N140: 0 | O140: 0 | P140: 0 | Q140: 0 | R140: 0 | S140: 0 | T140: 0 | U140: 0 | V140: 0 | W140: 0
D141: I Matrix
C142: A | D142: B | E142: C | F142: C19 | G142: C29 | H142: D1 | I142: D2 | J142: D3 | K142: E | L142: F | M142: G | N142: H | O142: I | P142: J_R_S | Q142: K | R142: L | S142: H_M_N | T142: O | U142: P | V142: Q | W142: T
B143: A | C143: {=_xlfn.MUNIT(21)} -> 1 | D143: 0 | E143: 0 | F143: 0 | G143: 0 | H143: 0 | I143: 0 | J143: 0 | K143: 0 | L143: 0 | M143: 0 | N143: 0 | O143: 0 | P143: 0 | Q143: 0 | R143: 0 | S143: 0 | T143: 0 | U143: 0 | V143: 0 | W143: 0
B144: B | C144: 0 | D144: 1 | E144: 0 | F144: 0 | G144: 0 | H144: 0 | I144: 0 | J144: 0 | K144: 0 | L144: 0 | M144: 0 | N144: 0 | O144: 0 | P144: 0 | Q144: 0 | R144: 0 | S144: 0 | T144: 0 | U144: 0 | V144: 0 | W144: 0
B145: C | C145: 0 | D145: 0 | E145: 1 | F145: 0 | G145: 0 | H145: 0 | I145: 0 | J145: 0 | K145: 0 | L145: 0 | M145: 0 | N145: 0 | O145: 0 | P145: 0 | Q145: 0 | R145: 0 | S145: 0 | T145: 0 | U145: 0 | V145: 0 | W145: 0
B146: C19 | C146: 0 | D146: 0 | E146: 0 | F146: 1 | G146: 0 | H146: 0 | I146: 0 | J146: 0 | K146: 0 | L146: 0 | M146: 0 | N146: 0 | O146: 0 | P146: 0 | Q146: 0 | R146: 0 | S146: 0 | T146: 0 | U146: 0 | V146: 0 | W146: 0
B147: C29 | C147: 0 | D147: 0 | E147: 0 | F147: 0 | G147: 1 | H147: 0 | I147: 0 | J147: 0 | K147: 0 | L147: 0 | M147: 0 | N147: 0 | O147: 0 | P147: 0 | Q147: 0 | R147: 0 | S147: 0 | T147: 0 | U147: 0 | V147: 0 | W147: 0
B148: D1 | C148: 0 | D148: 0 | E148: 0 | F148: 0 | G148: 0 | H148: 1 | I148: 0 | J148: 0 | K148: 0 | L148: 0 | M148: 0 | N148: 0 | O148: 0 | P148: 0 | Q148: 0 | R148: 0 | S148: 0 | T148: 0 | U148: 0 | V148: 0 | W148: 0
B149: D2 | C149: 0 | D149: 0 | E149: 0 | F149: 0 | G149: 0 | H149: 0 | I149: 1 | J149: 0 | K149: 0 | L149: 0 | M149: 0 | N149: 0 | O149: 0 | P149: 0 | Q149: 0 | R149: 0 | S149: 0 | T149: 0 | U149: 0 | V149: 0 | W149: 0
B150: D3 | C150: 0 | D150: 0 | E150: 0 | F150: 0 | G150: 0 | H150: 0 | I150: 0 | J150: 1 | K150: 0 | L150: 0 | M150: 0 | N150: 0 | O150: 0 | P150: 0 | Q150: 0 | R150: 0 | S150: 0 | T150: 0 | U150: 0 | V150: 0 | W150: 0
...

Sheet internationaltrade
A1: Z imp | C1: A1 | D1: A2 | E1: A3 | F1: B | G1: C10_12 | H1: C13_15 | I1: C16_17 | J1: C20_22 | K1: C19 | L1: C23 | M1: C24_33 | N1: C26_27 | O1: C31_32 | P1: D | Q1: E | R1: F | S1: G | T1: H | U1: I | V1: J | W1: K | X1: L | Y1: M_N | Z1: M_N_72 | AA1: M_N_73 | AB1: O | AC1: P | AD1: Q | AE1: R | AF1: S95 | AG1: ST
B2: A1 | C2: 69670000 | D2: 0 | E2: 0 | F2: 0 | G2: 277890000 | H2: 70000 | I2: 140000 | J2: 63260000 | K2: 0 | L2: 0 | M2: 0 | N2: 0 | O2: 220000 | P2: 0 | Q2: 0 | R2: 20000 | S2: 0 | T2: 0 | U2: 34580000 | V2: 0 | W2: 0 | X2: 0 | Y2: 830000 | Z2: 0 | AA2: 0 | AB2: 7320000 | AC2: 3020000 | AD2: 6370000 | AE2: 750000 | AF2: 0 | AG2: 110000
B3: A2 | C3: 130000 | D3: 3040000 | E3: 0 | F3: 0 | G3: 4630000 | H3: 0 | I3: 332020000 | J3: 0 | K3: 0 | L3: 0 | M3: 5460000 | N3: 0 | O3: 20000 | P3: 19230000 | Q3: 0 | R3: 180000 | S3: 180000 | T3: 0 | U3: 0 | V3: 0 | W3: 0 | X3: 230000 | Y3: 30000 | Z3: 0 | AA3: 0 | AB3: 300000 | AC3: 120000 | AD3: 270000 | AE3: 30000 | AF3: 0 | AG3: 0
B4: A3 | C4: 140000 | D4: 120000 | E4: 510000 | F4: 0 | G4: 33200000 | H4: 0 | I4: 0 | J4: 0 | K4: 0 | L4: 0 | M4: 0 | N4: 0 | O4: 0 | P4: 200000 | Q4: 150000 | R4: 930000 | S4: 1150000 | T4: 3190000 | U4: 44420000 | V4: 1660000 | W4: 730000 | X4: 1000000 | Y4: 3020000 | Z4: 80000 | AA4: 480000 | AB4: 3160000 | AC4: 1200000 | AD4: 2630000 | AE4: 620000 | AF4: 0 | AG4: 1020000
B5: B | C5: 780000 | D5: 0 | E5: 0 | F5: 9860000 | G5: 7930000 | H5: 410000 | I5: 139800000 | J5: 135740000 | K5: 4831730000 | L5: 48500000 | M5: 9.1365e+08 | N5: 40000 | O5: 270000 | P5: 1153250000 | Q5: 280000 | R5: 16030000 | S5: 16030000 | T5: 0 | U5: 0 | V5: 0 | W5: 0 | X5: 0 | Y5: 10000 | Z5: 0 | AA5: 0 | AB5: 20000 | AC5: 10000 | AD5: 0 | AE5: 0 | AF5: 0 | AG5: 0
B6: C10_12 | C6: 40500000 | D6: 1610000 | E6: 10000 | F6: 0 | G6: 521500000 | H6: 1180000 | I6: 37510000 | J6: 214400000 | K6: 51410000 | L6: 330000 | M6: 0 | N6: 0 | O6: 20000 | P6: 5710000 | Q6: 1560000 | R6: 10090000 | S6: 12470000 | T6: 33400000 | U6: 225660000 | V6: 19320000 | W6: 7400000 | X6: 12160000 | Y6: 38050000 | Z6: 970000 | AA6: 5570000 | AB6: 91820000 | AC6: 28880000 | AD6: 60890000 | AE6: 10600000 | AF6: 300000 | AG6: 13230000
B7: C13_15 | C7: 360000 | D7: 360000 | E7: 0 | F7: 670000 | G7: 4530000 | H7: 301590000 | I7: 30410000 | J7: 14710000 | K7: 0 | L7: 17880000 | M7: 28310000 | N7: 6600000 | O7: 24460000 | P7: 1480000 | Q7: 14630000 | R7: 25100000 | S7: 41030000 | T7: 20950000 | U7: 4020000 | V7: 12260000 | W7: 6230000 | X7: 2800000 | Y7: 53860000 | Z7: 990000 | AA7: 5900000 | AB7: 49740000 | AC7: 1220000 | AD7: 39550000 | AE7: 1120000 | AF7: 4690000 | AG7: 8920000
B8: C16_17 | C8: 640000 | D8: 1350000 | E8: 0 | F8: 300000 | G8: 70220000 | H8: 1500000 | I8: 536480000 | J8: 27600000 | K8: 210000 | L8: 11290000 | M8: 14740000 | N8: 4000000 | O8: 45400000 | P8: 4150000 | Q8: 2140000 | R8: 290730000 | S8: 301490000 | T8: 8020000 | U8: 1240000 | V8: 20840000 | W8: 7730000 | X8: 7180000 | Y8: 47620000 | Z8: 3290000 | AA8: 3410000 | AB8: 40490000 | AC8: 36480000 | AD8: 29030000 | AE8: 10520000 | AF8: 1500000 | AG8: 13600000
B9: C20_22 | C9: 182720000 | D9: 34840000 | E9: 0 | F9: 42080000 | G9: 288310000 | H9: 80530000 | I9: 718720000 | J9: 1399530000 | K9: 68090000 | L9: 80480000 | M9: 239290000 | N9: 1.0835e+08 | O9: 51540000 | P9: 278510000 | Q9: 77100000 | R9: 479580000 | S9: 549260000 | T9: 1.5765e+08 | U9: 1050000 | V9: 9660000 | W9: 3030000 | X9: 2260000 | Y9: 143110000 | Z9: 420000 | AA9: 11720000 | AB9: 60330000 | AC9: 38700000 | AD9: 6.3355e+08 | AE9: 18300000 | AF9: 2060000 | AG9: 41520000
B10: C19 | C10: 62060000 | D10: 37270000 | E10: 530000 | F10: 21130000 | G10: 3100000 | H10: 280000 | I10: 20180000 | J10: 3.1455e+08 | K10: 699640000 | L10: 28720000 | M10: 144610000 | N10: 5410000 | O10: 5110000 | P10: 150950000 | Q10: 7000000 | R10: 119560000 | S10: 137120000 | T10: 509220000 | U10: 2230000 | V10: 3540000 | W10: 6760000 | X10: 1.781e+08 | Y10: 22810000 | Z10: 1380000 | AA10: 20000 | AB10: 48650000 | AC10: 13250000 | AD10: 14000000 | AE10: 4770000 | AF10: 280000 | AG10: 5870000
B11: C23 | C11: 750000 | D11: 0 | E11: 0 | F11: 6170000 | G11: 19380000 | H11: 660000 | I11: 33520000 | J11: 21730000 | K11: 0 | L11: 103690000 | M11: 64620000 | N11: 12510000 | O11: 9830000 | P11: 380000 | Q11: 440000 | R11: 224470000 | S11: 250990000 | T11: 30000 | U11: 60000 | V11: 1290000 | W11: 720000 | X11: 20000 | Y11: 4060000 | Z11: 80000 | AA11: 720000 | AB11: 50000 | AC11: 190000 | AD11: 10060000 | AE11: 60000 | AF11: 190000 | AG11: 1390000
B12: C24_33 | C12: 57650000 | D12: 6250000 | E12: 150000 | F12: 27250000 | G12: 91720000 | H12: 530000 | I12: 46290000 | J12: 35610000 | K12: 3990000 | L12: 30830000 | M12: 3661330000 | N12: 1.1701e+08 | O12: 23730000 | P12: 1600000 | Q12: 52100000 | R12: 898520000 | S12: 1130520000 | T12: 3.795e+08 | U12: 960000 | V12: 65860000 | W12: 2540000 | X12: 510000 | Y12: 34210000 | Z12: 1690000 | AA12: 1780000 | AB12: 85910000 | AC12: 14640000 | AD12: 320000 | AE12: 1490000 | AF12: 4570000 | AG12: 2340000
B13: C26_27 | C13: 110000 | D13: 110000 | E13: 0 | F13: 0 | G13: 0 | H13: 50000 | I13: 2000000 | J13: 10910000 | K13: 0 | L13: 7400000 | M13: 622000000 | N13: 2912060000 | O13: 16330000 | P13: 610000 | Q13: 14720000 | R13: 4.5241e+08 | S13: 5.2317e+08 | T13: 28290000 | U13: 230000 | V13: 166940000 | W13: 1.7841e+08 | X13: 1880000 | Y13: 484410000 | Z13: 16370000 | AA13: 58620000 | AB13: 73280000 | AC13: 54260000 | AD13: 1.3147e+08 | AE13: 33880000 | AF13: 28220000 | AG13: 13170000
... B32: ST | C32: 0 | D32: 0 | E32: 0 | F32: 0 | G32: 0 | H32: 0 | I32: 0 | J32: 0 | K32: 0 | L32: 0 | M32: 0 | N32: 0 | O32: 0 | P32: 0 | Q32: 0 | R32: 0 | S32: 0 | T32: 0 | U32: 0 | V32: 0 | W32: 0 | X32: 0 | Y32: 0 | Z32: 0 | AA32: 0 | AB32: 0 | AC32: 0 | AD32: 0 | AE32: 0 | AF32: 0 | AG32: 0
C35: A1 | D35: A2 | E35: A3 | F35: B | G35: C10_12 | H35: C13_15 | I35: C16_17 | J35: C18 | K35: C20_22 | L35: C19 | M35: C23 | N35: C24_33 | O35: C26_27 | P35: C31_32 | Q35: D | R35: E | S35: F | T35: G | U35: H | V35: I | W35: J | X35: K | Y35: L | Z35: M_N | AA35: M_N_72 | AB35: M_N_73 | AC35: O | AD35: P | AE35: Q | AF35: R | AG35: S95 | AH35: ST | AI35: TOT
B36: EXP | C36: 4.74186e+08 | D36: 44825000 | E36: 17441000 | F36: 383252000 | G36: 1408114000 | H36: 607495000 | I36: 10980171000 | K36: 5.747783e+09 | L36: 3620733000 | M36: 6.34111e+08 | N36: 1.8500951e+10 | O36: 14182868000 | P36: 503411000 | Q36: 604495000 | R36: 2.73761e+08 | S36: 9332000 | T36: 1.293011e+09 | U36: 3.640756e+09 | V36: 184691000 | W36: 2.715785e+09 | X36: 6.3953e+08 | Y36: 55794000 | Z36: 1.662096e+09 | AA36: 3.88556e+08 | AB36: 104808000 | AC36: 99863000 | AD36: 8384000 | AE36: 19632000 | AF36: 27409000 | AG36: 15164000 | AH36: 1012000 | AI36: =SUM(C36:AH36) -> 6.884942e+10
B37: IMP | C37: 441478000 | D37: 102246000 | E37: 2301000 | F37: 145696000 | G37: 1576951000 | H37: 414921000 | I37: 2274141000 | J37: 170619000 | K37: 2546616000 | L37: 5683876000 | M37: 431667000 | N37: 10135073000 | O37: 8420656000 | P37: 375993000 | Q37: 1789351000 | R37: 344422000 | S37: 2945274000 | T37: 2938949000 | U37: 2265872000 | V37: 465146000 | W37: 1339850000 | X37: 634249000 | Y37: 299403000 | Z37: 1546505000 | AA37: 84090000 | AB37: 143733000 | AC37: 949775000 | AD37: 352203000 | AE37: 1181898000 | AF37: 245256000 | AG37: 52272000 | AH37: 230171000 | AI37: =SUM(C37:AH37) -> 50530653000 | AJ37: (with ind 18)
J38: Note additiona industry
A40: Final demand shares (elementwise ratio between f_imp and f_tot)
B41: Sector | C41: f_HH_imp/f_HH_tot | D41: f_gov_imp/f_gov_tot | E41: f_gfcf_imp/f_gfcf_tot | G41: f_hh_tot | J41: HH IMP | K41: GOV IMP | L41: GFCF IMP | O41: EXP | T41: P3/S14 Final consumption expenditure by households on imports in 2010 (total)
A42: A1 | B42: 1 | C42: =J42/inputoutput!#REF! -> #REF! | D42: =K42/inputoutput!#REF! -> #REF! | E42: =L42/inputoutput!#REF! -> #REF! | G42: =J42/C42 -> #REF! | J42: 146524000 | K42: 4000 | L42: 66000 | N42: A1 | O42: 4.74186e+08 | T42: 11213615000
A43: A2 | B43: 2 | C43: =J43/inputoutput!#REF! -> #REF! | D43: =K43/inputoutput!#REF! -> #REF! | E43: =L43/inputoutput!#REF! -> #REF! | G43: =J43/C43 -> #REF! | J43: 645000 | K43: 0 | L43: 52000 | N43: A2 | O43: 44825000
A44: A3 | B44: 3 | C44: =J44/inputoutput!#REF! -> #REF! | D44: =K44/inputoutput!#REF! -> #REF! | E44: =L44/inputoutput!#REF! -> #REF! | G44: =J44/C44 -> #REF! | J44: 419000 | K44: 0 | L44: 0 | N44: A3 | O44: 17441000
A45: B | B45: 4 | C45: =J45/inputoutput!#REF! -> #REF! | D45: =K45/inputoutput!#REF! -> #REF! | E45: =L45/inputoutput!#REF! -> #REF! | G45: =J45/C45 -> #REF! | J45: 32000 | K45: 0 | L45: 11000 | N45: B | O45: 383252000
A46: C10_12 | B46: 5 | C46: =J46/inputoutput!#REF! -> #REF! | D46: =K46/inputoutput!#REF! -> #REF! | E46: =L46/inputoutput!#REF! -> #REF! | G46: =J46/C46 -> #REF! | J46: 293426000 | K46: 69000 | L46: 115000 | N46: C10_12 | O46: 1408114000
A47: C13_15 | B47: 6 | C47: =J47/inputoutput!#REF! -> #REF! | D47: =K47/inputoutput!#REF! -> #REF! | E47: =L47/inputoutput!#REF! -> #REF! | G47: =J47/C47 -> #REF! | J47: 127857000 | K47: 12000 | L47: 215000 | N47: C13_15 | O47: 607495000
A48: C16_17 | B48: 7 | C48: =J48/inputoutput!#REF! -> #REF! | D48: =K48/inputoutput!#REF! -> #REF! | E48: =L48/inputoutput!#REF! -> #REF! | G48: =J48/C48 -> #REF! | J48: 7155000 | K48: 9000 | L48: 480000 | N48: C16_17 | O48: 10980171000
A49: C20_22 | B49: 8 | C49: =J49/inputoutput!#REF! -> #REF! | D49: =K49/inputoutput!#REF! -> #REF! | E49: =L49/inputoutput!#REF! -> #REF! | G49: =J49/C49 -> #REF! | J49: 48325000 | K49: 20296000 | L49: 1237000 | N49: C20_22 | O49: 5.747783e+09
A50: C19 | B50: 9 | C50: =J50/inputoutput!#REF! -> #REF! | D50: =K50/inputoutput!#REF! -> #REF! | E50: =L50/inputoutput!#REF! -> #REF! | G50: =J50/C50 -> #REF! | J50: 9405000 | K50: 35000 | L50: 25000 | N50: C19 | O50: 3620733000
A51: C23 | B51: 10 | C51: =J51/inputoutput!#REF! -> #REF! | D51: =K51/inputoutput!#REF! -> #REF! | E51: =L51/inputoutput!#REF! -> #REF! | G51: =J51/C51 -> #REF! | J51: 3115000 | K51: 6000 | L51: 89000 | N51: C23 | O51: 6.34111e+08
A52: C24_33 | B52: 11 | C52: =J52/inputoutput!#REF! -> #REF! | D52: =K52/inputoutput!#REF! -> #REF! | E52: =L52/inputoutput!#REF! -> #REF! | G52: =J52/C52 -> #REF! | J52: 53422000 | K52: 44000 | L52: 50818000 | N52: C24_33 | O52: 1.8500951e+10
A53: C26_27 | B53: 12 | C53: =J53/inputoutput!#REF! -> #REF! | D53: =K53/inputoutput!#REF! -> #REF! | E53: =L53/inputoutput!#REF! -> #REF! | G53: =J53/C53 -> #REF! | J53: 22842000 | K53: 3000 | L53: 7490000 | N53: C26_27 | O53: 14182868000
A54: C31_32 | B54: 13 | C54: =J54/inputoutput!#REF! -> #REF! | D54: =K54/inputoutput!#REF! -> #REF! | E54: =L54/inputoutput!#REF! -> #REF! | G54: =J54/C54 -> #REF! | J54: 54821000 | K54: 37000 | L54: 8606000 | N54: C31_32 | O54: 503411000
... A72: ST | B72: 31 | C72: =J72/inputoutput!#REF! -> #REF! | D72: =K72/inputoutput!#REF! -> #REF! | E72: =L72/inputoutput!#REF! -> #REF! | G72: =J72/C72 -> #REF! | J72: 3329000 | K72: 84000 | L72: 224000 | N72: ST | O72: 1012000
I73: TOT | J73: =SUM(J42:J72) -> 1549250000 | K73: =SUM(K42:K72) -> 27182000 | L73: =SUM(L42:L72) -> 179429000 | N73: TOT | O73: =SUM(O42:O72) -> 6.884942e+10 | P73: TOT
A75: Intermediate trade ratios (elementwise ratio between Z_imp and Z_dom)
B76: A1 | C76: A2 | D76: A3 | E76: B | F76: C10_12 | G76: C13_15 | H76: C16_17 | I76: C20_22 | J76: C19 | K76: C23 | L76: C24_33 | M76: C26_27 | N76: C31_32 | O76: D | P76: E | Q76: F | R76: G | S76: H | T76: I | U76: J | V76: K | W76: L | X76: M_N | Y76: M_N_72 | Z76: M_N_73 | AA76: O | AB76: P | AC76: Q | AD76: R | AE76: S95 | AF76: ST
A77: A1 | B77: =IF(inputoutput!C14=0, 0, C2/inputoutput!C14) -> #VALUE! | C77: =IF(inputoutput!D14=0, 0, D2/inputoutput!D14) -> 0 | D77: =IF(inputoutput!E14=0, 0, E2/inputoutput!E14) -> 0 | E77: =IF(inputoutput!F14=0, 0, F2/inputoutput!F14) -> 0 | F77: =IF(inputoutput!G14=0, 0, G2/inputoutput!G14) -> 0.031157318 | G77: =IF(inputoutput!H14=0, 0, H2/inputoutput!H14) -> 0 | H77: =IF(inputoutput!I14=0, 0, I2/inputoutput!I14) -> 0 | I77: =IF(inputoutput!J14=0, 0, J2/inputoutput!J14) -> 0 | ... V77: =IF(inputoutput!W14=0, 0, W2/inputoutput!W14) -> 0 | W77: =IF(inputoutput!#REF!=0, 0, X2/inputoutput!#REF!) -> #REF! | X77: =IF(inputoutput!#REF!=0, 0, Y2/inputoutput!#REF!) -> #REF! | Y77: =IF(inputoutput!#REF!=0, 0, Z2/inputoutput!#REF!) -> #REF! | Z77: =IF(inputoutput!#REF!=0, 0, AA2/inputoutput!#REF!) -> #REF! | AA77: =IF(inputoutput!#REF!=0, 0, AB2/inputoutput!#REF!) -> #REF! | AB77: =IF(inputoutput!#REF!=0, 0, AC2/inputoutput!#REF!) -> #REF! | AC77: =IF(inputoutput!#REF!=0, 0, AD2/inputoutput!#REF!) -> #REF! | AD77: =IF(inputoutput!#REF!=0, 0, AE2/inputoutput!#REF!) -> #REF! | ... AF77: =IF(inputoutput!#REF!=0, 0, AG2/inputoutput!#REF!) -> #REF!
A78: A2 | B78: =IF(inputoutput!C15=0, 0, C3/inputoutput!C15) -> #VALUE! | C78: =IF(inputoutput!D15=0, 0, D3/inputoutput!D15) -> 3.9105902e-05 | D78: =IF(inputoutput!E15=0, 0, E3/inputoutput!E15) -> 0 | E78: =IF(inputoutput!F15=0, 0, F3/inputoutput!F15) -> 0 | F78: =IF(inputoutput!G15=0, 0, G3/inputoutput!G15) -> 0.09816995 | G78: =IF(inputoutput!H15=0, 0, H3/inputoutput!H15) -> 0 | H78: =IF(inputoutput!I15=0, 0, I3/inputoutput!I15) -> 0 | I78: =IF(inputoutput!J15=0, 0, J3/inputoutput!J15) -> 0 | ... V78: =IF(inputoutput!W15=0, 0, W3/inputoutput!W15) -> 0 | W78: =IF(inputoutput!#REF!=0, 0, X3/inputoutput!#REF!) -> #REF! | X78: =IF(inputoutput!#REF!=0, 0, Y3/inputoutput!#REF!) -> #REF! | Y78: =IF(inputoutput!#REF!=0, 0, Z3/inputoutput!#REF!) -> #REF! | Z78: =IF(inputoutput!#REF!=0, 0, AA3/inputoutput!#REF!) -> #REF! | AA78: =IF(inputoutput!#REF!=0, 0, AB3/inputoutput!#REF!) -> #REF! | AB78: =IF(inputoutput!#REF!=0, 0, AC3/inputoutput!#REF!) -> #REF! | AC78: =IF(inputoutput!#REF!=0, 0, AD3/inputoutput!#REF!) -> #REF! | AD78: =IF(inputoutput!#REF!=0, 0, AE3/inputoutput!#REF!) -> #REF! | ... AF78: =IF(inputoutput!#REF!=0, 0, AG3/inputoutput!#REF!) -> #REF!
A79: A3 | B79: =IF(inputoutput!C16=0, 0, C4/inputoutput!C16) -> #VALUE! | C79: =IF(inputoutput!D16=0, 0, D4/inputoutput!D16) -> 1.6047376e-06 | D79: =IF(inputoutput!E16=0, 0, E4/inputoutput!E16) -> 7.1362215e-05 | E79: =IF(inputoutput!F16=0, 0, F4/inputoutput!F16) -> 0 | F79: =IF(inputoutput!G16=0, 0, G4/inputoutput!G16) -> 0.0032180089 | G79: =IF(inputoutput!H16=0, 0, H4/inputoutput!H16) -> 0 | H79: =IF(inputoutput!I16=0, 0, I4/inputoutput!I16) -> 0 | I79: =IF(inputoutput!J16=0, 0, J4/inputoutput!J16) -> 0 | ... V79: =IF(inputoutput!W16=0, 0, W4/inputoutput!W16) -> 0 | W79: =IF(inputoutput!#REF!=0, 0, X4/inputoutput!#REF!) -> #REF! | X79: =IF(inputoutput!#REF!=0, 0, Y4/inputoutput!#REF!) -> #REF! | Y79: =IF(inputoutput!#REF!=0, 0, Z4/inputoutput!#REF!) -> #REF! | Z79: =IF(inputoutput!#REF!=0, 0, AA4/inputoutput!#REF!) -> #REF! | AA79: =IF(inputoutput!#REF!=0, 0, AB4/inputoutput!#REF!) -> #REF! | AB79: =IF(inputoutput!#REF!=0, 0, AC4/inputoutput!#REF!) -> #REF! | AC79: =IF(inputoutput!#REF!=0, 0, AD4/inputoutput!#REF!) -> #REF! | AD79: =IF(inputoutput!#REF!=0, 0, AE4/inputoutput!#REF!) -> #REF! | ... AF79: =IF(inputoutput!#REF!=0, 0, AG4/inputoutput!#REF!) -> #REF!
A80: B | B80: =IF(inputoutput!C17=0, 0, C5/inputoutput!C17) -> #VALUE! | C80: =IF(inputoutput!D17=0, 0, D5/inputoutput!D17) -> 0 | D80: =IF(inputoutput!E17=0, 0, E5/inputoutput!E17) -> 0 | E80: =IF(inputoutput!F17=0, 0, F5/inputoutput!F17) -> 0.010124819 | F80: =IF(inputoutput!G17=0, 0, G5/inputoutput!G17) -> 0.0017949711 | G80: =IF(inputoutput!H17=0, 0, H5/inputoutput!H17) -> 0 | H80: =IF(inputoutput!I17=0, 0, I5/inputoutput!I17) -> 0 | I80: =IF(inputoutput!J17=0, 0, J5/inputoutput!J17) -> 0 | ... V80: =IF(inputoutput!W17=0, 0, W5/inputoutput!W17) -> 0 | W80: =IF(inputoutput!#REF!=0, 0, X5/inputoutput!#REF!) -> #REF! | X80: =IF(inputoutput!#REF!=0, 0, Y5/inputoutput!#REF!) -> #REF! | Y80: =IF(inputoutput!#REF!=0, 0, Z5/inputoutput!#REF!) -> #REF! | Z80: =IF(inputoutput!#REF!=0, 0, AA5/inputoutput!#REF!) -> #REF! | AA80: =IF(inputoutput!#REF!=0, 0, AB5/inputoutput!#REF!) -> #REF! | AB80: =IF(inputoutput!#REF!=0, 0, AC5/inputoutput!#REF!) -> #REF! | AC80: =IF(inputoutput!#REF!=0, 0, AD5/inputoutput!#REF!) -> #REF! | AD80: =IF(inputoutput!#REF!=0, 0, AE5/inputoutput!#REF!) -> #REF! | ... AF80: =IF(inputoutput!#REF!=0, 0, AG5/inputoutput!#REF!) -> #REF!
A81: C10_12 | B81: =IF(inputoutput!C18=0, 0, C6/inputoutput!C18) -> #VALUE! | C81: =IF(inputoutput!D18=0, 0, D6/inputoutput!D18) -> 1.0733315e-05 | D81: =IF(inputoutput!E18=0, 0, E6/inputoutput!E18) -> 6.7674266e-06 | E81: =IF(inputoutput!F18=0, 0, F6/inputoutput!F18) -> 0 | F81: =IF(inputoutput!G18=0, 0, G6/inputoutput!G18) -> 0.35093843 | G81: =IF(inputoutput!H18=0, 0, H6/inputoutput!H18) -> 0 | H81: =IF(inputoutput!I18=0, 0, I6/inputoutput!I18) -> 0 | I81: =IF(inputoutput!J18=0, 0, J6/inputoutput!J18) -> 0 | ... V81: =IF(inputoutput!W18=0, 0, W6/inputoutput!W18) -> 0 | W81: =IF(inputoutput!#REF!=0, 0, X6/inputoutput!#REF!) -> #REF! | X81: =IF(inputoutput!#REF!=0, 0, Y6/inputoutput!#REF!) -> #REF! | Y81: =IF(inputoutput!#REF!=0, 0, Z6/inputoutput!#REF!) -> #REF! | Z81: =IF(inputoutput!#REF!=0, 0, AA6/inputoutput!#REF!) -> #REF! | AA81: =IF(inputoutput!#REF!=0, 0, AB6/inputoutput!#REF!) -> #REF! | AB81: =IF(inputoutput!#REF!=0, 0, AC6/inputoutput!#REF!) -> #REF! | AC81: =IF(inputoutput!#REF!=0, 0, AD6/inputoutput!#REF!) -> #REF! | AD81: =IF(inputoutput!#REF!=0, 0, AE6/inputoutput!#REF!) -> #REF! | ... AF81: =IF(inputoutput!#REF!=0, 0, AG6/inputoutput!#REF!) -> #REF!
A82: C13_15 | B82: =IF(inputoutput!C19=0, 0, C7/inputoutput!C19) -> #VALUE! | C82: =IF(inputoutput!D19=0, 0, D7/inputoutput!D19) -> 1.5377621e-05 | D82: =IF(inputoutput!E19=0, 0, E7/inputoutput!E19) -> 0 | E82: =IF(inputoutput!F19=0, 0, F7/inputoutput!F19) -> 4.9332796e-05 | F82: =IF(inputoutput!G19=0, 0, G7/inputoutput!G19) -> 0.00022952447 | G82: =IF(inputoutput!H19=0, 0, H7/inputoutput!H19) -> 0 | H82: =IF(inputoutput!I19=0, 0, I7/inputoutput!I19) -> 0 | I82: =IF(inputoutput!J19=0, 0, J7/inputoutput!J19) -> 0 | ... V82: =IF(inputoutput!W19=0, 0, W7/inputoutput!W19) -> 0 | W82: =IF(inputoutput!#REF!=0, 0, X7/inputoutput!#REF!) -> #REF! | X82: =IF(inputoutput!#REF!=0, 0, Y7/inputoutput!#REF!) -> #REF! | Y82: =IF(inputoutput!#REF!=0, 0, Z7/inputoutput!#REF!) -> #REF! | Z82: =IF(inputoutput!#REF!=0, 0, AA7/inputoutput!#REF!) -> #REF! | AA82: =IF(inputoutput!#REF!=0, 0, AB7/inputoutput!#REF!) -> #REF! | AB82: =IF(inputoutput!#REF!=0, 0, AC7/inputoutput!#REF!) -> #REF! | AC82: =IF(inputoutput!#REF!=0, 0, AD7/inputoutput!#REF!) -> #REF! | AD82: =IF(inputoutput!#REF!=0, 0, AE7/inputoutput!#REF!) -> #REF! | ... AF82: =IF(inputoutput!#REF!=0, 0, AG7/inputoutput!#REF!) -> #REF!
A83: C16_17 | B83: =IF(inputoutput!C20=0, 0, C8/inputoutput!C20) -> #VALUE! | C83: =IF(inputoutput!D20=0, 0, D8/inputoutput!D20) -> 0.00069086307 | D83: =IF(inputoutput!E20=0, 0, E8/inputoutput!E20) -> 0 | E83: =IF(inputoutput!F20=0, 0, F8/inputoutput!F20) -> 0.0011429346 | F83: =IF(inputoutput!G20=0, 0, G8/inputoutput!G20) -> 0.72484784 | G83: =IF(inputoutput!H20=0, 0, H8/inputoutput!H20) -> 0 | H83: =IF(inputoutput!I20=0, 0, I8/inputoutput!I20) -> 0 | I83: =IF(inputoutput!J20=0, 0, J8/inputoutput!J20) -> 0 | ... V83: =IF(inputoutput!W20=0, 0, W8/inputoutput!W20) -> 0 | W83: =IF(inputoutput!#REF!=0, 0, X8/inputoutput!#REF!) -> #REF! | X83: =IF(inputoutput!#REF!=0, 0, Y8/inputoutput!#REF!) -> #REF! | Y83: =IF(inputoutput!#REF!=0, 0, Z8/inputoutput!#REF!) -> #REF! | Z83: =IF(inputoutput!#REF!=0, 0, AA8/inputoutput!#REF!) -> #REF! | AA83: =IF(inputoutput!#REF!=0, 0, AB8/inputoutput!#REF!) -> #REF! | AB83: =IF(inputoutput!#REF!=0, 0, AC8/inputoutput!#REF!) -> #REF! | AC83: =IF(inputoutput!#REF!=0, 0, AD8/inputoutput!#REF!) -> #REF! | AD83: =IF(inputoutput!#REF!=0, 0, AE8/inputoutput!#REF!) -> #REF! | ... AF83: =IF(inputoutput!#REF!=0, 0, AG8/inputoutput!#REF!) -> #REF!
A84: C20_22 | B84: =IF(inputoutput!C21=0, 0, C9/inputoutput!C21) -> #VALUE! | C84: =IF(inputoutput!D21=0, 0, D9/inputoutput!D21) -> 0.0029133495 | D84: =IF(inputoutput!E21=0, 0, E9/inputoutput!E21) -> 0 | E84: =IF(inputoutput!F21=0, 0, F9/inputoutput!F21) -> 0.58445216 | F84: =IF(inputoutput!G21=0, 0, G9/inputoutput!G21) -> 4.6137472 | G84: =IF(inputoutput!H21=0, 0, H9/inputoutput!H21) -> 0 | H84: =IF(inputoutput!I21=0, 0, I9/inputoutput!I21) -> 0 | I84: =IF(inputoutput!J21=0, 0, J9/inputoutput!J21) -> 0 | ... V84: =IF(inputoutput!W21=0, 0, W9/inputoutput!W21) -> 0 | W84: =IF(inputoutput!#REF!=0, 0, X9/inputoutput!#REF!) -> #REF! | X84: =IF(inputoutput!#REF!=0, 0, Y9/inputoutput!#REF!) -> #REF! | Y84: =IF(inputoutput!#REF!=0, 0, Z9/inputoutput!#REF!) -> #REF! | Z84: =IF(inputoutput!#REF!=0, 0, AA9/inputoutput!#REF!) -> #REF! | AA84: =IF(inputoutput!#REF!=0, 0, AB9/inputoutput!#REF!) -> #REF! | AB84: =IF(inputoutput!#REF!=0, 0, AC9/inputoutput!#REF!) -> #REF! | AC84: =IF(inputoutput!#REF!=0, 0, AD9/inputoutput!#REF!) -> #REF! | AD84: =IF(inputoutput!#REF!=0, 0, AE9/inputoutput!#REF!) -> #REF! | ... AF84: =IF(inputoutput!#REF!=0, 0, AG9/inputoutput!#REF!) -> #REF!
A85: C19 | B85: =IF(inputoutput!C22=0, 0, C10/inputoutput!C22) -> #VALUE! | C85: =IF(inputoutput!D22=0, 0, D10/inputoutput!D22) -> 0.0016998463 | D85: =IF(inputoutput!E22=0, 0, E10/inputoutput!E22) -> 4.9970199e-06 | E85: =IF(inputoutput!F22=0, 0, F10/inputoutput!F22) -> 0.026968922 | F85: =IF(inputoutput!G22=0, 0, G10/inputoutput!G22) -> 0.0042510421 | G85: =IF(inputoutput!H22=0, 0, H10/inputoutput!H22) -> 0 | H85: =IF(inputoutput!I22=0, 0, I10/inputoutput!I22) -> 0 | I85: =IF(inputoutput!J22=0, 0, J10/inputoutput!J22) -> 0 | ... V85: =IF(inputoutput!W22=0, 0, W10/inputoutput!W22) -> 0 | W85: =IF(inputoutput!#REF!=0, 0, X10/inputoutput!#REF!) -> #REF! | X85: =IF(inputoutput!#REF!=0, 0, Y10/inputoutput!#REF!) -> #REF! | Y85: =IF(inputoutput!#REF!=0, 0, Z10/inputoutput!#REF!) -> #REF! | Z85: =IF(inputoutput!#REF!=0, 0, AA10/inputoutput!#REF!) -> #REF! | AA85: =IF(inputoutput!#REF!=0, 0, AB10/inputoutput!#REF!) -> #REF! | AB85: =IF(inputoutput!#REF!=0, 0, AC10/inputoutput!#REF!) -> #REF! | AC85: =IF(inputoutput!#REF!=0, 0, AD10/inputoutput!#REF!) -> #REF! | AD85: =IF(inputoutput!#REF!=0, 0, AE10/inputoutput!#REF!) -> #REF! | ... AF85: =IF(inputoutput!#REF!=0, 0, AG10/inputoutput!#REF!) -> #REF!
A86: C23 | B86: =IF(inputoutput!C23=0, 0, C11/inputoutput!C23) -> #VALUE! | C86: =IF(inputoutput!D23=0, 0, D11/inputoutput!D23) -> 0 | D86: =IF(inputoutput!E23=0, 0, E11/inputoutput!E23) -> 0 | E86: =IF(inputoutput!F23=0, 0, F11/inputoutput!F23) -> 0 | F86: =IF(inputoutput!G23=0, 0, G11/inputoutput!G23) -> 0 | G86: =IF(inputoutput!H23=0, 0, H11/inputoutput!H23) -> 0 | H86: =IF(inputoutput!I23=0, 0, I11/inputoutput!I23) -> 0 | I86: =IF(inputoutput!J23=0, 0, J11/inputoutput!J23) -> 0 | ... V86: =IF(inputoutput!W23=0, 0, W11/inputoutput!W23) -> 0 | W86: =IF(inputoutput!#REF!=0, 0, X11/inputoutput!#REF!) -> #REF! | X86: =IF(inputoutput!#REF!=0, 0, Y11/inputoutput!#REF!) -> #REF! | Y86: =IF(inputoutput!#REF!=0, 0, Z11/inputoutput!#REF!) -> #REF! | Z86: =IF(inputoutput!#REF!=0, 0, AA11/inputoutput!#REF!) -> #REF! | AA86: =IF(inputoutput!#REF!=0, 0, AB11/inputoutput!#REF!) -> #REF! | AB86: =IF(inputoutput!#REF!=0, 0, AC11/inputoutput!#REF!) -> #REF! | AC86: =IF(inputoutput!#REF!=0, 0, AD11/inputoutput!#REF!) -> #REF! | AD86: =IF(inputoutput!#REF!=0, 0, AE11/inputoutput!#REF!) -> #REF! | ... AF86: =IF(inputoutput!#REF!=0, 0, AG11/inputoutput!#REF!) -> #REF!
A87: C24_33 | B87: =IF(inputoutput!C24=0, 0, C12/inputoutput!C24) -> #VALUE! | C87: =IF(inputoutput!D24=0, 0, D12/inputoutput!D24) -> 0.0016203489 | D87: =IF(inputoutput!E24=0, 0, E12/inputoutput!E24) -> 0.016911357 | E87: =IF(inputoutput!F24=0, 0, F12/inputoutput!F24) -> 0.50926297 | F87: =IF(inputoutput!G24=0, 0, G12/inputoutput!G24) -> 0 | G87: =IF(inputoutput!H24=0, 0, H12/inputoutput!H24) -> 0 | H87: =IF(inputoutput!I24=0, 0, I12/inputoutput!I24) -> 0 | I87: =IF(inputoutput!J24=0, 0, J12/inputoutput!J24) -> 0 | ... V87: =IF(inputoutput!W24=0, 0, W12/inputoutput!W24) -> 0 | W87: =IF(inputoutput!#REF!=0, 0, X12/inputoutput!#REF!) -> #REF! | X87: =IF(inputoutput!#REF!=0, 0, Y12/inputoutput!#REF!) -> #REF! | Y87: =IF(inputoutput!#REF!=0, 0, Z12/inputoutput!#REF!) -> #REF! | Z87: =IF(inputoutput!#REF!=0, 0, AA12/inputoutput!#REF!) -> #REF! | AA87: =IF(inputoutput!#REF!=0, 0, AB12/inputoutput!#REF!) -> #REF! | AB87: =IF(inputoutput!#REF!=0, 0, AC12/inputoutput!#REF!) -> #REF! | AC87: =IF(inputoutput!#REF!=0, 0, AD12/inputoutput!#REF!) -> #REF! | AD87: =IF(inputoutput!#REF!=0, 0, AE12/inputoutput!#REF!) -> #REF! | ... AF87: =IF(inputoutput!#REF!=0, 0, AG12/inputoutput!#REF!) -> #REF!
A88: C26_27 | B88: =IF(inputoutput!C25=0, 0, C13/inputoutput!C25) -> #VALUE! | C88: =IF(inputoutput!D25=0, 0, D13/inputoutput!D25) -> 1.455871e-05 | D88: =IF(inputoutput!E25=0, 0, E13/inputoutput!E25) -> 0 | E88: =IF(inputoutput!F25=0, 0, F13/inputoutput!F25) -> 0 | F88: =IF(inputoutput!G25=0, 0, G13/inputoutput!G25) -> 0 | G88: =IF(inputoutput!H25=0, 0, H13/inputoutput!H25) -> 0 | H88: =IF(inputoutput!I25=0, 0, I13/inputoutput!I25) -> 0 | I88: =IF(inputoutput!J25=0, 0, J13/inputoutput!J25) -> 0 | ... V88: =IF(inputoutput!W25=0, 0, W13/inputoutput!W25) -> 0 | W88: =IF(inputoutput!#REF!=0, 0, X13/inputoutput!#REF!) -> #REF! | X88: =IF(inputoutput!#REF!=0, 0, Y13/inputoutput!#REF!) -> #REF! | Y88: =IF(inputoutput!#REF!=0, 0, Z13/inputoutput!#REF!) -> #REF! | Z88: =IF(inputoutput!#REF!=0, 0, AA13/inputoutput!#REF!) -> #REF! | AA88: =IF(inputoutput!#REF!=0, 0, AB13/inputoutput!#REF!) -> #REF! | AB88: =IF(inputoutput!#REF!=0, 0, AC13/inputoutput!#REF!) -> #REF! | AC88: =IF(inputoutput!#REF!=0, 0, AD13/inputoutput!#REF!) -> #REF! | AD88: =IF(inputoutput!#REF!=0, 0, AE13/inputoutput!#REF!) -> #REF! | ... AF88: =IF(inputoutput!#REF!=0, 0, AG13/inputoutput!#REF!) -> #REF!
... A107: ST | B107: =IF(inputoutput!C44=0, 0, C32/inputoutput!C44) -> #VALUE! | C107: =IF(inputoutput!D44=0, 0, D32/inputoutput!D44) -> 0 | D107: =IF(inputoutput!E44=0, 0, E32/inputoutput!E44) -> 0 | E107: =IF(inputoutput!F44=0, 0, F32/inputoutput!F44) -> 0 | F107: =IF(inputoutput!G44=0, 0, G32/inputoutput!G44) -> 0 | G107: =IF(inputoutput!H44=0, 0, H32/inputoutput!H44) -> 0 | H107: =IF(inputoutput!I44=0, 0, I32/inputoutput!I44) -> 0 | I107: =IF(inputoutput!J44=0, 0, J32/inputoutput!J44) -> 0 | ... V107: =IF(inputoutput!W44=0, 0, W32/inputoutput!W44) -> 0 | W107: =IF(inputoutput!#REF!=0, 0, X32/inputoutput!#REF!) -> #REF! | X107: =IF(inputoutput!#REF!=0, 0, Y32/inputoutput!#REF!) -> #REF! | Y107: =IF(inputoutput!#REF!=0, 0, Z32/inputoutput!#REF!) -> #REF! | Z107: =IF(inputoutput!#REF!=0, 0, AA32/inputoutput!#REF!) -> #REF! | AA107: =IF(inputoutput!#REF!=0, 0, AB32/inputoutput!#REF!) -> #REF! | AB107: =IF(inputoutput!#REF!=0, 0, AC32/inputoutput!#REF!) -> #REF! | AC107: =IF(inputoutput!#REF!=0, 0, AD32/inputoutput!#REF!) -> #REF! | AD107: =IF(inputoutput!#REF!=0, 0, AE32/inputoutput!#REF!) -> #REF! | ... AF107: =IF(inputoutput!#REF!=0, 0, AG32/inputoutput!#REF!) -> #REF!
A110: Export trends (linear or polynomial regression model results for exports, per industry against year, 2010-2021)
D111: agriculture | E111: forestry | F111: fishing | G111: mining | H111: manu_food | I111: manu_clothing | J111: manu_forest | K111: manu_chemical | L111: manu_petroleum | M111: manu_mineral | N111: manu_metal | O111: manu_electrical | P111: manu_furniture | Q111: electricity | R111: water | S111: construction | T111: trade | U111: transport | V111: accommodation | W111: ict | X111: finance | Y111: realestate | Z111: serv_prof | AA111: serv_science | AB111: serv_advertising | AC111: public | AD111: education | AE111: health | AF111: entertainment | AG111: serv_repair | AH111: serv_serv
B112: Sector | D112: A1 | E112: A2 | F112: A3 | G112: B | H112: C10_12 | I112: C13_15 | J112: C16_17 | K112: C20_22 | L112: C19 | M112: C23 | N112: C24_33 | O112: C26_27 | P112: C31_32 | Q112: D | R112: E | S112: F | T112: G | U112: H | V112: I | W112: J | X112: K | Y112: L | Z112: M_N | AA112: M_N_72 | AB112: M_N_73 | AC112: O | AD112: P | AE112: Q | AF112: R | AG112: S95 | AH112: ST
C113: Intercept | D113: 4.1404337e+08 | E113: -4.4867615e+09 | F113: 17016873 | G113: 6.4978683e+08 | H113: 5.7140406e+10 | I113: 4.7608371e+10 | J113: -6.7303033e+10 | K113: -3.6249163e+11 | L113: 2.0938876e+11 | M113: 3.3575154e+10 | N113: 1.8527109e+10 | O113: 9.7215903e+09 | P113: 4.4404982e+08 | Q113: 234542748 | R113: 3.4200935e+08 | S113: -1.9061588e+10 | T113: 2.3316578e+09 | U113: 4.3514397e+09 | V113: 1.8730209e+10 | W113: 4.8398824e+09 | X113: 5.2481509e+08 | Y113: 8139618.9 | Z113: -1.4879038e+11 | AA113: 3.0331382e+10 | AB113: 2.1391174e+08 | AC113: -7.3968195e+09 | AD113: 15948321 | AE113: 19567660 | AF113: 46331776 | AG113: 26597851 | AH113: 2365064.2
B114: Trend | C114: Slope (Linear or Poly Term 1) | D114: -4.7025012e+08 | E114: 2257654.6 | F114: -9896974.1 | G114: 6.8826193e+08 | H114: -27641655 | I114: -23348939 | J114: 38821641 | K114: 1.833188e+08 | L114: -1.0174247e+08 | M114: -16352548 | N114: 2.4619104e+09 | O114: -5.1996545e+09 | P114: 23884376 | Q114: -3.4597728e+08 | R114: 42530828 | S114: 9483171.9 | T114: 3.0440762e+09 | U114: 1.1313426e+09 | V114: -9230322.2 | W114: 7.0994771e+09 | X114: -3.2723941e+08 | Y114: -16349338 | Z114: 74970132 | AA114: -14847185 | AB114: 2.0882694e+08 | AC114: 3717496.2 | AD114: 18120578 | AE114: 20614474 | AF114: 45155703 | AG114: 45851227 | AH114: 4216378.6
C115: Quadratic Term (Poly only) | D115: -39963080 | F115: -4510502.8 | G115: 1.9673548e+08 | N115: 3.5090065e+09 | O115: 2.9715391e+09 | P115: 78310478 | Q115: 2.3092356e+08 | R115: -1.0632628e+08 | T115: 1.1613831e+08 | U115: -9.0203603e+08 | W115: 2.5373642e+09 | X115: 2.0104013e+08 | Y115: 33526747 | AB115: -1.5085405e+08 | AD115: -8702825.4 | AE115: 13154123 | AF115: -13218937 | AG115: 33811983 | AH115: -1501621.2
C116: R-squared | D116: 0.91 | E116: 0.35 | F116: 0.55 | G116: 0.74 | H116: 0.33 | I116: 0.54 | J116: 0.04 | K116: 0.74 | L116: 0.11 | M116: 0.47 | N116: 0.76 | O116: 0.76 | P116: 0.36 | Q116: 0.88 | R116: 0.46 | S116: 0.55 | T116: 0.97 | U116: 0.42 | V116: 0.64 | W116: 0.95 | X116: 0.67 | Y116: 0.53 | Z116: 0.4 | AA116: 0.33 | AB116: 0.77 | AC116: 0.19 | AD116: 0.84 | AE116: 0.84 | AF116: 0.64 | AG116: 0.93 | AH116: 0.57
B117: Significance | C117: P-value | D117: 0 | E117: 0.0445 | F117: 0.0147 | G117: 0.0009 | H117: 0.0503 | I117: 0.0068 | J117: 0.5276 | K117: 0.0004 | L117: 0.2881 | M117: 0.0144 | N117: 0.0129 | O117: 0.0011 | P117: 0.5309 | Q117: 0.0001 | R117: 0.3325 | S117: 0.0057 | T117: 0 | U117: 0.0793 | V117: 0.0017 | W117: 0 | X117: 0.0052 | Y117: 0.1929 | Z117: 0.0281 | AA117: 0.0527 | AB117: 0.0065 | AC117: 0.1623 | AD117: 0.0014 | AE117: 0.0003 | AF117: 0.0304 | AG117: 0.0001 | AH117: 0.0532
C118: Model Used | D118: Polynomial | E118: Linear | F118: Polynomial | G118: Polynomial | H118: Linear | I118: Linear | J118: Linear | K118: Linear | L118: Linear | M118: Linear | N118: Polynomial | O118: Polynomial | P118: Polynomial | Q118: Polynomial | R118: Polynomial | S118: Linear | T118: Polynomial | U118: Polynomial | V118: Linear | W118: Polynomial | X118: Polynomial | Y118: Polynomial | Z118: Linear | AA118: Linear | AB118: Polynomial | AC118: Linear | AD118: Polynomial | AE118: Polynomial | AF118: Polynomial | AG118: Polynomial | AH118: Polynomial
C119: Polynomial Degree | D119: 3 | F119: 2 | G119: 2 | N119: 2 | O119: 2 | P119: 2 | Q119: 2 | R119: 2 | T119: 3 | U119: 2 | W119: 2 | X119: 2 | Y119: 2 | AB119: 3 | AD119: 3 | AE119: 2 | AF119: 3 | AG119: 3 | AH119: 3

Sheet prices
B1: Initial inflation rate (2010) | C1: 1.2
X6: QUAIDS
C7: Purchasing vs basic prices | Y7: alpha | Z7: beta | AA7: lambda | AB7: gamma
D8: %m | E8: ttm shares | F8: %t | J8: NET PROFITS | L8: Profit share | M8: Mark up | O8: ROUNDED | Y8: constant | Z8: logx | AA8: logx2 | AB8: A | AC8: B | AD8: C | AE8: C19 | AF8: C29 | AG8: D1 | AH8: D2 | AI8: D3 | AJ8: E | AK8: F | AL8: G | AM8: H | AN8: I | AO8: J_R_S | AP8: K | AQ8: L | AR8: H_M_N | AS8: O | AT8: P | AU8: Q | AV8: T
C9: A | D9: 1.3549232 | E9: 0 | F9: 0.055874184 | I9: A | J9: 12166 | L9: 0.42525971 | M9: 0.73991631 | N9: 0.73991631 | O9: 0.7399 | P9: 0.7399 | X9: A | Y9: -0.064848896 | Z9: 0.04228537 | AA9: -0.0035720667 | AB9: -0.0034549199 | AC9: 0.0024172738 | AD9: -0.016899921 | AE9: 0.00077302585 | AF9: -0.0012589731 | AG9: 0.0018866715 | AH9: 0.0022288912 | AI9: 5.605964e-06 | AJ9: 0.00098152814 | AK9: 0.0018044457 | AL9: -0.00076693067 | AM9: -5.5145869e-05 | AN9: -0.0084944965 | AO9: -0.00097551888 | AP9: 0.0011532421 | AQ9: 0.022035818 | AR9: -0.00036466417 | AS9: 4.8032443e-06 | AT9: -0.00016950876 | AU9: -0.0020173931 | AV9: 0.0011661747
C10: B | D10: 0.25883976 | E10: 0 | F10: 0.42863956 | I10: B | J10: 858.3 | L10: 0.18988938 | M10: 0.23439932 | N10: 0.23439932 | O10: 0.2344 | P10: 0.2344 | X10: B | Y10: 0.10395555 | Z10: -0.015242335 | AA10: 0.00033017896 | AB10: 0.0024172738 | AC10: -0.0025850906 | AD10: 0.013243738 | AE10: -0.00066603033 | AF10: 0.00074848713 | AG10: -0.0013282121 | AH10: -0.001569134 | AI10: -3.9467466e-06 | AJ10: -0.0034167647 | AK10: -0.0010597108 | AL10: 0.00045525572 | AM10: 0.00053070702 | AN10: 0.0040406308 | AO10: 0.001389119 | AP10: 0.00034908945 | AQ10: -0.012965444 | AR10: -0.0002122864 | AS10: -4.0875062e-05 | AT10: -0.00022524989 | AU10: 0.0014441282 | AV10: -0.0005456821
C11: C | D11: 0.89949778 | E11: 0 | F11: 0.15563465 | I11: C | J11: 38745.8 | L11: 0.18474917 | M11: 0.22661636 | N11: 0.22661636 | O11: 0.2266 | P11: 0.2266 | X11: C | Y11: -0.51751324 | Z11: 0.21334305 | AA11: -0.013524173 | AB11: -0.016899921 | AC11: 0.013243738 | AD11: -0.090413455 | AE11: 0.0048717493 | AF11: -0.0074036107 | AG11: 0.011404001 | AH11: 0.01347255 | AI11: 3.3885074e-05 | AJ11: 0.002202875 | AK11: 0.010285618 | AL11: -0.0044963226 | AM11: -0.00023776273 | AN11: -0.044247913 | AO11: -0.0090049038 | AP11: 0.0051587017 | AQ11: 0.12572778 | AR11: -0.0032140161 | AS11: -7.0918932e-05 | AT11: -0.0014649049 | AU11: -0.012339225 | AV11: 0.003392106
C12: C19 | D12: 0.23587856 | E12: 0 | F12: 0.84077569 | I12: C19 | J12: -1093.4 | L12: -0.43723757 | M12: -0.30422081 | N12: -0.30422081 | O12: -0.3042 | P12: -0.3042 | X12: C19 | Y12: 0.061805927 | Z12: -0.010194476 | AA12: 0.0010291914 | AB12: 0.00077302585 | AC12: -0.00066603033 | AD12: 0.0048717493 | AE12: 0.0038652979 | AF12: 0.0045670039 | AG12: -0.00016051399 | AH12: -0.00018962931 | AI12: -4.7698728e-07 | AJ12: -0.00082492652 | AK12: -0.0012798532 | AL12: 0.0027931938 | AM12: -0.0010412591 | AN12: 0.0012850754 | AO12: -0.00077345163 | AP12: -5.9337368e-05 | AQ12: -0.015767619 | AR12: 0.0012423208 | AS12: 4.3555549e-05 | AT12: 0.00063004942 | AU12: 0.0012763646 | AV12: -0.00058453382
C13: C29 | D13: 0.30455052 | E13: 0 | F13: 0.12853328 | I13: C29_30 | J13: -275.9 | L13: -0.016179351 | M13: -0.015921747 | N13: -0.015921747 | O13: -0.0159 | P13: -0.0159 | X13: C29 | Y13: -0.023802651 | Z13: 0.003653335 | AA13: 0.00070178345 | AB13: -0.0012589731 | AC13: 0.00074848713 | AD13: -0.0074036107 | AE13: 0.0045670039 | AF13: 0.0043061961 | AG13: 0.00077780732 | AH13: 0.00091889228 | AI13: 2.3111283e-06 | AJ13: 0.00021673048 | AK13: -0.00028122987 | AL13: 0.0026320383 | AM13: -0.00061067686 | AN13: -0.00021882652 | AO13: -0.002114048 | AP13: -0.00044731989 | AQ13: -0.003481305 | AR13: 0.0013090447 | AS13: 6.4031805e-06 | AT13: 0.00041422718 | AU13: 0.00027670685 | AV13: -0.00035985849
C14: D1 | D14: 0.00019206511 | E14: 0 | F14: 0.22739896 | I14: D | J14: 4527.4 | L14: 0.18606314 | M14: 0.22859653 | N14: 0.22859653 | O14: 0.2286 | P14: 0.2286 | Q14: repeat the same value D1. D2, D3 | X14: D1 | Y14: 0.083043649 | Z14: -0.013560398 | AA14: 0.00043808494 | AB14: 0.0018866715 | AC14: -0.0013282121 | AD14: 0.011404001 | AE14: -0.00016051399 | AF14: 0.00077780732 | AG14: -0.00085218077 | AH14: -0.0010067562 | AI14: -2.5321621e-06 | AJ14: -0.0010035414 | AK14: -0.0010355145 | AL14: 0.00047721671 | AM14: -0.00050978803 | AN14: 0.0015257487 | AO14: 0.0010792583 | AP14: 0.00033876654 | AQ14: -0.012741511 | AR14: 9.2713209e-05 | AS14: 3.7909277e-05 | AT14: 0.00026509266 | AU14: 0.0010294582 | AV14: -0.00027408775
C15: D2 | D15: 0.00019206511 | E15: 0 | F15: 0.22739896 | I15: E | J15: 323.7 | L15: 0.025606746 | M15: 0.026279683 | N15: 0.026279683 | O15: 0.0263 | P15: 0.0263 | X15: D2 | Y15: 0.098106776 | Z15: -0.016020093 | AA15: 0.00051754832 | AB15: 0.0022288912 | AC15: -0.001569134 | AD15: 0.01347255 | AE15: -0.00018962931 | AF15: 0.00091889228 | AG15: -0.0010067562 | AH15: -0.0011893697 | AI15: -2.991466e-06 | AJ15: -0.0011855718 | AK15: -0.0012233445 | AL15: 0.00056377813 | AM15: -0.0006022575 | AN15: 0.0018025013 | AO15: 0.0012750229 | AP15: 0.00040021474 | AQ15: -0.015052669 | AR15: 0.00010953028 | AS15: 4.4785567e-05 | AT15: 0.00031317731 | AU15: 0.0012161896 | AV15: -0.000323804
C16: D3 | D16: 0.00019206511 | E16: 0 | F16: 0.22739896 | I16: F | J16: 33520.6 | L16: 0.41104152 | M16: 0.69791255 | N16: 0.69791255 | O16: 0.6979 | P16: 0.6979 | X16: D3 | Y16: 0.0002467504 | Z16: -4.0292078e-05 | AA16: 1.3016396e-06 | AB16: 5.605964e-06 | AC16: -3.9467466e-06 | AD16: 3.3885074e-05 | AE16: -4.7698728e-07 | AF16: 2.3111283e-06 | AG16: -2.5321621e-06 | AH16: -2.991466e-06 | AI16: -7.5240431e-09 | AJ16: -2.9822893e-06 | AK16: -3.0768308e-06 | AL16: 1.4179713e-06 | AM16: -1.5145651e-06 | AN16: 4.5338296e-06 | AO16: 3.2068442e-06 | AP16: 1.0065961e-06 | AQ16: -3.7858922e-05 | AR16: 2.7542636e-07 | AS16: 1.1262695e-07 | AT16: 7.8759077e-07 | AU16: 3.0589e-06 | AV16: -8.1444318e-07
C17: E | D17: 0 | E17: 0 | F17: 0.086380336 | I17: G | J17: 75690.2 | L17: 0.464843 | M17: 0.86861053 | N17: 0.86861053 | O17: 0.8686 | P17: 0.8686 | X17: E | Y17: 0.018209119 | Z17: 0.0036244411 | AA17: -0.00085898339 | AB17: 0.00098152814 | AC17: -0.0034167647 | AD17: 0.002202875 | AE17: -0.00082492652 | AF17: 0.00021673048 | AG17: -0.0010035414 | AH17: -0.0011855718 | AI17: -2.9822893e-06 | AJ17: -0.0075420495 | AK17: 0.00025425857 | AL17: 0.00012082817 | AM17: 0.0030224833 | AN17: 0.005766964 | AO17: 0.00035571274 | AP17: 0.00017892013 | AQ17: 0.0033130324 | AR17: -0.00092232133 | AS17: -0.00023205649 | AT17: -0.0014337216 | AU17: 0.00083909704 | AV17: -0.00068850088
C18: F | D18: 0 | E18: 0 | F18: 0.095396654 | I18: H49_51 | J18: 16074.7 | L18: 0.33700499 | M18: 0.50830698 | N18: 0.50830698 | O18: 0.5083 | P18: 0.5083 | X18: F | Y18: 0.11554528 | Z18: -0.020706802 | AA18: 0.0010028413 | AB18: 0.0018044457 | AC18: -0.0010597108 | AD18: 0.010285618 | AE18: -0.0012798532 | AF18: -0.00028122987 | AG18: -0.0010355145 | AH18: -0.0012233445 | AI18: -3.0768308e-06 | AJ18: 0.00025425857 | AK18: -0.00099321259 | AL18: -0.00017290341 | AM18: 5.0164538e-05 | AN18: 0.0035531246 | AO18: 0.0015767941 | AP18: -0.00029295324 | AQ18: -0.012161829 | AR18: 5.9112008e-05 | AS18: 4.8779578e-06 | AT18: 3.3876606e-05 | AU18: 0.0011726295 | AV18: -0.000291274
C19: G | D19: 0 | E19: 0.92758928 | F19: 0.12050178 | I19: M+N+U | J19: 71055.2 | L19: 0.41970366 | M19: 0.72325746 | N19: 0.72325746 | O19: 0.7233 | P19: 0.7233 | X19: G | Y19: -0.014465698 | Z19: 0.0022924618 | AA19: 0.00041143783 | AB19: -0.00076693067 | AC19: 0.00045525572 | AD19: -0.0044963226 | AE19: 0.0027931938 | AF19: 0.0026320383 | AG19: 0.00047721671 | AH19: 0.00056377813 | AI19: 1.4179713e-06 | AJ19: 0.00012082817 | AK19: -0.00017290341 | AL19: 0.0016087227 | AM19: -0.00037038066 | AN19: -0.00016171294 | AO19: -0.0012823429 | AP19: -0.0002752909 | AQ19: -0.0021411103 | AR19: 0.00079807247 | AS19: 4.0433588e-06 | AT19: 0.00025414635 | AU19: 0.00017452357 | AV19: -0.00021624286
C20: H | D20: 0 | E20: 0.072410778 | F20: -0.2841447 | I20: I | J20: 22214.9 | L20: 0.42256707 | M20: 0.73180285 | N20: 0.73180285 | O20: 0.7318 | P20: 0.7318 | X20: H | Y20: -0.0074816122 | Z20: -0.0038831772 | AA20: 0.0005360698 | AB20: -5.5145869e-05 | AC20: 0.00053070702 | AD20: -0.00023776273 | AE20: -0.0010412591 | AF20: -0.00061067686 | AG20: -0.00050978803 | AH20: -0.0006022575 | AI20: -1.5145651e-06 | AJ20: 0.0030224833 | AK20: 5.0164538e-05 | AL20: -0.00037038066 | AM20: -0.0086434843 | AN20: 0.0033009382 | AO20: 0.0016884502 | AP20: -0.00032260884 | AQ20: 0.00071326054 | AR20: 0.00038037934 | AS20: 9.8902509e-05 | AT20: 0.00059217232 | AU20: 0.0013648171 | AV20: 0.00065262339
C21: I | D21: 0 | E21: 0 | F21: 0.056422516 | I21: J+R+S | J21: 44111.3 | L21: 0.42900602 | M21: 0.75133195 | N21: 0.75133195 | O21: 0.7513 | P21: 0.7513 | X21: I | Y21: -0.15344782 | Z21: 0.043606154 | AA21: -0.0018047008 | AB21: -0.0084944965 | AC21: 0.0040406308 | AD21: -0.044247913 | AE21: 0.0012850754 | AF21: -0.00021882652 | AG21: 0.0015257487 | AH21: 0.0018025013 | AI21: 4.5338296e-06 | AJ21: 0.005766964 | AK21: 0.0035531246 | AL21: -0.00016171294 | AM21: 0.0033009382 | AN21: -0.017076946 | AO21: -0.0013801909 | AP21: 0.00053774393 | AQ21: 0.043384271 | AR21: 0.0012320288 | AS21: 0.00032934975 | AT21: 0.0019665156 | AU21: 0.00054088996 | AV21: 0.0023097613
C22: J_R_S | D22: 0.064394869 | E22: 0 | F22: 0.22249796 | I22: K | J22: 30291.4 | L22: 0.40023149 | M22: 0.66730993 | N22: 0.66730993 | O22: 0.6673 | P22: 0.6673 | X22: J_R_S | Y22: -0.064586261 | Z22: 0.017245923 | AA22: 0.00020078734 | AB22: -0.00097551888 | AC22: 0.001389119 | AD22: -0.0090049038 | AE22: -0.00077345163 | AF22: -0.002114048 | AG22: 0.0010792583 | AH22: 0.0012750229 | AI22: 3.2068442e-06 | AJ22: 0.00035571274 | AK22: 0.0015767941 | AL22: -0.0012823429 | AM22: 0.0016884502 | AN22: -0.0013801909 | AO22: -0.0084765586 | AP22: -0.00032279118 | AQ22: 0.019430209 | AR22: -0.0010561577 | AS22: -3.3471069e-05 | AT22: -0.00034167624 | AU22: -0.0012701759 | AV22: 0.00023353801
C23: K | D23: 0 | E23: 0 | F23: 0.14059671 | I23: L | J23: 116564.2 | L23: 0.63143862 | M23: 1.7132522 | N23: 1.7132522 | O23: 1.7133 | P23: 1.7133 | X23: K | Y23: 0.020254662 | Z23: -0.0063479894 | AA23: 0.0010928222 | AB23: 0.0011532421 | AC23: 0.00034908945 | AD23: 0.0051587017 | AE23: -5.9337368e-05 | AF23: -0.00044731989 | AG23: 0.00033876654 | AH23: 0.00040021474 | AI23: 1.0065961e-06 | AJ23: 0.00017892013 | AK23: -0.00029295324 | AL23: -0.0002752909 | AM23: -0.00032260884 | AN23: 0.00053774393 | AO23: -0.00032279118 | AP23: -0.0023977257 | AQ23: -0.0036046832 | AR23: -0.00026067626 | AS23: -5.1430037e-05 | AT23: -0.00014163583 | AU23: 0.00037881375 | AV23: -0.0003200385
C24: L | D24: 0 | E24: 0 | F24: 0.0016907695 | I24: O | J24: 1234 | L24: 0.011926508 | M24: 0.012070466 | N24: 0.012070466 | O24: 0.0121 | P24: 0.0121 | X24: L | Y24: 1.422317 | Z24: -0.25444291 | AA24: 0.01233328 | AB24: 0.022035818 | AC24: -0.012965444 | AD24: 0.12572778 | AE24: -0.015767619 | AF24: -0.003481305 | AG24: -0.012741511 | AH24: -0.015052669 | AI24: -3.7858922e-05 | AJ24: 0.0033130324 | AK24: -0.012161829 | AL24: -0.0021411103 | AM24: 0.00071326054 | AN24: 0.043384271 | AO24: 0.019430209 | AP24: -0.0036046832 | AQ24: -0.14892437 | AR24: 0.00076560838 | AS24: 6.9785473e-05 | AT24: 0.00047542033 | AU24: 0.01449346 | AV24: -0.0035302403
C25: H_M_N | D25: 0.00011800368 | E25: 0 | F25: 0.13905726 | I25: P | J25: 2951 | L25: 0.045631033 | M25: 0.04781278 | N25: 0.04781278 | O25: 0.0478 | P25: 0.0478 | X25: H_M_N | Y25: -0.0084291149 | Z25: 0.0010968915 | AA25: 0.0005179038 | AB25: -0.00036466417 | AC25: -0.0002122864 | AD25: -0.0032140161 | AE25: 0.0012423208 | AF25: 0.0013090447 | AG25: 9.2713209e-05 | AH25: 0.00010953028 | AI25: 2.7542636e-07 | AJ25: -0.00092232133 | AK25: 5.9112008e-05 | AL25: 0.00079807247 | AM25: 0.00038037934 | AN25: 0.0012320288 | AO25: -0.0010561577 | AP25: -0.00026067626 | AQ25: 0.00076560838 | AR25: 0.00026991555 | AS25: -3.9994633e-05 | AT25: -0.0001224267 | AU25: 0.00022655537 | AV25: -0.00029301233
C26: O | D26: 0 | E26: 0 | F26: 0 | I26: Q | J26: 18873 | L26: 0.21729444 | M26: 0.27761965 | N26: 0.27761965 | O26: 0.2776 | P26: 0.2776 | X26: O | Y26: -0.00076014439 | Z26: -0.000260461 | AA26: 4.570969e-05 | AB26: 4.8032443e-06 | AC26: -4.0875062e-05 | AD26: -7.0918932e-05 | AE26: 4.3555549e-05 | AF26: 6.4031805e-06 | AG26: 3.7909277e-05 | AH26: 4.4785567e-05 | AI26: 1.1262695e-07 | AJ26: -0.00023205649 | AK26: 4.8779578e-06 | AL26: 4.0433588e-06 | AM26: 9.8902509e-05 | AN26: 0.00032934975 | AO26: -3.3471069e-05 | AP26: -5.1430037e-05 | AQ26: 6.9785473e-05 | AR26: -3.9994633e-05 | AS26: -2.1819564e-05 | AT26: -0.00012971946 | AU26: -8.3759274e-05 | AV26: 5.9514745e-05
C27: P | D27: 0 | E27: 0 | F27: 0.012684032 | I27: T | J27: 0 | L27: 0 | M27: 0 | N27: 0 | O27: 0 | P27: 0 | X27: P | Y27: -0.008320972 | Z27: -0.00075824646 | AA27: 0.00023861018 | AB27: -0.00016950876 | AC27: -0.00022524989 | AD27: -0.0014649049 | AE27: 0.00063004942 | AF27: 0.00041422718 | AG27: 0.00026509266 | AH27: 0.00031317731 | AI27: 7.8759077e-07 | AJ27: -0.0014337216 | AK27: 3.3876606e-05 | AL27: 0.00025414635 | AM27: 0.00059217232 | AN27: 0.0019665156 | AO27: -0.00034167624 | AP27: -0.00014163583 | AQ27: 0.00047542033 | AR27: -0.0001224267 | AS27: -0.00012971946 | AT27: -0.00075632874 | AU27: -0.00052846647 | AV27: 0.00036816466
C28: Q | D28: 0 | E28: 0 | F28: 0.071849625 | X28: Q | Y28: -0.068823204 | Z28: 0.02105857 | AA28: -0.00074932519 | AB28: -0.0020173931 | AC28: 0.0014441282 | AD28: -0.012339225 | AE28: 0.0012763646 | AF28: 0.00027670685 | AG28: 0.0010294582 | AH28: 0.0012161896 | AI28: 3.0589e-06 | AJ28: 0.00083909704 | AK28: 0.0011726295 | AL28: 0.00017452357 | AM28: 0.0013648171 | AN28: 0.00054088996 | AO28: -0.0012701759 | AP28: 0.00037881375 | AQ28: 0.01449346 | AR28: 0.00022655537 | AS28: -8.3759274e-05 | AT28: -0.00052846647 | AU28: -0.0081862522 | AV28: -1.1421068e-05
C29: T | D29: 0 | E29: 0 | F29: 0 | X29: T | Y29: 0.0089949638 | Z29: -0.0067490145 | AA29: 0.001111679 | AB29: 0.0011661747 | AC29: -0.0005456821 | AD29: 0.003392106 | AE29: -0.00058453382 | AF29: -0.00035985849 | AG29: -0.00027408775 | AH29: -0.000323804 | AI29: -8.1444318e-07 | AJ29: -0.00068850088 | AK29: -0.000291274 | AL29: -0.00021624286 | AM29: 0.00065262339 | AN29: 0.0023097613 | AO29: 0.00023353801 | AP29: -0.0003200385 | AQ29: -0.0035302403 | AR29: -0.00029301233 | AS29: 5.9514745e-05 | AT29: 0.00036816466 | AU29: -1.1421068e-05 | AV29: -0.00074237134
B33: Dataset: 6A. Value added and its components by activity, ISIC rev4 | C33: NET OPERATING SURPLUS | O33: CORRESPONDANCE
B34: Country | G34: Italy | O34: Old Eurogreen (till July 23) | R34: New Eurogreen (after July 23)
B35: Transaction | G35: Net operating surplus and net mixed income | O35: Million euro (2010) ITALY - TOTAL
B36: Measure | G36: Current prices | O36: A | P36: V01 | Q36: 1 | R36: A | S36: V01
B37: Unit | G37: Euro, Millions | P37: V02 | Q37: 2 | S37: V02
B38: Year | G38: 2010 | H38: 2011 | I38: 2012 | J38: 2013 | K38: 2014 | L38: 2015 | P38: V03 | Q38: 3 | S38: V03
B39: Activity | F39: i | O39: B | P39: VB | Q39: 4 | R39: B | S39: VB
B40: VTOT: Total activity | G40: 487832.6 | H40: 501130.3 | I40: 466755.7 | J40: 471861.1 | K40: 478427.9 | L40: 484861.3 | O40: C | P40: V10_12 | Q40: 5 | R40: C | S40: V10_12
B41: VTOT: Total activity | C41: VA0: Agriculture, forestry and fishing | G41: 12166 | H41: 14753.4 | I41: 15722.5 | J41: 19351.2 | K41: 17746.6 | L41: 16968 | P41: V13_15 | Q41: 6 | S41: V13_15
C42: VA0: Agriculture, forestry and fishing | D42: V01: Crop and animal production, hunting and related service activities | F42: V01 | G42: 10884.1 | H42: 13612.2 | I42: 14594.2 | J42: 18204.9 | K42: 16700 | L42: 15824.8 | P42: V16 | Q42: 7 | S42: V16
D43: V02: Forestry and logging | F43: V02 | G43: 642.2 | H43: 573.3 | I43: 709.6 | J43: 872.3 | K43: 799.5 | L43: 813.8 | P43: V17 | Q43: 8 | S43: V17
D44: V03: Fishing and aquaculture | F44: V03 | G44: 639.7 | H44: 568 | I44: 418.6 | J44: 273.9 | K44: 247.1 | L44: 329.3 | P44: V18 | Q44: 9 | S44: V18
C45: VB: Mining and quarrying | F45: VB | G45: 858.3 | H45: 1578.4 | I45: 2933.8 | J45: 2699.7 | K45: 1757.2 | L45: 492.7 | O45: C19 | P45: V19 | Q45: 10 | R45: C19 | S45: V19
C46: VC: Manufacturing | G46: 37376.5 | H46: 37110.7 | I46: 28181.8 | J46: 28971.5 | K46: 31159 | L46: 38395 | O46: C | P46: V20 | Q46: 11 | R46: C | S46: V20
C47: VC: Manufacturing | D47: V10_12: Manufacture of food products, beverages and tobacco products | F47: V10_12 | G47: 6077 | H47: 5047.9 | I47: 4325.4 | J47: 4302 | K47: 4707.5 | L47: 6016 | P47: V21 | Q47: 12 | S47: V21
D48: V13_15: Manufacture of textiles, wearing apparel, leather and related products | F48: V13_15 | G48: 6232.3 | H48: 6987.8 | I48: 5781.4 | J48: 6548.9 | K48: 6795.6 | L48: 6813.1 | P48: V22 | Q48: 13 | S48: V22
D49: V16_18: Manufacture of wood and paper products: printing | G49: 3420.2 | H49: 3497.6 | I49: 2832.3 | J49: 2664.2 | K49: 3028.8 | L49: 2872.6 | P49: V23 | Q49: 14 | S49: V23
D50: V16_18: Manufacture of wood and paper products: printing | E50: V16: Manufacture of wood and of products of wood and cork,etc. | F50: V16 | G50: 1731 | H50: 1762.6 | I50: 1302.3 | J50: 1283.9 | K50: 1305.4 | L50: 1327.6 | P50: V24 | Q50: 15 | S50: V24
E51: V17: Manufacture of paper and paper products | F51: V17 | G51: 331.2 | H51: 457.2 | I51: 438.1 | J51: 420.1 | K51: 768.9 | L51: 649.1 | P51: V25 | Q51: 16 | S51: V25
E52: V18: Printing and reproduction of recorded media | F52: V18 | G52: 1358.1 | H52: 1277.8 | I52: 1091.9 | J52: 960.2 | K52: 954.4 | L52: 895.9 | P52: V26 | Q52: 17 | S52: V26
D53: V19: Manufacture of coke and refined petroleum products | F53: V19 | G53: -1093.4 | H53: -906.5 | I53: -1348 | J53: -2061.8 | K53: -3594.5 | L53: -1070.1 | P53: V27 | Q53: 18 | S53: V27
D54: V20: Manufacture of chemicals and chemical products | F54: V20 | G54: 437.9 | H54: 35.4 | I54: -285.7 | J54: -96.9 | K54: 13 | L54: 852.5 | P54: V28 | Q54: 19 | S54: V28
D55: V21: Manufacture of basic pharmaceutical products and preparations | F55: V21 | G55: 2133.9 | H55: 2124.1 | I55: 1894.1 | J55: 2217.6 | K55: 1798.3 | L55: 2418.9 | P55: V29 | Q55: 20 | R55: C29_30 | S55: V29
D56: V22_23: Manufacture of rubber, plastics and other non-metallic mineral products | F56: - | G56: 2410.4 | H56: 1821.3 | I56: 1214.5 | J56: 1670.1 | K56: 1969.6 | L56: 2560.8 | P56: V30 | Q56: 21 | S56: V30
D57: V22_23: Manufacture of rubber, plastics and other non-metallic mineral products | E57: V22: Manufacture of rubber and plastics products | F57: V22 | G57: 1059.5 | H57: 949.6 | I57: 1053.9 | J57: 1429.2 | K57: 1776.2 | L57: 2161.3 | P57: V31_32 | Q57: 22 | R57: C | S57: V31_32
E58: V23: Manufacture of other non-metallic mineral products | F58: V23 | G58: 1350.9 | H58: 871.7 | I58: 160.6 | J58: 241 | K58: 193.4 | L58: 399.6 | P58: V33 | Q58: 23 | S58: V33
D59: V24_25: Manuf. of basic metals and fabricated metal products, except mach. & equip. | F59: - | G59: 5657.3 | H59: 6136.3 | I59: 3887 | J59: 3775.5 | K59: 4873 | L59: 4780.7 | O59: D | P59: VD | Q59: 24 | R59: D | S59: VD
D60: V24_25: Manuf. of basic metals and fabricated metal products, except mach. & equip. | E60: V24: Manufacture of basic metals | F60: V24 | G60: -540.6 | H60: -37.6 | I60: -1125.3 | J60: -1307.4 | K60: -766.3 | L60: -895.4 | O60: E | P60: V36 | Q60: 25 | R60: E | S60: V36
E61: V25: Manufacture of fabricated metal products, except machinery and equipment | F61: V25 | G61: 6197.9 | H61: 6174 | I61: 5012.3 | J61: 5082.9 | K61: 5639.3 | L61: 5676.2 | P61: V37_39 | Q61: 26 | S61: V37_39
D62: V26: Manufacture of computer, electronic and optical products | F62: V26 | G62: 515 | H62: 617.1 | I62: 409.6 | J62: -36.5 | K62: 345.1 | L62: 604.9 | O62: F | P62: VF | Q62: 27 | R62: F | S62: VF
D63: V27: Manufacture of electrical equipment | F63: V27 | G63: 1911 | H63: 1828.7 | I63: 1561.5 | J63: 1587.9 | K63: 854 | L63: 1457.9 | O63: G | P63: V45 | Q63: 28 | R63: G | S63: V45
D64: V28: Manufacture of machinery and equipment n.e.c. | F64: V28 | G64: 5024.2 | H64: 5731.5 | I64: 5511.4 | J64: 5889 | K64: 6692.2 | L64: 6674.4 | P64: V46 | Q64: 29 | S64: V46
D65: V29_30: Manufacture of transport equipment | G65: -275.9 | H65: -1020 | I65: -2403.1 | J65: -2520 | K65: -1782.5 | L65: -1514.7 | P65: V47 | Q65: 30 | S65: V47
D66: V29_30: Manufacture of transport equipment | E66: V29: Manufacture of motor vehicles, trailers and semi-trailers | F66: V29 | G66: -338.7 | H66: -969.7 | I66: -2312.9 | J66: -1697.2 | K66: -1916.6 | L66: -1239.2 | O66: H | P66: V49 | Q66: 31 | R66: H49_51 | S66: V49
E67: V30: Manufacture of other transport equipment | F67: V30 | G67: 62.8 | H67: -50.2 | I67: -90.1 | J67: -822.8 | K67: 134.2 | L67: -275.5 | P67: V50 | Q67: 32 | S67: V50
D68: V31_33: Other manufacturing, repair and installation of machinery and equipment | G68: 4926.5 | H68: 5209.4 | I68: 4801.3 | J68: 5031.3 | K68: 5458.9 | L68: 5928 | P68: V51 | Q68: 33 | S68: V51
D69: V31_33: Other manufacturing, repair and installation of machinery and equipment | E69: V31_32: Manufacture of furniture, other manufacturing | F69: V31_32 | G69: 3078.7 | H69: 3097.7 | I69: 2659.2 | J69: 2848.1 | K69: 3261.6 | L69: 3607.2 | P69: V52 | Q69: 34 | R69: M+N+U | S69: V52
E70: V33: Repair and installation of machinery and equipment | F70: V33 | G70: 1847.8 | H70: 2111.8 | I70: 2142.1 | J70: 2183.2 | K70: 2197.3 | L70: 2320.7 | P70: V53 | Q70: 35 | S70: V53
C71: VD: Electricity, gas, steam and air conditioning supply | F71: VD | G71: 4527.4 | H71: 2531.9 | I71: 4076.4 | J71: 4570.9 | K71: 3779.9 | L71: 1926.5 | O71: I | P71: VI | Q71: 36 | R71: I | S71: VI
C72: VE: Water supply, sewerage, waste management and remediation activities | G72: 323.7 | H72: 291.3 | I72: 251.2 | J72: 748.8 | K72: 1485.9 | L72: 1446.5 | O72: J | P72: V58 | Q72: 37 | R72: J, R, S | S72: V58
C73: VE: Water supply, sewerage, waste management and remediation activities | D73: V36: Water collection, treatment and supply | F73: V36 | G73: -755.5 | H73: -691 | I73: -545 | J73: -203.2 | K73: 184.6 | L73: 413.7 | P73: V59_60 | Q73: 38 | S73: V59_60
D74: V37_39: Sewerage, waste collection and management services | F74: V37_39 | G74: 1079.2 | H74: 982.2 | I74: 796.2 | J74: 952 | K74: 1301.3 | L74: 1032.8 | P74: V61 | Q74: 39 | S74: V61
C75: VF: Construction | F75: VF | G75: 33520.6 | H75: 34577.1 | I75: 31690.8 | J75: 30372 | K75: 26600.4 | L75: 25431.8 | P75: V62_63 | Q75: 40 | S75: V62_63
C76: VG: Wholesale and retail trade, repair of motor vehicles and motorcycles | F76: V46 | G76: 75690.2 | H76: 79331.4 | I76: 75757.9 | J76: 75073.8 | K76: 77841.1 | L76: 83020.6 | O76: K | P76: V64 | Q76: 41 | R76: K | S76: V64
C77: VG: Wholesale and retail trade, repair of motor vehicles and motorcycles | D77: V46: Wholesale trade, except of motor vehicles and motorcycles | F77: - | G77: 33774 | H77: 37745.2 | I77: 35519 | J77: 34887 | K77: 35573.8 | L77: 37599.4 | P77: V65 | Q77: 42 | S77: V65
C78: VH: Transportation and storage | G78: 21086.3 | H78: 21537 | I78: 19069.5 | J78: 20250.8 | K78: 21104.2 | L78: 21600.7 | P78: V66 | Q78: 43 | S78: V66
C79: VH: Transportation and storage | D79: V49: Land transport and transport via pipelines | F79: V49 | G79: 18325.9 | H79: 18434.5 | I79: 18072.5 | J79: 18304.6 | K79: 18500.6 | L79: 19341 | O79: L | P79: VL | Q79: 44 | R79: L | S79: VL
D80: V50: Water transport | F80: V50 | G80: -2149.9 | H80: -2155.9 | I80: -2569.4 | J80: -2412.3 | K80: -2185.9 | L80: -1880.7 | O80: M+N | P80: V69_70 | Q80: 45 | S80: V69_70
D81: V51: Air transport | F81: V51 | G81: -101.3 | H81: 362.9 | I81: -693.3 | J81: -934.8 | K81: -802.6 | L81: -697.3 | P81: V71 | Q81: 46 | R81: M+N+U | S81: V71
D82: V52: Warehousing and support activities for transportation | F82: V52 | G82: 5303.5 | H82: 5343.4 | I82: 5449.4 | J82: 5774.3 | K82: 6403.9 | L82: 5323.2 | P82: V72 | Q82: 47 | S82: V72
D83: V53: Postal and courier activities | F83: V53 | G83: -291.9 | H83: -447.8 | I83: -1189.8 | J83: -481.1 | K83: -811.8 | L83: -485.5 | P83: V73 | Q83: 48 | S83: V73
C84: VI: Accommodation and food service activities | F84: VI | G84: 22214.9 | H84: 22894.1 | I84: 21984.3 | J84: 21174.6 | K84: 22343.7 | L84: 21800.5 | P84: V74_75 | Q84: 49 | S84: V74_75
C85: VJ: Information and communication | G85: 22326.8 | H85: 21310.9 | I85: 18108.9 | J85: 14686.3 | K85: 13610.3 | L85: 11986.2 | P85: V77 | Q85: 50 | S85: V77
C86: VJ: Information and communication | D86: V58_60: Publishing, audiovisual and broadcasting activities | G86: 3355.9 | H86: 2660.5 | I86: 1322.8 | J86: 1009.4 | K86: 635.9 | L86: 103.9 | P86: V78 | Q86: 51 | S86: V78
D87: V58_60: Publishing, audiovisual and broadcasting activities | E87: V58: Publishing activities | F87: V58 | G87: 1782.1 | H87: 1245.6 | I87: 517.7 | J87: 344.2 | K87: 544.9 | L87: 412.3 | P87: V79 | Q87: 52 | S87: V79
E88: V59_60: Audiovisual and broadcasting activities | F88: V59_60 | G88: 1573.8 | H88: 1415 | I88: 805.1 | J88: 665.3 | K88: 91 | L88: -308.4 | P88: V80_82 | Q88: 53 | S88: V80_82
D89: V61: Telecommunications | F89: V61 | G89: 13902 | H89: 13108.2 | I89: 11398.3 | J89: 8420.3 | K89: 7161.2 | L89: 5805.9 | O89: O | P89: VO | Q89: 54 | R89: O | S89: VO
D90: V62_63: IT and other information services | F90: V62_63 | G90: 5068.9 | H90: 5542.2 | I90: 5387.8 | J90: 5256.5 | K90: 5813.2 | L90: 6076.4 | O90: P | P90: VP | Q90: 55 | R90: P | S90: VP
C91: VK: Financial and insurance activities | G91: 30291.5 | H91: 31637 | I91: 32066.6 | J91: 34888.9 | K91: 40989.9 | L91: 37140.8 | O91: Q | P91: V86 | Q91: 56 | S91: V86
C92: VK: Financial and insurance activities | D92: V64: Financial service activities, except insurance and pension funding | F92: V64 | G92: 21785.1 | H92: 21244.3 | I92: 19526 | J92: 22543 | K92: 28286.5 | L92: 24175.6 | P92: V87_88 | Q92: 57 | R92: Q | S92: V87_88
D93: V65: Insurance, reinsurance and pension funding, except compulsory S.S. | F93: V65 | G93: 852.6 | H93: 2176.4 | I93: 3927 | J93: 3378.4 | K93: 3963.8 | L93: 5050.9 | P93: V90_92 | Q93: 58 | S93: V90_92
D94: V66: Activities auxiliary to financial service and insurance activities | F94: V66 | G94: 7653.7 | H94: 8216.2 | I94: 8613.6 | J94: 8967.5 | K94: 8739.6 | L94: 7914.4 | O94: R | P94: V93 | Q94: 59 | R94: J, R, S | S94: V93
C95: VL: Real estate activities | F95: VL | G95: 116564.2 | H95: 120415.5 | I95: 106634.4 | J95: 109662 | K95: 106983.6 | L95: 112364.8 | O95: S+T+U | P95: V94 | Q95: 60 | S95: V94
C96: VL: Real estate activities | D96: V68A: of which: imputed rents of owner-occupied dwellings | G96: .. | H96: .. | I96: .. | J96: 130422 | K96: .. | L96: .. | P96: V95 | Q96: 61 | S96: V95
C97: VM: Professional, scientific and technical activities | G97: 56010.1 | H97: 54367.9 | I97: 54037.3 | J97: 53073.1 | K97: 53086.3 | L97: 53238.2 | P97: V96 | Q97: 62 | S97: V96
C98: VM: Professional, scientific and technical activities | D98: V69_71: Legal, accounting, management, architecture, engineering activities | G98: 43862.8 | H98: 42847.1 | I98: 41855.4 | J98: 41884.7 | K98: 41773.3 | L98: 42183.7 | P98: VT | Q98: 63 | S98: VT
D99: V69_71: Legal, accounting, management, architecture, engineering activities | E99: V69_70: Legal, accounting, head offices, management consultancy activities | F99: V69_70 | G99: 30838.5 | H99: 29800.7 | I99: 29672 | J99: 29477.2 | K99: 30012.4 | L99: 30213.8 | P99: V | Q99: 64 | R99: T | S99: V
E100: V71: Architectural and engineering activities, technical testing and analysis | F100: V71 | G100: 13024.2 | H100: 13046.4 | I100: 12183.4 | J100: 12407.4 | K100: 11760.8 | L100: 11969.9 | Q100: 65 | R100: M+N+U
D101: V72: Scientific research and development | F101: V72 | G101: 592.4 | H101: 411.4 | I101: 609.5 | J101: 533.2 | K101: 66.8 | L101: 42.3
D102: V73_75: Other professional, scientific and technical activities | G102: 11554.9 | H102: 11109.3 | I102: 11572.4 | J102: 10655.2 | K102: 11246.3 | L102: 11012.2
D103: V73_75: Other professional, scientific and technical activities | E103: V73: Advertising and market research | F103: V73 | G103: 2207.8 | H103: 2135 | I103: 2041.9 | J103: 1571.2 | K103: 1839.5 | L103: 1944.9
E104: V74_75: Other professional, scientific and tech. activities, veterinary activities | F104: V74_75 | G104: 9347.2 | H104: 8974.4 | I104: 9530.4 | J104: 9084.1 | K104: 9406.8 | L104: 9067.3
C105: VN: Administrative and support service activities | G105: 10033.5 | H105: 11572.8 | I105: 10332 | J105: 9906.7 | K105: 10843.8 | L105: 10593.1
C106: VN: Administrative and support service activities | D106: V77: Rental and leasing activities | F106: V77 | G106: 76.6 | H106: 50.3 | I106: -231 | J106: -351.5 | K106: 179.4 | L106: 78.4
D107: V78: Employment activities | F107: V78 | G107: 32.3 | H107: 252.6 | I107: 267.6 | J107: -120.7 | K107: -150.8 | L107: 312.8
...

Sheet consumption
A1: Bridge matrix to convert elasticities in coicop to elasticities in industries, and to convert consumption per coicop in consumption per industry
B2: CP01 | C2: CP02 | D2: CP03 | E2: CP041_043 | F2: CP044 | G2: CP045 | H2: CP05 | I2: CP06 | J2: CP071_072 | K2: CP073 | L2: CP08 | M2: CP09 | N2: CP10 | O2: CP11 | P2: CP121 | Q2: CP122_127
A3: A | B3: 0.80856339 | C3: 3.6229471e-05 | D3: 0 | E3: 0 | F3: 1.9008405e-08 | G3: 0.01223122 | H3: 4.4159524e-06 | I3: 0.0043145903 | J3: 0 | K3: 0 | L3: 0 | M3: 0.11387252 | N3: 0 | O3: 0.060973436 | P3: 0 | Q3: 4.1784029e-06 | R3: =SUM(B3:Q3) -> 1
A4: B | B4: 0 | C4: 0 | D4: 0 | E4: 0.12287792 | F4: 0.24545902 | G4: 0.55530243 | H4: 0 | I4: 0 | J4: 0 | K4: 0 | L4: 0 | M4: 0.054342633 | N4: 0 | O4: 0 | P4: 0 | Q4: 0.022017994 | R4: =SUM(B4:Q4) -> 1
A5: C | B5: 0.33127068 | C5: 0.1275798 | D5: 0.19176278 | E5: 0.0037296377 | F5: 7.9869189e-07 | G5: 6.216661e-06 | H5: 0.1391398 | I5: 0.037736473 | J5: 0.038648037 | K5: 0 | L5: 0.013298409 | M5: 0.043769555 | N5: 0 | O5: 0.0098082424 | P5: 0 | Q5: 0.063249561 | R5: =SUM(B5:Q5) -> 1
A6: C19 | B6: 0 | C6: 0 | D6: 0 | E6: 0 | F6: 2.0928001e-07 | G6: 0.24011012 | H6: 0.00013796073 | I6: 0 | J6: 0.75975171 | K6: 0 | L6: 0 | M6: 0 | N6: 0 | O6: 0 | P6: 0 | Q6: 0 | R6: =SUM(B6:Q6) -> 1
A7: C29 | B7: 0 | C7: 0 | D7: 0 | E7: 0 | F7: 0 | G7: 0 | H7: 0.00084870699 | I7: 0.00042678429 | J7: 0.97684942 | K7: 0 | L7: 0 | M7: 0.015649849 | N7: 0 | O7: 0 | P7: 0 | Q7: 0.0062252375 | R7: =SUM(B7:Q7) -> 1
A8: D1 | B8: 0 | C8: 0 | D8: 0 | E8: 0 | F8: 0 | G8: 1 | H8: 0 | I8: 0 | J8: 0 | K8: 0 | L8: 0 | M8: 0 | N8: 0 | O8: 0 | P8: 0 | Q8: 0 | R8: =SUM(B8:Q8) -> 1
A9: D2 | B9: 0 | C9: 0 | D9: 0 | E9: 0 | F9: 0 | G9: 1 | H9: 0 | I9: 0 | J9: 0 | K9: 0 | L9: 0 | M9: 0 | N9: 0 | O9: 0 | P9: 0 | Q9: 0 | R9: =SUM(B9:Q9) -> 1
A10: D3 | B10: 0 | C10: 0 | D10: 0 | E10: 0 | F10: 2.5062424e-05 | G10: 0.99997494 | H10: 0 | I10: 0 | J10: 0 | K10: 0 | L10: 0 | M10: 0 | N10: 0 | O10: 0 | P10: 0 | Q10: 0 | R10: =SUM(B10:Q10) -> 1
A11: E | B11: 0 | C11: 0 | D11: 0 | E11: 2.2139924e-06 | F11: 0.96973932 | G11: 8.0669478e-06 | H11: 1.932009e-06 | I11: 0 | J11: 6.5533943e-06 | K11: 0 | L11: 0 | M11: 5.9310074e-07 | N11: 0 | O11: 0 | P11: 0 | Q11: 0.030241319 | R11: =SUM(B11:Q11) -> 1
A12: F | B12: 0 | C12: 0 | D12: 0 | E12: 0.99974864 | F12: 5.9143422e-05 | G12: 0.00013380028 | H12: 4.2364606e-05 | I12: 0 | J12: 0 | K12: 0 | L12: 1.6053675e-05 | M12: 0 | N12: 0 | O12: 0 | P12: 0 | Q12: 0 | R12: =SUM(B12:Q12) -> 1
A13: G | B13: 0 | C13: 0 | D13: 0 | E13: 0 | F13: 0 | G13: 0 | H13: 0 | I13: 0 | J13: 0.99999978 | K13: 0 | L13: 0 | M13: 2.1575638e-07 | N13: 0 | O13: 0 | P13: 0 | Q13: 0 | R13: =SUM(B13:Q13) -> 1
A14: H | B14: 0 | C14: 0 | D14: 0 | E14: 0 | F14: 0 | G14: 0 | H14: 0 | I14: 0 | J14: 0.0036617984 | K14: 0.93395673 | L14: 0 | M14: 0.00020210196 | N14: 0 | O14: 0 | P14: 0.062179373 | Q14: 0 | R14: =SUM(B14:Q14) -> 1
... A23: T | B23: 0 | C23: 0 | D23: 0 | E23: 3.0896752e-06 | F23: 0 | G23: 0 | H23: 0.13441556 | I23: 0 | J23: 0 | K23: 0 | L23: 0 | M23: 0 | N23: 0 | O23: 0 | P23: 0.86558135 | Q23: 0 | R23: =SUM(B23:Q23) -> 1
A25: Bridge matrix to convert consumption shares in coicop to consumption shares in industries
B26: CP01 | C26: CP02 | D26: CP03 | E26: CP041_043 | F26: CP044 | G26: CP045 | H26: CP05 | I26: CP06 | J26: CP071_072 | K26: CP073 | L26: CP08 | M26: CP09 | N26: CP10 | O26: CP11 | P26: CP121 | Q26: CP122_127
A27: A | B27: 0.2568889 | C27: 4.0218001e-05 | D27: 0 | E27: 0 | F27: 4.9489568e-08 | G27: 0.014537703 | H27: 3.7787024e-06 | I27: 0.0062472771 | J27: 0 | K27: 0 | L27: 0 | M27: 0.072181148 | N27: 0 | O27: 0.029561788 | P27: 0 | Q27: 2.0633928e-06
A28: B | B28: 0 | C28: 0 | D28: 0 | E28: 0.011796333 | F28: 0.22057574 | G28: 0.22780662 | H28: 0 | I28: 0 | J28: 0 | K28: 0 | L28: 0 | M28: 0.011889301 | N28: 0 | O28: 0 | P28: 0 | Q28: 0.0037528407
A29: C | B29: 0.74311107 | C29: 0.99995368 | D29: 0.95073081 | E29: 0.0073243402 | F29: 1.4682051e-05 | G29: 5.2170219e-05 | H29: 0.84063827 | I29: 0.38579091 | J29: 0.11317985 | K29: 0 | L29: 0.14937066 | M29: 0.1958919 | N29: 0 | O29: 0.033575361 | P29: 0 | Q29: 0.22053047
A30: C19 | B30: 0 | C30: 0 | D30: 0 | E30: 0 | F30: 4.5271504e-07 | G30: 0.23711862 | H30: 9.8085092e-05 | I30: 0 | J30: 0.26182015 | K30: 0 | L30: 0 | M30: 0 | N30: 0 | O30: 0 | P30: 0 | Q30: 0
A31: C29 | B31: 0 | C31: 0 | D31: 0 | E31: 0 | F31: 0 | G31: 0 | H31: 0.00053464478 | I31: 0.0004549345 | J31: 0.29827651 | K31: 0 | L31: 0 | M31: 0.00730305 | N31: 0 | O31: 0 | P31: 0 | Q31: 0.0022631679
A32: D1 | B32: 0 | C32: 0 | D32: 0 | E32: 0 | F32: 0 | G32: 0.23825409 | H32: 0 | I32: 0 | J32: 0 | K32: 0 | L32: 0 | M32: 0 | N32: 0 | O32: 0 | P32: 0 | Q32: 0
A33: D2 | B33: 0 | C33: 0 | D33: 0 | E33: 0 | F33: 0 | G33: 0.28147054 | H33: 0 | I33: 0 | J33: 0 | K33: 0 | L33: 0 | M33: 0 | N33: 0 | O33: 0 | P33: 0 | Q33: 0
A34: D3 | B34: 0 | C34: 0 | D34: 0 | E34: 0 | F34: 3.8865645e-08 | G34: 0.00070792938 | H34: 0 | I34: 0 | J34: 0 | K34: 0 | L34: 0 | M34: 0 | N34: 0 | O34: 0 | P34: 0 | Q34: 0
A35: E | B35: 0 | C35: 0 | D35: 0 | E35: 1.6045457e-07 | F35: 0.65786465 | G35: 2.4983243e-06 | H35: 4.3076559e-07 | I35: 0 | J35: 7.082426e-07 | K35: 0 | L35: 0 | M35: 9.7959576e-08 | N35: 0 | O35: 0 | P35: 0 | Q35: 0.003891221
A36: F | B36: 0 | C36: 0 | D36: 0 | E36: 0.073478076 | F36: 4.0689186e-05 | G36: 4.2023053e-05 | H36: 9.5791296e-06 | I36: 0 | J36: 0 | K36: 0 | L36: 6.7484679e-06 | M36: 0 | N36: 0 | O36: 0 | P36: 0 | Q36: 0
A37: G | B37: 0 | C37: 0 | D37: 0 | E37: 0 | F37: 0 | G37: 0 | H37: 0 | I37: 0 | J37: 0.18168307 | K37: 0 | L37: 0 | M37: 5.9907459e-08 | N37: 0 | O37: 0 | P37: 0 | Q37: 0
A38: H | B38: 0 | C38: 0 | D38: 0 | E38: 0 | F38: 0 | G38: 0 | H38: 0 | I38: 0 | J38: 0.00056545289 | K38: 0.99996463 | L38: 0 | M38: 4.7695257e-05 | N38: 0 | O38: 0 | P38: 0.048594923 | Q38: 0
... A47: T | B47: 0 | C47: 0 | D47: 0 | E47: 3.4055098e-07 | F47: 0 | G47: 0 | H47: 0.045580049 | I47: 0 | J47: 0 | K47: 0 | L47: 0 | M47: 0 | N47: 0 | O47: 0 | P47: 0.72004487 | Q47: 0
B48: =+SUM(B27:B47) -> 1 | C48: =+SUM(C27:C47) -> 1 | D48: =+SUM(D27:D47) -> 1 | E48: =+SUM(E27:E47) -> 1 | F48: =+SUM(F27:F47) -> 1 | G48: =+SUM(G27:G47) -> 1 | H48: =+SUM(H27:H47) -> 1 | I48: =+SUM(I27:I47) -> 1 | ... Q48: =+SUM(Q27:Q47) -> 1
A50: Initial total consumption per coicop category
B51: CP01 | C51: CP02 | D51: CP03 | E51: CP041_043 | F51: CP044 | G51: CP045 | H51: CP05 | I51: CP06 | J51: CP071_072 | K51: CP073 | L51: CP08 | M51: CP09 | N51: CP10 | O51: CP11 | P51: CP121 | Q51: CP122_127
B52: 141251.6 | C52: 40426.5 | D52: 63910.3 | E52: 161347.5 | F52: 17236.8 | G52: 37757.1 | H52: 52445.27 | I52: 30993.7 | J52: 108198.8 | K52: 15605.1 | L52: 28209.7 | M52: 70797.8 | N52: 9606.2 | O52: 92562.4 | P52: 21378.63 | Q52: 90876.8 | R52: =+SUM(cons_coicop_initial) -> 982604.2

Sheet covid
A1: 2020 | L1: Source
A3: LFPR gs | B3: 2020 | E3: 2021 | H3: 2022 | L3: Computed KLEMS-adjusted LFPR, based on Eurostat edat_lfs
B4: low | C4: mid | D4: high | E4: low | F4: mid | G4: high | H4: low | I4: mid | J4: high
A5: female | B5: -0.056408198 | C5: -0.03069005 | D5: -0.01748116 | E5: 0.019741292 | F5: 0.020376855 | G5: 0.037318382 | H5: 0.013267893 | I5: 0.011618344 | J5: -0.00010558285
A6: male | B6: -0.029514891 | C6: -0.02080501 | D6: -0.0039245149 | E6: 0.024756791 | F6: 0.024677767 | G6: 0.0092216964 | H6: 0.0095148757 | I6: 0.0087829324 | J6: 0.0022176255
A8: Consumption | B8: 2020 | C8: 2021 | D8: 2022 | L8: Istat, Final consumption expenditure of resident and non-resident households on the economic territory
B9: -0.10977915 | C9: 0.070035318 | D9: 0.13739711
A11: Government consumption | B11: 2020 | C11: 2021 | D11: 2022 | L11: Eurostat, nama_10_gdp
B12: 0.0033942042 | C12: 0.023136315 | D12: 0.0064457643
A14: Exports | B14: 2020 | C14: 2021 | D14: 2022 | L14: Eurostat, nama_10_gdp
B15: -0.13709371 | C15: 0.14085505 | D15: 0.097877736
A17: GFCF | B17: 2020 | C17: 2021 | D17: 2022 | E17: 2023 | L17: Eurostat, nama_10_gdp
B18: -0.07106432 | C18: 0.21543333 | D18: 0.07536156 | E18: 0.084799998
A21: Time2 | B21: 0 | C21: 1 | D21: 2 | E21: 3 | F21: 4 | G21: 5 | H21: 6 | I21: 7 | J21: 8 | K21: 9 | L21: 10 | M21: 11 | N21: 12 | O21: 13
A22: gov | C22: -0.022508933 | D22: -0.023324029 | E22: -0.010782952 | F22: -0.0060011705 | G22: -0.0010477136 | H22: 0.012645008 | I22: 0.002787183 | J22: -0.00019389227 | K22: -0.0042874819 | L22: 0.0033942042 | M22: 0.023136315 | N22: 0.0064457643 | O22: 0.019079849
A23: GFCF | C23: -0.015305524 | D23: -0.098409744 | E23: -0.067291694 | F23: -0.021601333 | G23: 0.019496156 | H23: 0.03847182 | I23: 0.032591412 | J23: 0.032805069 | K23: 0.015792902 | L23: -0.07106432 | M23: 0.21543333 | N23: 0.07536156 | O23: 0.084799998
A24: exp | C24: 0.049328571 | D24: 0.018330119 | E24: 0.0024781082 | F24: 0.025404968 | G24: 0.039856656 | H24: 0.023380541 | I24: 0.053675456 | J24: 0.021295903 | K24: 0.012260525 | L24: -0.13709371 | M24: 0.14085505 | N24: 0.097877736 | O24: 0.0082102889
A25: cons | C25: 0.03222992 | D25: -0.0084244099 | E25: -0.010510836 | F25: 0.0049145471 | G25: 0.021154806 | H25: 0.013174097 | I25: 0.025963167 | J25: 0.019680297 | K25: 0.009639998 | L25: -0.1124341 | M25: 0.075179065 | N25: 0.13143828 | O25: 0.062277817
A27: Output expected shocks
B28: covid shock | C28: covid rebound
A29: A | B29: -0.113609 | C29: 0.111828
A30: B | B30: -0.106128 | C30: 0.115606
A31: C | B31: -0.117868 | C31: 0.125933
A32: C19 | B32: -0.124167 | C32: 0.0976994
A33: C29_30 | B33: -0.119721 | C33: 0.132272
A34: D1 | B34: -0.0927163 | C34: 0.110286
A35: D2 | B35: -0.100635 | C35: 0.0961261
A36: D3 | B36: -0.07889 | C36: 0.165377
A37: E | B37: -0.101382 | C37: 0.110902
A38: F | B38: -0.0454576 | C38: 0.189954
A39: G | B39: -0.103204 | C39: 0.0985951
A40: H49_51 | B40: -0.101124 | C40: 0.0955293
... A49: T | B49: -0.113424 | C49: 0.0432718

Sheet investments
A1: Investment Matrix
B2: A | C2: B | D2: C | E2: C19 | F2: C29_30 | G2: D1 | H2: D2 | I2: D3 | J2: E | K2: F | L2: G | M2: H49_51 | N2: I | O2: J_R_S | P2: K | Q2: L | R2: H_M_N | S2: O | T2: P | U2: Q | V2: T
A3: A | B3: 0.043413299 | C3: 0.00062249142 | D3: 0.00072598691 | E3: 1.0002465e-05 | F3: 0.00149655 | G3: 1.0224543e-05 | H3: 1.0279192e-05 | I3: 1.0289445e-05 | J3: 1.5611137e-05 | K3: 4.5133039e-05 | L3: 3.7500113e-05 | M3: 2.4700363e-05 | N3: 4.3443913e-06 | O3: 0.0023865067 | P3: 0.00044894153 | Q3: 5.0275051e-07 | R3: 0.00069540312 | S3: 8.9097819e-06 | T3: 7.491258e-05 | U3: 0.00052952771 | V3: 0
A4: B | B4: 6.4936897e-06 | C4: 0.05928973 | D4: 0.00085366971 | E4: 1.1761646e-05 | F4: 0.0017597554 | G4: 1.2022782e-05 | H4: 1.2087042e-05 | I4: 1.2099099e-05 | J4: 1.8356742e-05 | K4: 5.3070803e-05 | L4: 4.4095438e-05 | M4: 2.9044534e-05 | N4: 5.1084602e-06 | O4: 0.00083384627 | P4: 0.00052789903 | Q4: 5.9117165e-07 | R4: 0.000817707 | S4: 1.0476788e-05 | T4: 8.8087814e-05 | U4: 0.00062265829 | V4: 0
A5: C | B5: 0.52615539 | C5: 0.18446281 | D5: 0.59809798 | E5: 0.40917184 | F5: 0.29967727 | G5: 0.33421887 | H5: 0.33600523 | I5: 0.33634039 | J5: 0.49758745 | K5: 0.49725702 | L5: 0.20666007 | M5: 0.14593078 | N5: 0.4994738 | O5: 0.24339876 | P5: 0.13062205 | Q5: 0.0063392932 | R5: 0.08308914 | S5: 0.20349553 | T5: 0.37278369 | U5: 0.24723912 | V5: 0
A6: C19 | B6: 0.00040823868 | C6: 0.0005890805 | D6: 0.00091150114 | E6: 0.00089759152 | F6: 0.0013057412 | G6: 0.00026414392 | H6: 0.00026555575 | I6: 0.00026582063 | J6: 0.00039353875 | K6: 0.00041450057 | L6: 0.00018573587 | M6: 0.00012987625 | N6: 0.00038689136 | O6: 0.00069662486 | P6: 0.00042299172 | Q6: 5.2320762e-06 | R6: 0.0005635878 | S6: 0.00016275817 | T6: 0.00034026269 | U6: 0.0005705068 | V6: 0
A7: C29_30 | B7: 0.045980634 | C7: 0.010610364 | D7: 0.027794606 | E7: 0.0031060816 | F7: 0.24816701 | G7: 0.0055381912 | H7: 0.0055677922 | I7: 0.005573346 | J7: 0.092373231 | K7: 0.17042138 | L7: 0.067313586 | M7: 0.65512494 | N7: 0.027706202 | O7: 0.014605156 | P7: 0.01467482 | Q7: 0.0017102917 | R7: 0.071795521 | S7: 0.03869918 | T7: 0.030793635 | U7: 0.020468052 | V7: 0
A8: D1 | B8: 5.438523e-05 | C8: 0.0061303305 | D8: 0.0071495599 | E8: 9.8504834e-05 | F8: 0.014738109 | G8: 0.0081560416 | H8: 0.00010123006 | I8: 0.00010133103 | J8: 0.00015373935 | K8: 0.00044447271 | L8: 0.00036930322 | M8: 0.00024325056 | N8: 4.278381e-05 | O8: 0.0069835368 | P8: 0.0044212014 | Q8: 4.9511153e-06 | R8: 0.006848369 | S8: 8.7744033e-05 | T8: 0.0007377433 | U8: 0.0052148187 | V8: 0
A9: D2 | B9: 1.8491339e-05 | C9: 0.0020843531 | D9: 0.0024308978 | E9: 3.3492298e-05 | F9: 0.0050110548 | G9: 3.4235905e-05 | H9: 0.0027879302 | I9: 3.4453224e-05 | J9: 5.2272401e-05 | K9: 0.00015112367 | L9: 0.00012556555 | M9: 8.2706807e-05 | N9: 1.4546779e-05 | O9: 0.0023744489 | P9: 0.0015032378 | Q9: 1.6834121e-06 | R9: 0.0023284909 | S9: 2.9833554e-05 | T9: 0.00025083762 | U9: 0.001773073 | V9: 0
A10: D3 | B10: 1.1799358e-05 | C10: 0.0013300295 | D10: 0.0015511604 | E10: 2.1371497e-05 | F10: 0.0031975633 | G10: 2.1845994e-05 | H10: 2.1962758e-05 | I10: 0.0017807579 | J10: 3.3355115e-05 | K10: 9.6432294e-05 | L10: 8.0123607e-05 | M10: 5.2775366e-05 | N10: 9.2823268e-06 | O10: 0.0015151402 | P10: 0.00095921884 | Q10: 1.0741883e-06 | R10: 0.0014858144 | S10: 1.9036846e-05 | T10: 0.00016005995 | U10: 0.0011314011 | V10: 0
A11: E | B11: 1.6261043e-05 | C11: 0.001832953 | D11: 0.0021376999 | E11: 2.945269e-05 | F11: 0.0044066564 | G11: 3.0106609e-05 | H11: 3.0267525e-05 | I11: 3.0297717e-05 | J11: 0.0037233812 | K11: 0.00013289619 | L11: 0.00011042071 | M11: 7.2731289e-05 | N11: 1.2792248e-05 | O11: 0.0020880594 | P11: 0.0013219278 | Q11: 1.4803707e-06 | R11: 0.0020476446 | S11: 2.6235239e-05 | T11: 0.00022058334 | U11: 0.0015592173 | V11: 0
A12: F | B12: 0.35396923 | C12: 0.54070718 | D12: 0.1135796 | E12: 0.5307976 | F12: 0.034085978 | G12: 0.55473101 | H12: 0.55769599 | I12: 0.55825228 | J12: 0.33343269 | K12: 0.26631723 | L12: 0.1132676 | M12: 0.074367824 | N12: 0.42338074 | O12: 0.13272684 | P12: 0.37547419 | Q12: 0.9229628 | R12: 0.17476138 | S12: 0.64268914 | T12: 0.3990824 | U12: 0.43423526 | V12: 0
A13: G | B13: 0.0010039665 | C13: 0.11316761 | D13: 0.13198287 | E13: 0.0018184267 | F13: 0.27206959 | G13: 0.0018588 | H13: 0.0018687351 | I13: 0.0018705991 | J13: 0.0028380713 | K13: 0.0082050901 | L13: 0.55221267 | M13: 0.0044904732 | N13: 0.00078980105 | O13: 0.12891804 | P13: 0.081616611 | Q13: 9.1398968e-05 | R13: 0.1264228 | S13: 0.0016197793 | T13: 0.013618947 | U13: 0.096267006 | V13: 0
A14: H49_51 | B14: 0.00010198478 | C14: 0.011495776 | D14: 0.013407065 | E14: 0.00018471916 | F14: 0.027637334 | G14: 0.00018882035 | H14: 0.00018982958 | I14: 0.00019001893 | J14: 0.00028829655 | K14: 0.00083348826 | L14: 0.00069252824 | M14: 0.036948198 | N14: 8.0229456e-05 | O14: 0.013095733 | P14: 0.0082907667 | Q14: 9.2844767e-06 | R14: 0.012842263 | S14: 0.00016454019 | T14: 0.0013834379 | U14: 0.009778981 | V14: 0
... A23: T | B23: 0 | C23: 0 | D23: 0 | E23: 0 | F23: 0 | G23: 0 | H23: 0 | I23: 0 | J23: 0 | K23: 0 | L23: 0 | M23: 0 | N23: 0 | O23: 0 | P23: 0 | Q23: 0 | R23: 0 | S23: 0 | T23: 0 | U23: 0 | V23: 0

Sheet regions
B1: BETA ELASTICITIES | T1: Category shares by regions | AW1: Expenditure shares per COICOP category, region and quintile (betas)
C2: c_01 | D2: c_02 | E2: c_03 | F2: c_041_043 | G2: c_044 | H2: c_045 | I2: c_05 | J2: c_06 | K2: c_071_072 | L2: c_073 | M2: c_08 | N2: c_09 | O2: c_10 | P2: c_11 | Q2: c_121 | R2: c_122_127 | T2: ireg | U2: quint | V2: low_u_f | W2: low_e_f | X2: low_o_f | Y2: low_r_f | Z2: low_u_m | AA2: low_e_m | AB2: low_o_m | AC2: low_r_m | AD2: mid_u_f | AE2: mid_e_f | AF2: mid_o_f | AG2: mid_r_f | AH2: mid_u_m | AI2: mid_e_m | AJ2: mid_o_m | AK2: mid_r_m | AL2: hig_u_f | AM2: hig_e_f | AN2: hig_o_f | AO2: hig_r_f | AP2: hig_u_m | AQ2: hig_e_m | AR2: hig_o_m | AS2: hig_r_m | AT2: capitalist | AU2: child | AW2: irgn | AX2: rgn | AY2: quintile_r | AZ2: sh_01 | BA2: sh_02 | BB2: sh_03 | BC2: sh_041_043 | BD2: sh_044 | BE2: sh_045 | BF2: sh_05r | BG2: sh_06 | BH2: sh_071_072 | BI2: sh_073 | BJ2: sh_08 | BK2: sh_09 | BL2: sh_10 | BM2: sh_11 | BN2: sh_056dom_124 | BO2: sh_121_127
B3: Piemonte_q1 | C3: -1.23368 | D3: -0.0297395 | E3: 0.0536428 | F3: -2.268176 | G3: -0.0980841 | H3: 0.0051238 | I3: 0.3568174 | J3: 0.012668 | K3: -0.0236368 | L3: 0.0088123 | M3: -0.0168448 | N3: -0.0208991 | O3: -0.029201 | P3: -0.1529253 | Q3: -0.0960171 | R3: 0.3132995 | T3: Piemonte | U3: 1 | V3: 0.045789801 | W3: 0.017785103 | X3: 0.020583403 | Y3: 0.014577003 | Z3: 0.032221701 | AA3: 0.015514701 | AB3: 0.0177754 | AC3: 0.0168078 | AD3: 0.025270402 | AE3: 0.007472797 | AF3: 0.016216402 | AG3: 0.0019532042 | AH3: 0.021919505 | AI3: 0.0075513004 | AJ3: 0.016989304 | AK3: 0.0069048041 | AL3: 0.0082378978 | AM3: 0.001889102 | AN3: 0.0082925042 | AO3: 0.0018309962 | AP3: 0.014867002 | AQ3: 0.0016047949 | AR3: 0.0073584958 | AS3: 0.0014913976 | AT3: 0 | AU3: 0.0184062 | AW3: 1 | AX3: Piemonte | AY3: 1 | AZ3: 0.19371434 | BA3: 0.04244254 | BB3: 0.039964338 | BC3: 0.22508274 | BD3: 0.034030143 | BE3: 0.066666925 | BF3: 0.047460339 | BG3: 0.022222383 | BH3: 0.071915569 | BI3: 0.020371656 | BJ3: 0.051012812 | BK3: 0.049482194 | BL3: 0.0088184558 | BM3: 0.050294772 | BN3: 0.0064337802 | BO3: 0.070087008 | BP3: =SUM(AZ3:BO3) -> 1
B4: Valle_d'Ao~1 | C4: -1.06162 | D4: 0.0338689 | E4: 0.1849246 | F4: 0.8950912 | G4: 0.0345932 | H4: -0.0175731 | I4: 0.0314796 | J4: 0.0461337 | K4: 0.0642827 | L4: -0.0499341 | M4: -0.014709 | N4: -0.0393379 | O4: -0.0241268 | P4: -0.0023013 | Q4: 0.3180247 | R4: -0.1057629 | T4: Valle d'Aosta | U4: 1 | V4: 0.00068730112 | W4: 0.000932603 | X4: 0.000793403 | Y4: 0.000442603 | Z4: 0.0006707011 | AA4: 0.000832101 | AB4: 0.0003086 | AC4: 0.0005923 | AD4: 0.00029290204 | AE4: 8.3497e-05 | AF4: 0.000171802 | AG4: 0 | AH4: 0.00085190505 | AI4: 5.38004e-05 | AJ4: 0.00028460404 | AK4: 0 | AL4: 0 | AM4: 0.00011610204 | AN4: 0.00062980417 | AO4: 0 | AP4: 0 | AQ4: 0 | AR4: 0.0010525958 | AS4: 0 | AT4: 0 | AU4: 0.0007338 | AW4: 2 | AX4: Valle d'Aosta | AY4: 1 | AZ4: 0.13718534 | BA4: 0.032049719 | BB4: 0.025744301 | BC4: 0.27962628 | BD4: 0.035757958 | BE4: 0.064590455 | BF4: 0.049116267 | BG4: 0.035208013 | BH4: 0.082273979 | BI4: 0.012604613 | BJ4: 0.031352613 | BK4: 0.037811345 | BL4: 0.0054940396 | BM4: 0.098037052 | BN4: 0.0093533086 | BO4: 0.063794718 | BP4: =SUM(AZ4:BO4) -> 1
B5: Lombardia_q1 | C5: -0.7828116 | D5: -0.1476169 | E5: 0.3686543 | F5: -4.535627 | G5: 0.010787 | H5: 0.1011566 | I5: 0.471736 | J5: 0.1810767 | K5: -0.0583756 | L5: -0.0249649 | M5: -0.0225425 | N5: 0.187877 | O5: -0.0560876 | P5: 0.1150722 | Q5: 0.0146158 | R5: -0.5010709 | T5: Lombardia | U5: 1 | V5: 0.070460901 | W5: 0.034788903 | X5: 0.036518303 | Y5: 0.031421203 | Z5: 0.054701101 | AA5: 0.033402801 | AB5: 0.0490314 | AC5: 0.0233432 | AD5: 0.051360402 | AE5: 0.018718897 | AF5: 0.043815202 | AG5: 0.0088071042 | AH5: 0.044093605 | AI5: 0.0253429 | AJ5: 0.029912904 | AK5: 0.011041604 | AL5: 0.024600498 | AM5: 0.007753102 | AN5: 0.045087004 | AO5: 0.0003820962 | AP5: 0.041417102 | AQ5: 0.012702995 | AR5: 0.032135296 | AS5: 0.0036940976 | AT5: 0 | AU5: 0.0532921 | AW5: 3 | AX5: Lombardia | AY5: 1 | AZ5: 0.19239522 | BA5: 0.04576769 | BB5: 0.043164695 | BC5: 0.24452897 | BD5: 0.02889318 | BE5: 0.074987068 | BF5: 0.039610421 | BG5: 0.019472255 | BH5: 0.07051102 | BI5: 0.017424218 | BJ5: 0.049843815 | BK5: 0.040091829 | BL5: 0.008711942 | BM5: 0.045043701 | BN5: 0.0038270951 | BO5: 0.075726881 | BP5: =SUM(AZ5:BO5) -> 1
B6: Trentino_q1 | C6: -1.617181 | D6: -0.0305569 | E6: 0.1133866 | F6: 0.8604106 | G6: -0.3433128 | H6: 0.0704503 | I6: -0.3553915 | J6: 0.0432003 | K6: -0.0605034 | L6: 0.0342975 | M6: 0.000165 | N6: -0.0440568 | O6: -0.0087157 | P6: 0.9375273 | Q6: 0.1026725 | R6: -0.4790951 | T6: Trentino | U6: 1 | V6: 0.0027293011 | W6: 0.004863703 | X6: 0.003318003 | Y6: 0.003613603 | Z6: 0.0028864011 | AA6: 0.002993401 | AB6: 0.0062528 | AC6: 0.0026172 | AD6: 0.003400302 | AE6: 0.002779197 | AF6: 0.004184202 | AG6: 0.00077660421 | AH6: 0.0024205051 | AI6: 0.0028422004 | AJ6: 0.003563704 | AK6: 0.0023034041 | AL6: 0.0038274978 | AM6: 0.00074000204 | AN6: 0.0063479042 | AO6: 0 | AP6: 0.0018810023 | AQ6: 0.0012067949 | AR6: 0 | AS6: 0.00012599756 | AT6: 0 | AU6: 0.0074654 | AW6: 4 | AX6: Trentino | AY6: 1 | AZ6: 0.13177824 | BA6: 0.03074661 | BB6: 0.04659165 | BC6: 0.23063032 | BD6: 0.025452741 | BE6: 0.049141632 | BF6: 0.052287106 | BG6: 0.019583743 | BH6: 0.048236129 | BI6: 0.013096072 | BJ6: 0.034884717 | BK6: 0.043031845 | BL6: 0.0050779995 | BM6: 0.20113899 | BN6: 0.0036584587 | BO6: 0.064663749 | BP6: =SUM(AZ6:BO6) -> 1
B7: Veneto_q1 | C7: 0.0654574 | D7: 0.0049439 | E7: 0.0831349 | F7: 0.7950794 | G7: -0.024523 | H7: -0.0033563 | I7: -0.2367598 | J7: -0.0094649 | K7: 0.0589558 | L7: -0.0075931 | M7: -0.032526 | N7: -0.0314416 | O7: -0.0054672 | P7: 0.2760588 | Q7: -0.0890091 | R7: -0.0534792 | T7: Veneto | U7: 1 | V7: 0.028210301 | W7: 0.017991403 | X7: 0.024567803 | Y7: 0.011989103 | Z7: 0.019048201 | AA7: 0.024257901 | AB7: 0.024618 | AC7: 0.0132329 | AD7: 0.013163202 | AE7: 0.008987297 | AF7: 0.015413602 | AG7: 0.0016516042 | AH7: 0.018932705 | AI7: 0.0108138 | AJ7: 0.018543904 | AK7: 0.0027208041 | AL7: 0.027643698 | AM7: 0.001623602 | AN7: 0.026449604 | AO7: 0.0004531962 | AP7: 0.00090270227 | AQ7: 0.0033590949 | AR7: 0.0093878958 | AS7: 0.0012533976 | AT7: 0 | AU7: 0.0287521 | AW7: 5 | AX7: Veneto | AY7: 1 | AZ7: 0.17372702 | BA7: 0.031551888 | BB7: 0.058316253 | BC7: 0.24638885 | BD7: 0.02180848 | BE7: 0.072483666 | BF7: 0.041398946 | BG7: 0.032212521 | BH7: 0.06692007 | BI7: 0.011420092 | BJ7: 0.040772161 | BK7: 0.047490613 | BL7: 0.010855291 | BM7: 0.052080983 | BN7: 0.0043411431 | BO7: 0.08823202 | BP7: =SUM(AZ7:BO7) -> 1
B8: Friuli_q1 | C8: -0.7698151 | D8: -0.020877 | E8: 0.0417324 | F8: -0.9696132 | G8: 0.0132959 | H8: 0.0813573 | I8: -0.0425111 | J8: 0.0562961 | K8: 0.0311962 | L8: -0.0034001 | M8: 0.0097736 | N8: 0.0161915 | O8: -0.0313402 | P8: 0.2713317 | Q8: 0.1878776 | R8: -0.1988034 | T8: Friuli | U8: 1 | V8: 0.0055346011 | W8: 0.005125703 | X8: 0.004743703 | Y8: 0.004101903 | Z8: 0.0042304011 | AA8: 0.004217101 | AB8: 0.0093362 | AC8: 0.0030002 | AD8: 0.004638002 | AE8: 0.004198197 | AF8: 0.005611402 | AG8: 0.0017844042 | AH8: 0.0048139051 | AI8: 0.0041232004 | AJ8: 0.005115004 | AK8: 0.0016322041 | AL8: 0.0021199978 | AM8: 0.00041730204 | AN8: 0.0081928042 | AO8: 0.0016765962 | AP8: 0.0061659023 | AQ8: 0.0008659949 | AR8: 0.0064379958 | AS8: 0.00039929756 | AT8: 0 | AU8: 0.0071427 | AW8: 6 | AX8: Friuli | AY8: 1 | AZ8: 0.19501206 | BA8: 0.045944546 | BB8: 0.049644876 | BC8: 0.2309801 | BD8: 0.021557569 | BE8: 0.072119025 | BF8: 0.044962016 | BG8: 0.038342583 | BH8: 0.064736675 | BI8: 0.020847412 | BJ8: 0.031812237 | BK8: 0.044590188 | BL8: 0.012331606 | BM8: 0.051177741 | BN8: 0.0033270657 | BO8: 0.072614306 | BP8: =SUM(AZ8:BO8) -> 1
B9: Liguria_q1 | C9: -1.617887 | D9: -0.0727485 | E9: 0.093035 | F9: 5.125817 | G9: -0.050838 | H9: 0.0327946 | I9: 0.3789817 | J9: 0.1018763 | K9: -0.0367942 | L9: -0.0052709 | M9: 0.0075627 | N9: 0.0230897 | O9: -0.0191317 | P9: -0.5015831 | Q9: 0.0245088 | R9: -0.0101863 | T9: Liguria | U9: 1 | V9: 0.0071292011 | W9: 0.006054903 | X9: 0.007928903 | Y9: 0.005787303 | Z9: 0.0097461011 | AA9: 0.006004001 | AB9: 0.0120002 | AC9: 0.0070283 | AD9: 0.007008702 | AE9: 0.003267697 | AF9: 0.005239802 | AG9: 0.0038928042 | AH9: 0.0075915051 | AI9: 0.0030123004 | AJ9: 0.006054404 | AK9: 0.0022696041 | AL9: 0.0047863978 | AM9: 0.002251602 | AN9: 0.0062445042 | AO9: 0.0014291962 | AP9: 0.0042306023 | AQ9: 0.0050171949 | AR9: 0.0028876958 | AS9: 0.0018637976 | AT9: 0 | AU9: 0.0064435 | AW9: 7 | AX9: Liguria | AY9: 1 | AZ9: 0.18584543 | BA9: 0.043056489 | BB9: 0.03861568 | BC9: 0.30050263 | BD9: 0.041247969 | BE9: 0.067714792 | BF9: 0.031556744 | BG9: 0.020884288 | BH9: 0.046038278 | BI9: 0.029817074 | BJ9: 0.029642574 | BK9: 0.033454194 | BL9: 0.012849501 | BM9: 0.047838502 | BN9: 0.0019706511 | BO9: 0.068965206 | BP9: =SUM(AZ9:BO9) -> 1
B10: Emilia_Rom~1 | C10: -0.1862164 | D10: -0.02665 | E10: 0.0953944 | F10: -0.7910289 | G10: -0.0826772 | H10: 0.009466 | I10: 0.0575996 | J10: 0.0071157 | K10: -0.0016959 | L10: 0.0013932 | M10: 0.0029149 | N10: -0.04234 | O10: -0.0165303 | P10: 0.152248 | Q10: -0.003136 | R10: 0.290529 | T10: Emilia Romagna | U10: 1 | V10: 0.021471901 | W10: 0.021364703 | X10: 0.016006503 | Y10: 0.014558603 | Z10: 0.016911701 | AA10: 0.020755201 | AB10: 0.0130845 | AC10: 0.0118655 | AD10: 0.012858202 | AE10: 0.009128197 | AF10: 0.015811702 | AG10: 0.0059247042 | AH10: 0.011561405 | AI10: 0.0088388004 | AJ10: 0.009941504 | AK10: 0.0047155041 | AL10: 0.021264498 | AM10: 0.004996702 | AN10: 0.014239204 | AO10: 0.0006230962 | AP10: 0.022075602 | AQ10: 0.0060133949 | AR10: 0.014364396 | AS10: 0.00042449756 | AT10: 0 | AU10: 0.0220496 | AW10: 8 | AX10: Emilia Romagna | AY10: 1 | AZ10: 0.17249914 | BA10: 0.042756113 | BB10: 0.049325349 | BC10: 0.23601145 | BD10: 0.027059793 | BE10: 0.064398668 | BF10: 0.043755102 | BG10: 0.026208373 | BH10: 0.076482567 | BI10: 0.014833188 | BJ10: 0.043993942 | BK10: 0.048689569 | BL10: 0.01001988 | BM10: 0.054721611 | BN10: 0.009225725 | BO10: 0.080019531 | BP10: =SUM(AZ10:BO10) -> 1
B11: Toscana_q1 | C11: 0.2487433 | D11: 0.0182924 | E11: -0.0662168 | F11: -0.5518462 | G11: -0.0285374 | H11: 0.0318956 | I11: 0.1907291 | J11: 0.0754401 | K11: -0.0684416 | L11: 0.0102828 | M11: 0.0045376 | N11: 0.0818613 | O11: 0.0017313 | P11: -0.3392033 | Q11: 0.0471437 | R11: 0.0206872 | T11: Toscana | U11: 1 | V11: 0.026069901 | W11: 0.012307403 | X11: 0.017473003 | Y11: 0.015991203 | Z11: 0.025303501 | AA11: 0.015438901 | AB11: 0.0139138 | AC11: 0.0145567 | AD11: 0.015824102 | AE11: 0.008260197 | AF11: 0.011186302 | AG11: 0.0046718042 | AH11: 0.014070805 | AI11: 0.0069151004 | AJ11: 0.011148304 | AK11: 0.0031607041 | AL11: 0.019100198 | AM11: 0.005416402 | AN11: 0.0081127042 | AO11: 0.0013317962 | AP11: 0.010474402 | AQ11: 0.0033304949 | AR11: 0.013277396 | AS11: 0.00035979756 | AT11: 0 | AU11: 0.0149109 | AW11: 9 | AX11: Toscana | AY11: 1 | AZ11: 0.18727964 | BA11: 0.045590898 | BB11: 0.044929148 | BC11: 0.25147914 | BD11: 0.02155882 | BE11: 0.063066767 | BF11: 0.034060624 | BG11: 0.022167667 | BH11: 0.076682631 | BI11: 0.015877251 | BJ11: 0.045503494 | BK11: 0.042320805 | BL11: 0.0084074795 | BM11: 0.058205873 | BN11: 0.0090016613 | BO11: 0.073868098 | BP11: =SUM(AZ11:BO11) -> 1
B12: Umbria_q1 | C12: -1.435818 | D12: 0.1359631 | E12: -0.2562902 | F12: -1.680748 | G12: -0.1249434 | H12: -0.0231329 | I12: 0.5059736 | J12: 0.016534 | K12: 0.1241981 | L12: -0.0028895 | M12: 0.0437512 | N12: 0.0561327 | O12: -0.0081294 | P12: 0.0057852 | Q12: 0.283886 | R12: -0.1034683 | T12: Umbria | U12: 1 | V12: 0.0070817011 | W12: 0.002845303 | X12: 0.003680703 | Y12: 0.003307403 | Z12: 0.0039086011 | AA12: 0.002199901 | AB12: 0.004471 | AC12: 0.0033606 | AD12: 0.006631602 | AE12: 0.001838197 | AF12: 0.004443402 | AG12: 0.0021171042 | AH12: 0.010837605 | AI12: 0.0024833004 | AJ12: 0.006413604 | AK12: 0.0016975041 | AL12: 0.0057314978 | AM12: 0.00034040204 | AN12: 0.0032763042 | AO12: 0.0001156962 | AP12: 0.0043109023 | AQ12: 8.5594898e-05 | AR12: 0.0030501958 | AS12: 0 | AT12: 0 | AU12: 0.0039639 | AW12: 10 | AX12: Umbria | AY12: 1 | AZ12: 0.21682993 | BA12: 0.036080231 | BB12: 0.051588887 | BC12: 0.22883841 | BD12: 0.023888958 | BE12: 0.064633826 | BF12: 0.051771491 | BG12: 0.02899908 | BH12: 0.070584363 | BI12: 0.016517519 | BJ12: 0.034474736 | BK12: 0.038451334 | BL12: 0.0063755743 | BM12: 0.038422908 | BN12: 0.010926438 | BO12: 0.081616322 | BP12: =SUM(AZ12:BO12) -> 1
B13: Marche_q1 | C13: 1.473084 | D13: -0.0006001 | E13: -0.1013741 | F13: 1.58134 | G13: -0.0399505 | H13: 0.0002856 | I13: -0.1431532 | J13: -0.2745579 | K13: -0.0900438 | L13: 0.0033608 | M13: -0.0441795 | N13: -0.2078898 | O13: -0.0255838 | P13: -0.3948775 | Q13: -0.1414664 | R13: -0.115415 | T13: Marche | U13: 1 | V13: 0.0080425011 | W13: 0.005701103 | X13: 0.006201603 | Y13: 0.009191403 | Z13: 0.0083134011 | AA13: 0.005475601 | AB13: 0.0070384 | AC13: 0.0063835 | AD13: 0.006691702 | AE13: 0.002648597 | AF13: 0.005414602 | AG13: 0.0011247042 | AH13: 0.0072040051 | AI13: 0.0024852004 | AJ13: 0.005189904 | AK13: 0.0023402041 | AL13: 0.0057177978 | AM13: 0.002746502 | AN13: 0.0021426042 | AO13: 0.0003667962 | AP13: 0.0056918023 | AQ13: 0.0022203949 | AR13: 0.0039124958 | AS13: 0 | AT13: 0 | AU13: 0.0049076 | AW13: 11 | AX13: Marche | AY13: 1 | AZ13: 0.21418091 | BA13: 0.042390649 | BB13: 0.044143535 | BC13: 0.24238589 | BD13: 0.02200055 | BE13: 0.072907057 | BF13: 0.044248345 | BG13: 0.02255664 | BH13: 0.095900076 | BI13: 0.0076481352 | BJ13: 0.037382672 | BK13: 0.038250886 | BL13: 0.006105822 | BM13: 0.028743389 | BN13: 0.0032914322 | BO13: 0.077864015 | BP13: =SUM(AZ13:BO13) -> 1
B14: Lazio_q1 | C14: -0.1151593 | D14: -0.0499081 | E14: -0.9840317 | F14: 0.4297861 | G14: -0.0124316 | H14: -0.0332781 | I14: 0.3825353 | J14: 0.0346469 | K14: 0.0857691 | L14: 0.0200672 | M14: -0.0218482 | N14: 0.0202009 | O14: -0.0035984 | P14: -0.2455896 | Q14: -0.0864436 | R14: -0.04265 | T14: Lazio | U14: 1 | V14: 0.055764401 | W14: 0.017534903 | X14: 0.026956303 | Y14: 0.014371403 | Z14: 0.057826301 | AA14: 0.016080601 | AB14: 0.0266426 | AC14: 0.014121 | AD14: 0.044372202 | AE14: 0.007679397 | AF14: 0.028682702 | AG14: 0.0082319042 | AH14: 0.068317405 | AI14: 0.0117398 | AJ14: 0.012818304 | AK14: 0.0045427041 | AL14: 0.036411798 | AM14: 0.004948302 | AN14: 0.039915804 | AO14: 0.0003001962 | AP14: 0.017343102 | AQ14: 0.0087507949 | AR14: 0.010030596 | AS14: 0.0026996976 | AT14: 0 | AU14: 0.0226568 | AW14: 12 | AX14: Lazio | AY14: 1 | AZ14: 0.20944877 | BA14: 0.052276067 | BB14: 0.048501733 | BC14: 0.22280529 | BD14: 0.019013788 | BE14: 0.055107253 | BF14: 0.041408427 | BG14: 0.034468404 | BH14: 0.085385776 | BI14: 0.017617565 | BJ14: 0.039685793 | BK14: 0.036633478 | BL14: 0.0037945934 | BM14: 0.04540565 | BN14: 0.0042812869 | BO14: 0.084166125 | BP14: =SUM(AZ14:BO14) -> 1
... B102: Sardegna_q5 | C102: 0.8728597 | D102: -0.0182143 | E102: 0.1829141 | F102: -1.162729 | G102: -0.0030343 | H102: 0.0237361 | I102: 0.5984611 | J102: 0.1317538 | K102: 0.2290593 | L102: -0.0939478 | M102: 0.0106912 | N102: 0.0773547 | O102: 0.00738 | P102: 0.0379006 | Q102: -0.017865 | R102: -0.4719119 | T102: Sardegna | U102: 5 | V102: 0.0012182011 | W102: 0.004341003 | X102: 0.003281003 | Y102: 0.004686703 | Z102: 0 | AA102: 0.005514501 | AB102: 0.0028568 | AC102: 0.0053647 | AD102: 0.001767802 | AE102: 0.008696197 | AF102: 0.003762402 | AG102: 0.014692904 | AH102: 0.0041842051 | AI102: 0.0062488004 | AJ102: 0.002729404 | AK102: 0.0089341041 | AL102: 0.010500398 | AM102: 0.011672702 | AN102: 0.0058545042 | AO102: 0.017134096 | AP102: 0.0027686023 | AQ102: 0.011123595 | AR102: 0.0038084958 | AS102: 0.019727998 | AT102: 0.00963189 | AU102: 0.0037043 | AW102: 20 | AX102: Sardegna | AY102: 5 | AZ102: 0.12104726 | BA102: 0.037982092 | BB102: 0.075487041 | BC102: 0.11186428 | BD102: 0.0087349186 | BE102: 0.021364311 | BF102: 0.052748699 | BG102: 0.027386261 | BH102: 0.12301592 | BI102: 0.016878328 | BJ102: 0.019398997 | BK102: 0.096828296 | BL102: 0.010797576 | BM102: 0.12824035 | BN102: 0.044365266 | BO102: 0.10386039 | BP102: =SUM(AZ102:BO102) -> 1
V103: 1 | W103: 1 | X103: 1 | Y103: 1 | Z103: 1 | AA103: 1 | AB103: 1 | AC103: 1 | AD103: 1 | AE103: 1 | AF103: 1 | AG103: 1 | AH103: 1 | AI103: 1 | AJ103: 1 | AK103: 1 | AL103: 1 | AM103: 1 | AN103: 1 | AO103: 1 | AP103: 1 | AQ103: 1 | AR103: 1 | AS103: 1 | AT103: 1 | AU103: 1
C105: y_rq_mean_adjna | L105: init_static_exp_yd | S105: init_dynamic_exp_yd | Y105: pw_ratio | AG105: deciles
C106: min | D106: q1 | E106: q2 | F106: q3 | G106: q4 | H106: q5 | I106: max | L106: q1 | M106: q2 | N106: q3 | O106: q4 | P106: q5 | S106: q1 | T106: q2 | U106: q3 | V106: q4 | W106: q5 | Z106: q1 | AA106: q2 | AB106: q3 | AC106: q4 | AD106: q5 | AG106: q1 | AH106: q2 | AI106: q3 | AJ106: q4 | AK106: q5
B107: Piemonte | C107: 0 | D107: 22166.9 | E107: 34023.62 | F107: 44755.84 | G107: 49194.36 | H107: 76931.89 | I107: 10000000 | K107: Piemonte | L107: 744.906 | M107: 998.004 | N107: 1108.21 | O107: 1511.81 | P107: 1880.18 | R107: Piemonte | S107: 15908.5 | T107: 28415.6 | U107: 36832 | V107: 49970.4 | W107: 89422.4 | Y107: Piemonte | Z107: 0.3465351 | AA107: 0.6282882 | AB107: 0.8036587 | AC107: 1.725451 | AD107: 1.355922 | AF107: Piemonte | AG107: 2 | AH107: 5 | AI107: 7 | AJ107: 7 | AK107: 9
B108: Valle d'Aosta | C108: 0 | D108: 26942.67 | E108: 32671.34 | F108: 57773.21 | G108: 61339.91 | H108: 51990.99 | I108: 10000000 | K108: Valle d'Aosta | L108: 667.029 | M108: 1515.52 | N108: 1224.37 | O108: 2882.05 | P108: 1477.4 | R108: Valle d'Aosta | S108: 23601.2 | T108: 36401.2 | U108: 51347.1 | V108: 64349.8 | W108: 75685.4 | Y108: Valle d'Aosta | Z108: 0.7169513 | AA108: 1.287533 | AB108: 2.672266 | AC108: 0 | AD108: 1.823655 | AF108: Valle d'Aosta | AG108: 3 | AH108: 4 | AI108: 8 | AJ108: 9 | AK108: 8
B109: Lombardia | C109: 0 | D109: 19023.99 | E109: 30743.01 | F109: 44157.88 | G109: 57789.72 | H109: 108317.8 | I109: 10000000 | K109: Lombardia | L109: 745.355 | M109: 1154.63 | N109: 1360.53 | O109: 1584.58 | P109: 1655.42 | R109: Lombardia | S109: 13992.7 | T109: 24247 | U109: 36322.5 | V109: 54359.3 | W109: 123741 | Y109: Lombardia | Z109: 0.3658846 | AA109: 0.4957481 | AB109: 0.9174579 | AC109: 1.225053 | AD109: 1.918561 | AF109: Lombardia | AG109: 1 | AH109: 4 | AI109: 7 | AJ109: 8 | AK109: 10
B110: Trentino | C110: 0 | D110: 22528.3 | E110: 38631.81 | F110: 50765.33 | G110: 67189.74 | H110: 90025.96 | I110: 10000000 | K110: Trentino | L110: 1350.79 | M110: 1475.58 | N110: 1560.22 | O110: 1722.57 | P110: 1836.59 | R110: Trentino | S110: 18355.3 | T110: 35252.1 | U110: 47951.2 | V110: 65277.6 | W110: 108933 | Y110: Trentino | Z110: 0.4786556 | AA110: 0.9191139 | AB110: 1.110827 | AC110: 1.539036 | AD110: 1.727824 | AF110: Trentino | AG110: 3 | AH110: 6 | AI110: 8 | AJ110: 9 | AK110: 10
B111: Veneto | C111: 0 | D111: 23318.37 | E111: 32820 | F111: 42241.72 | G111: 50147.43 | H111: 86727.02 | I111: 10000000 | K111: Veneto | L111: 991.384 | M111: 1485.53 | N111: 1550.9 | O111: 1798.36 | P111: 2121.36 | R111: Veneto | S111: 17029.8 | T111: 28518.9 | U111: 37459 | V111: 50020.6 | W111: 103802 | Y111: Veneto | Z111: 0.5036669 | AA111: 0.8543023 | AB111: 0.8528557 | AC111: 1.601804 | AD111: 2.08999 | AF111: Veneto | AG111: 3 | AH111: 4 | AI111: 6 | AJ111: 8 | AK111: 10
B112: Friuli | C112: 0 | D112: 19397.41 | E112: 27117.84 | F112: 35686.71 | G112: 48170.7 | H112: 93614.45 | I112: 10000000 | K112: Friuli | L112: 866.881 | M112: 1161.55 | N112: 1227.05 | O112: 1679.77 | P112: 1750.12 | R112: Friuli | S112: 14100.8 | T112: 22568.5 | U112: 32242.6 | V112: 45069.3 | W112: 103763 | Y112: Friuli | Z112: 0.3936133 | AA112: 0.6268176 | AB112: 0.8906466 | AC112: 1.167071 | AD112: 2.662005 | AF112: Friuli | AG112: 1 | AH112: 3 | AI112: 5 | AJ112: 7 | AK112: 10
B113: Liguria | C113: 0 | D113: 20701.63 | E113: 31010.4 | F113: 38606.79 | G113: 47945.59 | H113: 74555.09 | I113: 10000000 | K113: Liguria | L113: 622.293 | M113: 973.064 | N113: 1183.31 | O113: 1518.88 | P113: 1573.02 | R113: Liguria | S113: 16749.4 | T113: 26704.9 | U113: 36198.4 | V113: 49959 | W113: 87699.8 | Y113: Liguria | Z113: 0.3781129 | AA113: 0.747916 | AB113: 0.9690525 | AC113: 1.244796 | AD113: 1.321318 | AF113: Liguria | AG113: 2 | AH113: 4 | AI113: 6 | AJ113: 7 | AK113: 9
B114: Emilia Romagna | C114: 0 | D114: 19861.93 | E114: 32465.8 | F114: 45536.27 | G114: 54056.19 | H114: 91453.4 | I114: 10000000 | K114: Emilia Romagna | L114: 679.896 | M114: 848.462 | N114: 1212.07 | O114: 1494.41 | P114: 1861.13 | R114: Emilia Romagna | S114: 14573.3 | T114: 25913.1 | U114: 36739.9 | V114: 51314.3 | W114: 101962 | Y114: Emilia Romagna | Z114: 0.3893287 | AA114: 0.6058888 | AB114: 0.9415435 | AC114: 1.536584 | AD114: 1.838792 | AF114: Emilia Romagna | AG114: 2 | AH114: 4 | AI114: 7 | AJ114: 8 | AK114: 10
B115: Toscana | C115: 0 | D115: 20449.48 | E115: 33165.91 | F115: 40663.12 | G115: 49482.18 | H115: 88334.02 | I115: 10000000 | K115: Toscana | L115: 771.468 | M115: 1021.36 | N115: 1263.4 | O115: 1740.79 | P115: 1790.64 | R115: Toscana | S115: 15009.5 | T115: 26628.8 | U115: 36123.3 | V115: 46495.5 | W115: 101038 | Y115: Toscana | Z115: 0.3429409 | AA115: 0.5676895 | AB115: 0.634706 | AC115: 1.298115 | AD115: 1.614004 | AF115: Toscana | AG115: 2 | AH115: 5 | AI115: 6 | AJ115: 7 | AK115: 10
B116: Umbria | C116: 0 | D116: 21894.46 | E116: 32035.75 | F116: 40258.71 | G116: 51242.81 | H116: 81522.42 | I116: 10000000 | K116: Umbria | L116: 1016.98 | M116: 1154.31 | N116: 1296.28 | O116: 1590.57 | P116: 1556.25 | R116: Umbria | S116: 16862.4 | T116: 26192.5 | U116: 35520.8 | V116: 50496.5 | W116: 88445.8 | Y116: Umbria | Z116: 0.3895589 | AA116: 0.3348216 | AB116: 0.8460701 | AC116: 0.8075218 | AD116: 1.235505 | AF116: Umbria | AG116: 2 | AH116: 4 | AI116: 6 | AJ116: 8 | AK116: 9
B117: Marche | C117: 0 | D117: 20260.33 | E117: 29604.51 | F117: 38065.39 | G117: 56130.1 | H117: 78525.84 | I117: 10000000 | K117: Marche | L117: 781.564 | M117: 996.88 | N117: 1339.3 | O117: 2036.69 | P117: 2117.56 | R117: Marche | S117: 16219.4 | T117: 25118.2 | U117: 37029.8 | V117: 55751.9 | W117: 92873.8 | Y117: Marche | Z117: 0.25795 | AA117: 0.6327419 | AB117: 1.032997 | AC117: 1.464662 | AD117: 0.9155324 | AF117: Marche | AG117: 2 | AH117: 4 | AI117: 6 | AJ117: 8 | AK117: 9
B118: Lazio | C118: 0 | D118: 19853.08 | E118: 33298.53 | F118: 43164.13 | G118: 53322.57 | H118: 92152.31 | I118: 10000000 | K118: Lazio | L118: 859.728 | M118: 1278.96 | N118: 1487.68 | O118: 1536.11 | P118: 2158.02 | R118: Lazio | S118: 15220.6 | T118: 28448.8 | U118: 38535.1 | V118: 54298.5 | W118: 112686 | Y118: Lazio | Z118: 0.5358432 | AA118: 0.7459989 | AB118: 1.124856 | AC118: 1.077989 | AD118: 2.310704 | AF118: Lazio | AG118: 2 | AH118: 5 | AI118: 6 | AJ118: 8 | AK118: 10
... B126: Sardegna | C126: 0 | D126: 16186.26 | E126: 25414.68 | F126: 33141.43 | G126: 42825.3 | H126: 58558.19 | I126: 10000000 | K126: Sardegna | L126: 819.464 | M126: 1274.63 | N126: 1257.4 | O126: 1443.61 | P126: 1510.15 | R126: Sardegna | S126: 10755.6 | T126: 20037.3 | U126: 31300.2 | V126: 40721.5 | W126: 64867.9 | Y126: Sardegna | Z126: 0.2911498 | AA126: 0.5845348 | AB126: 0.4959975 | AC126: 0.8816931 | AD126: 1.113298 | AF126: Sardegna | AG126: 1 | AH126: 3 | AI126: 4 | AJ126: 6 | AK126: 9
D128: alpha | K128: Number of households | Y128: Non financial profit by regions | AM128: share of self-employment per industry
C129: min | D129: q1 | E129: q2 | F129: q3 | G129: q4 | H129: q5 | I129: max | K129: from istat | R129: calibrated | AN129: share
B130: Piemonte | C130: 1.3690771 | D130: 1.303883 | E130: 1.05492 | F130: 0.9180165 | G130: 0.8619171 | H130: 0.7839947 | I130: 0.4 | L130: q1 | M130: q2 | N130: q3 | O130: q4 | P130: q5 | S130: q1 | T130: q2 | U130: q3 | V130: q4 | W130: q5 | Y130: region | Z130: total_profits_nifi | AA130: regional shares | AC130: region | AD130: q1 | AE130: q2 | AF130: q3 | AG130: q4 | AH130: q5 | AJ130: region | AK130: total rents share | AM130: A | AN130: 0.51331592
B131: Valle d'Aosta | C131: 1.5060433 | D131: 1.434327 | E131: 1.062945 | F131: 1.085444 | G131: 1.034939 | H131: 0.8658059 | I131: 0.4 | K131: Piemonte | L131: 382745.39 | M131: 382745.39 | N131: 382745.39 | O131: 382745.39 | P131: 382745.39 | R131: Piemonte | S131: 383528 | T131: 383079 | U131: 382196 | V131: 384004 | W131: 380919 | Y131: Piemonte | Z131: =AA131*$Z$151 -> 3.1923005e+10 | AA131: 0.098527795 | AC131: Piemonte | AD131: 0.051088571 | AE131: 0.12048889 | AF131: 0.1949077 | AG131: 0.20192076 | AH131: 0.43159408 | AJ131: Piemonte | AK131: 0.37920659 | AM131: B | AN131: 0.081386907
B132: Lombardia | C132: 1.2531698 | D132: 1.193495 | E132: 0.9917337 | F132: 0.9445375 | G132: 0.8703856 | H132: 0.7615244 | I132: 0.4 | K132: Valle d'Aosta | L132: 11541.545 | M132: 11541.545 | N132: 11541.545 | O132: 11541.545 | P132: 11541.545 | R132: Valle d'Aosta | S132: 14167 | T132: 8929 | U132: 14020 | V132: 9427 | W132: 11164 | Y132: Valle d'Aosta | Z132: =AA132*$Z$151 -> 1.1545212e+09 | AA132: 0.0035633371 | AC132: Valle d'Aosta | AD132: 0.14531586 | AE132: 0.049290811 | AF132: 0.44404716 | AG132: 0.20233405 | AH132: 0.15901212 | AJ132: Valle d'Aosta | AK132: 0.38586819 | AM132: C | AN132: 0.13793905
B133: Trentino | C133: 1.3465757 | D133: 1.282453 | E133: 1.115413 | F133: 1.046318 | G133: 0.8797817 | H133: 0.8206871 | I133: 0.4 | K133: Lombardia | L133: 805884.5 | M133: 805884.5 | N133: 805884.5 | O133: 805884.5 | P133: 805884.5 | R133: Lombardia | S133: 807968 | T133: 816296 | U133: 794586 | V133: 816677 | W133: 793896 | Y133: Lombardia | Z133: =AA133*$Z$151 -> 7.2864129e+10 | AA133: 0.22488929 | AC133: Lombardia | AD133: 0 | AE133: 0.038826822 | AF133: 0.12026463 | AG133: 0.21741294 | AH133: 0.6400153 | AJ133: Lombardia | AK133: 0.4219335 | AM133: C19 | AN133: 0.0075120612
B134: Veneto | C134: 1.4555436 | D134: 1.386232 | E134: 1.038793 | F134: 0.9594902 | G134: 0.935582 | H134: 0.7976964 | I134: 0.4 | K134: Trentino | L134: 85165.083 | M134: 85165.083 | N134: 85165.083 | O134: 85165.083 | P134: 85165.083 | R134: Trentino | S134: 87349 | T134: 84797 | U134: 84450 | V134: 88750 | W134: 80477 | Y134: Trentino | Z134: =AA134*$Z$151 -> 8.8091288e+09 | AA134: 0.027188669 | AC134: Trentino | AD134: 0.012501926 | AE134: 0.10163287 | AF134: 0.1853899 | AG134: 0.31606157 | AH134: 0.38441373 | AJ134: Trentino | AK134: 0.35404427 | AM134: C29_30 | AN134: 0.019481404
B135: Friuli | C135: 1.4389851 | D135: 1.370462 | E135: 1.121612 | F135: 0.9849231 | G135: 0.9369236 | H135: 0.7669753 | I135: 0.4 | K135: Veneto | L135: 389069.76 | M135: 389069.76 | N135: 389069.76 | O135: 389069.76 | P135: 389069.76 | R135: Veneto | S135: 404705 | T135: 373656 | U135: 392318 | V135: 392921 | W135: 381749 | Y135: Veneto | Z135: =AA135*$Z$151 -> 2.9430815e+10 | AA135: 0.09083585 | AC135: Veneto | AD135: 0.048337882 | AE135: 0.06498395 | AF135: 0.15171182 | AG135: 0.19530825 | AH135: 0.5396581 | AJ135: Veneto | AK135: 0.43247891 | AM135: D1 | AN135: 0.023653667
B136: Liguria | C136: 1.3358699 | D136: 1.272257 | E136: 1.02476 | F136: 0.888016 | G136: 0.8659047 | H136: 0.7716978 | I136: 0.4 | K136: Friuli | L136: 106600.87 | M136: 106600.87 | N136: 106600.87 | O136: 106600.87 | P136: 106600.87 | R136: Friuli | S136: 108337 | T136: 105960 | U136: 109282 | V136: 106334 | W136: 103092 | Y136: Friuli | Z136: =AA136*$Z$151 -> 6.2415536e+09 | AA136: 0.019264054 | AC136: Friuli | AD136: 0 | AE136: 0 | AF136: 0.079272604 | AG136: 0.18795264 | AH136: 0.79275066 | AJ136: Friuli | AK136: 0.52217475 | AM136: D2 | AN136: 0.023653667
B137: Emilia Romagna | C137: 1.3808277 | D137: 1.315074 | E137: 1.041653 | F137: 0.9266126 | G137: 0.9436029 | H137: 0.7638124 | I137: 0.4 | K137: Liguria | L137: 151574.95 | M137: 151574.95 | N137: 151574.95 | O137: 151574.95 | P137: 151574.95 | R137: Liguria | S137: 153828 | T137: 151641 | U137: 151512 | V137: 150750 | W137: 150144 | Y137: Liguria | Z137: =AA137*$Z$151 -> 8.9499213e+09 | AA137: 0.027623214 | AC137: Liguria | AD137: 0 | AE137: 0.094824924 | AF137: 0.16544541 | AG137: 0.21886452 | AH137: 0.52392706 | AJ137: Liguria | AK137: 0.61677402 | AM137: D3 | AN137: 0.023653667
B138: Toscana | C138: 1.3853543 | D138: 1.319385 | E138: 1.019562 | F138: 0.9753575 | G138: 0.9250857 | H138: 0.8018464 | I138: 0.4 | K138: Emilia Romagna | L138: 377434 | M138: 377434 | N138: 377434 | O138: 377434 | P138: 377434 | R138: Emilia Romagna | S138: 378685 | T138: 376566 | U138: 381916 | V138: 374264 | W138: 375739 | Y138: Emilia Romagna | Z138: =AA138*$Z$151 -> 3.0473227e+10 | AA138: 0.09405317 | AC138: Emilia Romagna | AD138: 0 | AE138: 0.038920837 | AF138: 0.17537386 | AG138: 0.21369065 | AH138: 0.58799584 | AJ138: Emilia Romagna | AK138: 0.4474761 | AM138: E | AN138: 0.03441045
B139: Umbria | C139: 1.3133852 | D139: 1.250843 | E139: 0.9930352 | F139: 0.9619973 | G139: 0.8433328 | H139: 0.7306089 | I139: 0.4 | K139: Toscana | L139: 308882.67 | M139: 308882.67 | N139: 308882.67 | O139: 308882.67 | P139: 308882.67 | R139: Toscana | S139: 308960 | T139: 314631 | U139: 303226 | V139: 312704 | W139: 304892 | Y139: Toscana | Z139: =AA139*$Z$151 -> 2.1293152e+10 | AA139: 0.065719604 | AC139: Toscana | AD139: 0 | AE139: 0.092928632 | AF139: 0.1211761 | AG139: 0.19651423 | AH139: 0.61347887 | AJ139: Toscana | AK139: 0.51460109 | AM139: F | AN139: 0.39430784
B140: Marche | C140: 1.2876056 | D140: 1.226291 | E140: 1.0357 | F140: 0.9503627 | G140: 0.8435444 | H140: 0.8089811 | I140: 0.4 | K140: Umbria | L140: 70794.96 | M140: 70794.96 | N140: 70794.96 | O140: 70794.96 | P140: 70794.96 | R140: Umbria | S140: 71706 | T140: 69894 | U140: 71908 | V140: 71194 | W140: 69273 | Y140: Umbria | Z140: =AA140*$Z$151 -> 4.6985913e+09 | AA140: 0.014501825 | AC140: Umbria | AD140: 0.014551186 | AE140: 0.076777749 | AF140: 0.13965093 | AG140: 0.22535524 | AH140: 0.54366489 | AJ140: Umbria | AK140: 0.45549428 | AM140: G | AN140: 0.41291249
B141: Lazio | C141: 1.3318137 | D141: 1.268394 | E141: 0.9710807 | F141: 0.8896863 | G141: 0.8953859 | H141: 0.7324367 | I141: 0.4 | K141: Marche | L141: 123744 | M141: 123744 | N141: 123744 | O141: 123744 | P141: 123744 | R141: Marche | S141: 124947 | T141: 123395 | U141: 123598 | V141: 124087 | W141: 122692 | Y141: Marche | Z141: =AA141*$Z$151 -> 7.5808459e+09 | AA141: 0.023397673 | AC141: Marche | AD141: 0 | AE141: 0.025567613 | AF141: 0.1038661 | AG141: 0.37944976 | AH141: 0.5430787 | AJ141: Marche | AK141: 0.48290622 | AM141: H49_51 | AN141: 0.21557417
B142: Abruzzo | C142: 1.3813727 | D142: 1.315593 | E142: 1.10561 | F142: 1.007299 | G142: 0.8795131 | H142: 0.8454806 | I142: 0.4 | K142: Lazio | L142: 459668.83 | M142: 459668.83 | N142: 459668.83 | O142: 459668.83 | P142: 459668.83 | R142: Lazio | S142: 459716 | T142: 461923 | U142: 461486 | V142: 457323 | W142: 457896 | Y142: Lazio | Z142: =AA142*$Z$151 -> 3.8917704e+10 | AA142: 0.12011637 | AC142: Lazio | AD142: 0.012449187 | AE142: 0.11410765 | AF142: 0.16218541 | AG142: 0.19452642 | AH142: 0.51673133 | AJ142: Lazio | AK142: 0.46674161 | AM142: I | AN142: 0.30335869
... B149: Sardegna | C149: 1.450742 | D149: 1.381659 | E149: 1.130161 | F149: 1.117485 | G149: 0.9597866 | H149: 0.8677063 | I149: 0.4 | K149: Sicilia | L149: 388003.46 | M149: 388003.46 | N149: 388003.46 | O149: 388003.46 | P149: 388003.46 | R149: Sicilia | S149: 392688 | T149: 388549 | U149: 383758 | V149: 387021 | W149: 388001 | Y149: Sicilia | Z149: =AA149*$Z$151 -> 1.4645185e+10 | AA149: 0.045201187 | AC149: Sicilia | AD149: 0.072459835 | AE149: 0.075005071 | AF149: 0.12246228 | AG149: 0.14967861 | AH149: 0.5803942 | AJ149: Sicilia | AK149: 0.73642053 | AM149: Q | AN149: 0.17121085
K150: Sardegna | L150: 132296.88 | M150: 132296.88 | N150: 132296.88 | O150: 132296.88 | P150: 132296.88 | R150: Sardegna | S150: 136290 | T150: 128773 | U150: 132372 | V150: 132451 | W150: 131598 | Y150: Sardegna | Z150: =AA150*$Z$151 -> 4.6949698e+09 | AA150: 0.014490647 | AC150: Sardegna | AD150: 0 | AE150: 0.056325107 | AF150: 0.2058561 | AG150: 0.32655572 | AH150: 0.42052216 | AJ150: Sardegna | AK150: 0.61739843 | AM150: T | AN150: 0
Y151: Italy | Z151: 324000000000
L153: q1 | M153: q2 | N153: q3 | O153: q4 | P153: q5 | Q153: average number of household members per region
K154: Piemonte | L154: 2.3 | M154: 2.3 | N154: 2.3 | O154: 2.3 | P154: 2.3 | Q154: 2.3
K155: Valle d'Aosta | L155: 2.2 | M155: 2.2 | N155: 2.2 | O155: 2.2 | P155: 2.2 | Q155: 2.2
K156: Lombardia | L156: 2.4 | M156: 2.4 | N156: 2.4 | O156: 2.4 | P156: 2.4 | Q156: 2.4
K157: Trentino | L157: 2.4 | M157: 2.4 | N157: 2.4 | O157: 2.4 | P157: 2.4 | Q157: 2.4 | AA157: 0.099180561 | AD157: 0.058335676 | AE157: 0.13140394 | AF157: 0.20456951 | AG157: 0.20955667 | AH157: 0.39613421
K158: Veneto | L158: 2.5 | M158: 2.5 | N158: 2.5 | O158: 2.5 | P158: 2.5 | Q158: 2.5 | AA158: 0.003596002 | AD158: 0.14892778 | AE158: 0.058458715 | AF158: 0.4371044 | AG158: 0.20695196 | AH158: 0.14855715
K159: Friuli | L159: 2.3 | M159: 2.3 | N159: 2.3 | O159: 2.3 | P159: 2.3 | Q159: 2.3 | AA159: 0.22158872 | AD159: 0 | AE159: 0.051601039 | AF159: 0.12954322 | AG159: 0.2162151 | AH159: 0.61031741
K160: Liguria | L160: 2.1 | M160: 2.1 | N160: 2.1 | O160: 2.1 | P160: 2.1 | Q160: 2.1 | AA160: 0.02730319 | AD160: 0.021207299 | AE160: 0.10870051 | AF160: 0.19073843 | AG160: 0.31412917 | AH160: 0.36522459
K161: Emilia Romagna | L161: 2.3 | M161: 2.3 | N161: 2.3 | O161: 2.3 | P161: 2.3 | Q161: 2.3 | AA161: 0.091539873 | AD161: 0.057361628 | AE161: 0.077976617 | AF161: 0.16294048 | AG161: 0.20328249 | AH161: 0.49843878
K162: Toscana | L162: 2.4 | M162: 2.4 | N162: 2.4 | O162: 2.4 | P162: 2.4 | Q162: 2.4 | AA162: 0.019361915 | AD162: 0 | AE162: 0.0014409484 | AF162: 0.091759424 | AG162: 0.19161955 | AH162: 0.74228465
K163: Umbria | L163: 2.5 | M163: 2.5 | N163: 2.5 | O163: 2.5 | P163: 2.5 | Q163: 2.5 | AA163: 0.027052811 | AD163: 0.0097451245 | AE163: 0.11101691 | AF163: 0.18004912 | AG163: 0.22610646 | AH163: 0.47308239
K164: Marche | L164: 2.5 | M164: 2.5 | N164: 2.5 | O164: 2.5 | P164: 2.5 | Q164: 2.5 | AA164: 0.094535533 | AD164: 0 | AE164: 0.054025227 | AF164: 0.18031485 | AG164: 0.21428889 | AH164: 0.55592557
K165: Lazio | L165: 2.4 | M165: 2.4 | N165: 2.4 | O165: 2.4 | P165: 2.4 | Q165: 2.4 | AA165: 0.065990242 | AD165: 0 | AE165: 0.11203226 | AF165: 0.13560891 | AG165: 0.20261665 | AH165: 0.55734214
K166: Abruzzo | L166: 2.5 | M166: 2.5 | N166: 2.5 | O166: 2.5 | P166: 2.5 | Q166: 2.5 | AA166: 0.014780119 | AD166: 0.027615989 | AE166: 0.0941284 | AF166: 0.15553428 | AG166: 0.22931926 | AH166: 0.49340208
K167: Molise | L167: 2.6 | M167: 2.6 | N167: 2.6 | O167: 2.6 | P167: 2.6 | Q167: 2.6 | AA167: 0.023766706 | AD167: 0 | AE167: 0.047097443 | AF167: 0.11943109 | AG167: 0.37731067 | AH167: 0.48378848
K168: Campania | L168: 2.8 | M168: 2.8 | N168: 2.8 | O168: 2.8 | P168: 2.8 | Q168: 2.8 | AA168: 0.11678257 | AD168: 0.017426476 | AE168: 0.1233913 | AF168: 0.17318123 | AG168: 0.20073675 | AH168: 0.48526425
... K173: Sardegna | L173: 2.5 | M173: 2.5 | N173: 2.5 | O173: 2.5 | P173: 2.5 | Q173: 2.5 | AA173: 0.0047662346 | AD173: 0.030031563 | AE173: 0 | AF173: 0.039745312 | AG173: 0.25519886 | AH173: 0.73595521
AA174: 0.011647787 | AD174: 0.0053973663 | AE174: 0.17212835 | AF174: 0.10374128 | AG174: 0.25809848 | AH174: 0.46063453
AA175: 0.044623547 | AD175: 0.070010738 | AE175: 0.097520818 | AF175: 0.1448936 | AG175: 0.1759232 | AH175: 0.51165163
AA176: 0.015423502 | AD176: 0.0059376147 | AE176: 0.085672291 | AF176: 0.22215956 | AG176: 0.3320535 | AH176: 0.35417703

Sheet finance
B2: per adult national wealth
B3: 2101384.5
B5: % of national wealth by skill
B6: low | C6: middle | D6: high | E6: capitalists
B7: -0.000248 | C7: 0.065737 | D7: 0.256113 | E7: 0.678398
B9: Initial interest rate
B10: 2.02
B14: Time | C14: Spread italy Bonds
B15: 0 | C15: 0.036011583
B16: 1 | C16: 0.045493333
B17: 2 | C17: 0.052631167
B18: 3 | C18: 0.04228325
B19: 4 | C19: 0.027971667
B20: 5 | C20: 0.01821925
B21: 6 | C21: 0.018042833
B22: 7 | C22: 0.024696917
B23: 8 | C23: 0.0297285
B24: 9 | C24: 0.02344175
B25: 10 | C25: 0.016290583
B26: 11 | C26: 0.012951167
B27: 40 | C27: 0.012951167

Sheet labour
D2: coefficient wage dispersion | L2: timeuse, also in sheet timeuse | S2: male share initial is | X2: male share trend is | AC2: skill distribution initial is | AH2: skill distribution trend is | AM2: wages initial gis
E3: male | H3: female | M3: phys | N3: study | O3: paid w | P3: unpaid w | Q3: leisure | T3: low | U3: mid | V3: high | Y3: low | Z3: mid | AA3: high | AD3: low | AE3: mid | AF3: high | AI3: low | AJ3: mid | AK3: high | AN3: male | AQ3: female
E4: low | F4: mid | G4: high | H4: low | I4: mid | J4: high | L4: low_u_f | M4: 11.3837 | N4: 0.154514 | O4: 0.305556 | P4: 7.18316 | Q4: 4.9375 | S4: A | T4: 0.715878 | U4: 0.695194 | V4: 0.615416 | X4: A | Y4: 0.00484402 | Z4: 0.00307339 | AA4: 0.00691112 | AC4: A | AD4: 0.672075 | AE4: 0.295082 | AF4: 0.0328432 | AH4: A | AI4: -0.00767738 | AJ4: 0.00562237 | AK4: 0.00205501 | AN4: low | AO4: mid | AP4: high | AQ4: low | AR4: mid | AS4: high
D5: A | E5: 0.612257 | F5: 0.818503 | G5: 0.617269 | H5: 0.638428 | I5: 0.512021 | J5: 0.926055 | L5: low_e_f | M5: 10.4033 | N5: 0.0720102 | O5: 6.13588 | P5: 4.3341 | Q5: 3.02774 | S5: B | T5: 0.876099 | U5: 0.859065 | V5: 0.674243 | X5: B | Y5: -0.0117069 | Z5: -0.00265703 | AA5: -0.0211025 | AC5: B | AD5: 0.481134 | AE5: 0.395513 | AF5: 0.123353 | AH5: B | AI5: -0.00883485 | AJ5: 0.00126364 | AK5: 0.00757121 | AM5: A | AN5: 7.30396 | AO5: 10.7001 | AP5: 13.1647 | AQ5: 5.52364 | AR5: 9.61248 | AS5: 13.257
D6: B | E6: 0.435526 | F6: 0.464754 | G6: 0.604247 | H6: 0.456336 | I6: 0.425929 | J6: 0.519882 | L6: low_o_f | M6: 11.1842 | N6: 1.60138 | O6: 0.0336405 | P6: 6.25684 | Q6: 4.89616 | S6: C | T6: 0.74382 | U6: 0.727531 | V6: 0.680136 | X6: C | Y6: 0.00315836 | Z6: 0.00240399 | AA6: -0.00688594 | AC6: C | AD6: 0.442529 | AE6: 0.479863 | AF6: 0.0776073 | AH6: C | AI6: -0.00813273 | AJ6: 0.00354467 | AK6: 0.00458807 | AM6: B | AN6: 13.3405 | AO6: 15.4822 | AP6: 22.4451 | AQ6: 10.5338 | AR6: 13.2977 | AS6: 17.5772
D7: C | E7: 0.435526 | F7: 0.464754 | G7: 0.604247 | H7: 0.456336 | I7: 0.425929 | J7: 0.519882 | L7: low_p_f | M7: 12.5375 | N7: 0.00778816 | O7: 0.0738763 | P7: 5.5287 | Q7: 5.82844 | S7: C19 | T7: 0.74382 | U7: 0.727531 | V7: 0.680136 | X7: C19 | Y7: 0.00315836 | Z7: 0.00240399 | AA7: -0.00688594 | AC7: C19 | AD7: 0.442529 | AE7: 0.479863 | AF7: 0.0776073 | AH7: C19 | AI7: -0.00813273 | AJ7: 0.00354467 | AK7: 0.00458807 | AM7: C | AN7: 13.3405 | AO7: 15.4822 | AP7: 22.4451 | AQ7: 10.5338 | AR7: 13.2977 | AS7: 17.5772
D8: C19 | E8: 0.435526 | F8: 0.464754 | G8: 0.604247 | H8: 0.456336 | I8: 0.425929 | J8: 0.519882 | L8: low_u_m | M8: 11.759 | N8: 0.0600601 | O8: 1.69069 | P8: 3.47898 | Q8: 6.97673 | S8: C29 | T8: 0.74382 | U8: 0.727531 | V8: 0.680136 | X8: C29 | Y8: 0.00315836 | Z8: 0.00240399 | AA8: -0.00688594 | AC8: C29 | AD8: 0.442529 | AE8: 0.479863 | AF8: 0.0776073 | AH8: C29 | AI8: -0.00813273 | AJ8: 0.00354467 | AK8: 0.00458807 | AM8: C19 | AN8: 13.3405 | AO8: 15.4822 | AP8: 22.4451 | AQ8: 10.5338 | AR8: 13.2977 | AS8: 17.5772
D9: C29 | E9: 0.435526 | F9: 0.464754 | G9: 0.604247 | H9: 0.456336 | I9: 0.425929 | J9: 0.519882 | L9: low_e_m | M9: 10.5426 | N9: 0.0316612 | O9: 8.28413 | P9: 1.38871 | Q9: 3.72039 | S9: D1 | T9: 0.943169 | U9: 0.8061 | V9: 0.657978 | X9: D1 | Y9: -0.0071469 | Z9: -0.00187432 | AA9: -0.0122479 | AC9: D1 | AD9: 0.179796 | AE9: 0.645167 | AF9: 0.175037 | AH9: D1 | AI9: -0.00384466 | AJ9: -0.00748558 | AK9: 0.0113302 | AM9: C29 | AN9: 13.3405 | AO9: 15.4822 | AP9: 22.4451 | AQ9: 10.5338 | AR9: 13.2977 | AS9: 17.5772
D10: D1 | E10: 0.435526 | F10: 0.464754 | G10: 0.604247 | H10: 0.456336 | I10: 0.425929 | J10: 0.519882 | L10: low_o_m | M10: 11.505 | N10: 2.61377 | O10: 0.194215 | P10: 2.27245 | Q10: 7.38898 | S10: D2 | T10: 0.943169 | U10: 0.8061 | V10: 0.657978 | X10: D2 | Y10: -0.0071469 | Z10: -0.00187432 | AA10: -0.0122479 | AC10: D2 | AD10: 0.179796 | AE10: 0.645167 | AF10: 0.175037 | AH10: D2 | AI10: -0.00384466 | AJ10: -0.00748558 | AK10: 0.0113302 | AM10: D1 | AN10: 13.3405 | AO10: 15.4822 | AP10: 22.4451 | AQ10: 10.5338 | AR10: 13.2977 | AS10: 17.5772
D11: D2 | E11: 0.435526 | F11: 0.464754 | G11: 0.604247 | H11: 0.456336 | I11: 0.425929 | J11: 0.519882 | L11: low_p_m | M11: 12.6685 | N11: 0.00310457 | O11: 0.435458 | P11: 3.39559 | Q11: 7.47712 | S11: D3 | T11: 0.943169 | U11: 0.8061 | V11: 0.657978 | X11: D3 | Y11: -0.0071469 | Z11: -0.00187432 | AA11: -0.0122479 | AC11: D3 | AD11: 0.179796 | AE11: 0.645167 | AF11: 0.175037 | AH11: D3 | AI11: -0.00384466 | AJ11: -0.00748558 | AK11: 0.0113302 | AM11: D2 | AN11: 13.3405 | AO11: 15.4822 | AP11: 22.4451 | AQ11: 10.5338 | AR11: 13.2977 | AS11: 17.5772
D12: D3 | E12: 0.435526 | F12: 0.464754 | G12: 0.604247 | H12: 0.456336 | I12: 0.425929 | J12: 0.519882 | L12: mid_u_f | M12: 11.6779 | N12: 0.602392 | O12: 0.59716 | P12: 5.62631 | Q12: 5.47235 | S12: E | T12: 0.949377 | U12: 0.791337 | V12: 0.579982 | X12: E | Y12: 7.054e-05 | Z12: 0.00239686 | AA12: -0.00174627 | AC12: E | AD12: 0.529256 | AE12: 0.408138 | AF12: 0.0626058 | AH12: E | AI12: -0.00146734 | AJ12: -0.00173 | AK12: 0.00319712 | AM12: D3 | AN12: 13.3405 | AO12: 15.4822 | AP12: 22.4451 | AQ12: 10.5338 | AR12: 13.2977 | AS12: 17.5772
D13: E | E13: 0.435526 | F13: 0.464754 | G13: 0.604247 | H13: 0.456336 | I13: 0.425929 | J13: 0.519882 | L13: mid_e_f | M13: 10.4434 | N13: 0.0508831 | O13: 6.47084 | P13: 3.8566 | Q13: 3.15027 | S13: F | T13: 0.983539 | U13: 0.89184 | V13: 0.797757 | X13: F | Y13: -0.00018156 | Z13: 0.0024578 | AA13: -0.0116784 | AC13: F | AD13: 0.590625 | AE13: 0.372901 | AF13: 0.0364746 | AH13: F | AI13: -0.00502655 | AJ13: 0.00387269 | AK13: 0.00115386 | AM13: E | AN13: 13.3405 | AO13: 15.4822 | AP13: 22.4451 | AQ13: 10.5338 | AR13: 13.2977 | AS13: 17.5772
D14: F | E14: 0.465351 | F14: 0.583853 | G14: 0.724823 | H14: 0.602411 | I14: 0.402124 | J14: 0.441224 | L14: mid_o_f | M14: 11.2257 | N14: 1.79773 | O14: 0.0798274 | P14: 5.69849 | Q14: 5.17125 | S14: G | T14: 0.677029 | U14: 0.54504 | V14: 0.468567 | X14: G | Y14: 0.00299829 | Z14: 0.00139427 | AA14: -0.00146444 | AC14: G | AD14: 0.41236 | AE14: 0.515886 | AF14: 0.071754 | AH14: G | AI14: -0.00761999 | AJ14: 0.00217868 | AK14: 0.0054413 | AM14: F | AN14: 10.6293 | AO14: 12.29 | AP14: 22.8267 | AQ14: 8.70209 | AR14: 13.8769 | AS14: 13.4818
D15: G | E15: 0.490991 | F15: 0.561368 | G15: 0.535373 | H15: 0.463066 | I15: 0.448941 | J15: 0.491294 | L15: mid_p_f | M15: 11.624 | N15: 0.0103306 | O15: 0.286501 | P15: 5.94284 | Q15: 6.11433 | S15: H | T15: 0.920486 | U15: 0.740458 | V15: 0.573661 | X15: H | Y15: -0.00107562 | Z15: 0.00128498 | AA15: -0.00348453 | AC15: H | AD15: 0.41564 | AE15: 0.521307 | AF15: 0.0630528 | AH15: H | AI15: -0.00399098 | AJ15: -0.00042701 | AK15: 0.00441799 | AM15: G | AN15: 11.1089 | AO15: 13.847 | AP15: 15.852 | AQ15: 10.4073 | AR15: 12.2057 | AS15: 15.4729
D16: H | E16: 0.474207 | F16: 0.45651 | G16: 0.52611 | H16: 0.467338 | I16: 0.358451 | J16: 0.40725 | L16: mid_u_m | M16: 11.7754 | N16: 0.474603 | O16: 1.51032 | P16: 2.31746 | Q16: 7.88809 | S16: I | T16: 0.50041 | U16: 0.498425 | V16: 0.367771 | X16: I | Y16: 0.00241683 | Z16: -0.00014764 | AA16: 0.00048759 | AC16: I | AD16: 0.476793 | AE16: 0.477999 | AF16: 0.0452081 | AH16: I | AI16: -0.00756614 | AJ16: 0.00366332 | AK16: 0.00390282 | AM16: H | AN16: 12.8734 | AO16: 16.3151 | AP16: 23.3689 | AQ16: 10.4864 | AR16: 16.1834 | AS16: 17.2064
... D24: Q | E24: 0.581286 | F24: 0.402236 | G24: 0.563971 | H24: 0.466298 | I24: 0.354443 | J24: 0.604426 | L24: hig_u_m | M24: 11.438 | N24: 1.96124 | O24: 1.04651 | P24: 2.53101 | Q24: 6.97287 | S24: T | T24: 0.329334 | U24: 0.378385 | V24: 0.406063 | X24: T | Y24: -0.0189839 | Z24: 0.00073253 | AA24: -0.00311772 | AC24: T | AD24: 0.410918 | AE24: 0.453102 | AF24: 0.135981 | AH24: T | AI24: 0.00106136 | AJ24: -0.00473286 | AK24: 0.00367151 | AM24: Q | AN24: 15.5637 | AO24: 16.6395 | AP24: 31.129 | AQ24: 13.4328 | AR24: 14.9965 | AS24: 20.2955
D25: T | E25: 2.49984 | F25: 0.628882 | G25: 0.596693 | H25: 0.458744 | I25: 0.58205 | J25: 0.53819 | L25: hig_e_m | M25: 10.2468 | N25: 0.0826923 | O25: 8.22019 | P25: 1.46122 | Q25: 3.96154 | AM25: T | AN25: 7.35379 | AO25: 8.11902 | AP25: 11.0322 | AQ25: 4.89549 | AR25: 5.58137 | AS25: 7.13641
L26: hig_o_m | M26: 11.231 | N26: 3.40351 | O26: 0.576023 | P26: 2.10234 | Q26: 6.6579
L27: hig_p_m | M27: 11.6349 | N27: 0.0568783 | O27: 1.43122 | P27: 3.15741 | Q27: 7.63624
L28: cap | M28: 0 | N28: 0 | O28: 0 | P28: 0 | Q28: 0
D33: LFPR initial gs | N33: g lambda impact on skil shares
E34: low | F34: mid | G34: high | O34: low | P34: mid | Q34: hig
D35: female | E35: 0.3615465 | F35: 0.70141515 | G35: 0.86174503 | N35: A | O35: -0.72 | P35: 0.1 | Q35: 3.45863
D36: male | E36: 0.71628976 | F36: 0.89365533 | G36: 0.96640498 | N36: B | O36: -0.314 | P36: 0.1 | Q36: 1.034
N37: C | O37: -1.73066 | P37: 0.1 | Q37: 5.434
D38: sens skill cs | N38: C19 | O38: -0.734 | P38: 0.1 | Q38: 2.54644
E39: low | F39: mid | G39: high | N39: C29 | O39: -0.594 | P39: 0.1 | Q39: 1.80912
D40: p0014 | E40: 0 | F40: 0 | G40: 0 | N40: D | O40: 2.94263 | P40: 0.1 | Q40: -0.694
D41: p1524 | E41: 0.736 | F41: 0.753 | G41: 0.688 | N41: D | O41: 2.94263 | P41: 0.1 | Q41: -0.694
D42: p2544 | E42: 0.736 | F42: 0.753 | G42: 0.688 | N42: D | O42: 2.94263 | P42: 0.1 | Q42: -0.694
D43: p4564 | E43: 0.736 | F43: 0.753 | G43: 0.688 | N43: E | O43: 0.1 | P43: 0.1 | Q43: -2.27428
D44: p65 | E44: 0 | F44: 0 | G44: 0 | N44: F | O44: 0.64 | P44: 0.1 | Q44: -1.20424
N45: G | O45: -1.348 | P45: 0.1 | Q45: 3.93779
N46: H | O46: 0.994 | P46: 0.1 | Q46: -5.53186
D47: trend skills cgs - female | H47: trend skills cgs - male | N47: I | O47: 2.96331 | P47: 0.1 | Q47: -11.3509
E48: low | F48: mid | G48: high | H48: low | I48: mid | J48: high | N48: J_R_S | O48: 2.58211 | P48: 0.1 | Q48: -5.17819
D49: p0014 | E49: 0 | F49: 0 | G49: 0 | H49: 0 | I49: 0 | J49: 0 | N49: K | O49: -7.10457 | P49: 0.1 | Q49: 4.39549
D50: p1524 | E50: -0.01038532 | F50: -0.0023318049 | G50: 0.047113441 | H50: -0.010475111 | I50: 0.0039943756 | J50: 0.058835782 | N50: L | O50: -1.768 | P50: 0.1 | Q50: 4.68
D51: p2544 | E51: -0.051097264 | F51: -0.020760787 | G51: 0.0083834317 | H51: -0.041560228 | I51: -0.013741235 | J51: 0.022549609 | N51: H_M_N | O51: 0.44 | P51: 0.1 | Q51: -1.434
D52: p4564 | E52: -0.011547742 | F52: 0.025287079 | G52: 0.049545147 | H52: -0.0023633325 | I52: 0.021925003 | J52: 0.033737792 | N52: O | O52: -5.11146 | P52: 0.1 | Q52: 4.52467
D53: p65 | E53: -0.0035525321 | F53: 0.078274405 | G53: 0.11394422 | H53: -0.010934113 | I53: 0.061133988 | J53: 0.053610503 | N53: P | O53: 2.17016 | P53: 0.1 | Q53: -1.77519
N54: Q | O54: 1.72208 | P54: 13.2949 | Q54: -2.282
D55: init skill shares cgs - female | H55: init skill shares cgs - male | N55: T | O55: 0 | P55: 0 | Q55: 0
E56: low | F56: mid | G56: high | H56: low | I56: mid | J56: high
D57: p0014 | E57: 0 | F57: 0 | G57: 0 | H57: 0 | I57: 0 | J57: 0
D58: p1524 | E58: 0.51220681 | F58: 0.44766307 | G58: 0.040130115 | H58: 0.56549855 | I58: 0.41320749 | J58: 0.021293968
D59: p2544 | E59: 0.32493738 | F59: 0.46285025 | G59: 0.21221236 | H59: 0.38604361 | I59: 0.4661863 | J59: 0.14777009
D60: p4564 | E60: 0.5607905 | F60: 0.32663587 | G60: 0.11257364 | H60: 0.53477972 | I60: 0.34881938 | J60: 0.1164009
D61: p65 | E61: 0.80013357 | F61: 0.15099265 | G61: 0.048873778 | H61: 0.70186461 | I61: 0.21328199 | J61: 0.084853398
D63: LFPR trends
E64: low | F64: mid | G64: high
D65: female | E65: 0.014655433 | F65: 0.001574996 | G65: 0.0074394036
D66: male | E66: 0.0025768123 | F66: 0.0030031115 | G66: 0.0032582552

Sheet government
C2: employees social contribution | D2: 0.0583 | J2: NP 2010 ('Population by age group and sex 1960-2023 demo_pjangroup__custom_13219747_spreadsheet'"), 65+ male+female | V2: FINLAND SPECIFIC
C3: employers social contribution | D3: 0.223 | J3: 910441
J4: L 2010 ("Employment by Industry and Sex 2007-2022 001_115i_2022_20240608-144719”, Industries total 2010, Employed)
B5: BENEFITS | E5: Millions | F5: People | J5: 2325679
C6: SD per capita | D6: =E6/F6 -> 1337.0393 | E6: 4479000000 | F6: 3349939 | G6: Working age pop total (18-64) | J6: D62OS 2010 ("Social benefits Eurostat COFOG 2000-2022 gov_10a_exp__custom_12289504_spreadsheet)", sheet 9 (old age) + sheet 12 (survivors)
C7: FC per child | D7: =E7/F7 -> 5574.1237 | E7: 6044000000 | F7: 1084296 | G7: Children (0-17) | J7: 20475000000
C8: ub coverage ratio | D8: =F8/G8 -> 0.57210282 | E8: 3950000000 | F8: =ROUND(E8/(2145*12),0) -> 153458 | G8: 268235 | J8: GWB 2010 (D1 Compensation of employees from file 'Input Output 2010-2015 pt_004_201500_20240328-101829')
C9: ub wage ratio | D9: 0.53040729 | J9: 92404000000
C10: pw ratio | D10: =J7/(J9/J5*J3) -> 0.56601912
C11: initial other benefits per capita | D11: 118.53433
B14: FINAL CONSUMPTION | D14: A1 | E14: A2 | F14: A3 | G14: B | H14: C10_12 | I14: C13_15 | J14: C16_17 | K14: C20_22 | L14: C19 | M14: C23 | N14: C24_33 | O14: C26_27 | P14: C31_32 | Q14: D | R14: E | S14: F | T14: G | U14: H | V14: I | W14: J | X14: K | Y14: L | Z14: M_N | AA14: M_N_72 | AB14: M_N_73 | AC14: O | AD14: P | AE14: Q | AF14: R | AG14: S95 | AH14: ST
C15: total final cons expenditure | D15: 7748277.3 | E15: 3800961.5 | F15: 841137.32 | G15: 10000 | H15: 2215000 | I15: 2787000 | J15: 824000 | K15: 118388000 | L15: 15420935 | M15: 310000 | N15: 7817000 | O15: 1197000 | P15: 291000 | Q15: 15724564 | R15: 161000 | S15: 394657000 | T15: 438472000 | U15: 62456000 | V15: 6000000 | W15: 20375000 | X15: 32864740 | Y15: 99030000 | Z15: 495649000 | AA15: 802152000 | AB15: 142000 | AC15: 14460426000 | AD15: 9442560000 | AE15: 16489712000 | AF15: 1159265000 | AG15: 71000 | AH15: -3163000
C16: trend in total final cons exp | D16: 21831207 | E16: 3377931 | F16: 1.1173086e+08 | G16: -1222069 | H16: 3549655.2 | I16: 2.2559017e+08 | J16: -1.6305155e+08 | K16: -11884310 | L16: 99095000 | M16: -98063276 | N16: 3.6193431e+08 | O16: 22979310 | P16: -1.329781e+08 | Q16: 5.8098207e+08 | R16: -1.7872245e+09 | S16: -59911379 | T16: 4.7700672e+08 | U16: -1.519019e+08 | V16: -47276552
B19: OTHER EXPENDITURE
C20: wage ratio | D20: 0.88473775
C21: investment ratio | D21: 0.16203008
C23: inflation target | D23: 0.02
C24: initial i | D24: 0.01
C25: Government consolidated gross debt | D25: 94286000000
C28: VAT rate | D28: A1 | E28: A2 | F28: A3 | G28: B | H28: C10_12 | I28: C13_15 | J28: C16_17 | K28: C20_22 | L28: C19 | M28: C23 | N28: C24_33 | O28: C26_27 | P28: C31_32 | Q28: D | R28: E | S28: F | T28: G | U28: H | V28: I | W28: J | X28: K | Y28: L | Z28: M_N | AA28: M_N_72 | AB28: M_N_73 | AC28: O | AD28: P | AE28: Q | AF28: R | AG28: S95 | AH28: ST
C29: vat effective rates 2010 | D29: 0.062385851 | E29: 0.05374777 | F29: 0.031952753 | G29: 0.10384029 | H29: 0.051120193 | I29: 0.057449673 | J29: 0.033483484 | K29: 0.030125064 | L29: 0.031999384 | M29: 0.025307903 | N29: 0.028748601 | O29: 0.051770586 | P29: 0.013760836 | Q29: 0.022717243 | R29: 0.041214814 | S29: 0.055215629 | T29: 0.043100834 | U29: 0.026087794 | V29: 0.010866905
B33: Personal income tax (Irpef) rates | G33: 2010
C34: Tax bracket | D34: Bracket treshold | E34: tax rate
C35: 0-15000 | D35: 0 | E35: 0.23 | G35: A,* 0
C36: 15000-28000 | D36: 15000 | E36: 0.27 | G36: A,* 15 200
C37: 28000-55000 | D37: 28000 | E37: 0.38 | G37: A,* 6.5
C38: 55000-75000 | D38: 55000 | E38: 0.41 | G38: A,* 22 600
C39: >75000 | D39: 75000 | E39: 0.43 | G39: A,* 17.5
G40: A,* 36 800
C41: Corporate income tax rate (Ires) | G41: A,* 21.5
C42: Year | D42: Year Vensim | E42: tax rate | G42: A,* 66 400
C43: 2010 | D43: =C43-2010 -> 0 | E43: 26 | G43: A,* 30
C44: 2011 | D44: =C44-2010 -> 1 | E44: 26
C45: 2012 | D45: =C45-2010 -> 2 | E45: 24.5
C46: 2013 | D46: =C46-2010 -> 3 | E46: 24.5
C47: 2014 | D47: =C47-2010 -> 4 | E47: 20
C48: 2015 | D48: =C48-2010 -> 5 | E48: 20
C49: 2016 | D49: =C49-2010 -> 6 | E49: 20
C50: 2017 | D50: =C50-2010 -> 7 | E50: 20
C51: 2018 | D51: =C51-2010 -> 8 | E51: 20
C52: 2019 | D52: =C52-2010 -> 9 | E52: 20
C53: 2020 | D53: =C53-2010 -> 10 | E53: 20
C54: 2021 | D54: =C54-2010 -> 11 | E54: 20
C56: Financial income tax rate
C57: Year | D57: Year Vensim | E57: tax rate | F57: Progressive | G57: Prog. threshold, EUR
C58: 2010 | D58: =C58-2010 -> 0 | E58: 0.28
C59: 2011 | D59: =C59-2010 -> 1 | E59: 0.28
C60: 2012 | D60: =C60-2010 -> 2 | E60: 0.3 | F60: 0.32 | G60: 50000
C61: 2013 | D61: =C61-2010 -> 3 | E61: 0.3 | F61: 0.32 | G61: 50000
C62: 2014 | D62: =C62-2010 -> 4 | E62: 0.3 | F62: 0.32 | G62: 40000
C63: 2015 | D63: =C63-2010 -> 5 | E63: 0.3 | F63: 0.33 | G63: 30000
C64: 2016 | D64: =C64-2010 -> 6 | E64: 0.3 | F64: 0.34 | G64: 30000
C65: 2017 | D65: =C65-2010 -> 7 | E65: 0.26
C66: 2018 | D66: =C66-2010 -> 8 | E66: 0.26
C67: 2019 | D67: =C67-2010 -> 9 | E67: 0.26
C68: 2020 | D68: =C68-2010 -> 10 | E68: 0.26
C69: 2021 | D69: =C69-2010 -> 11 | E69: 0.26

Sheet technology
B1: TECHNOLOGY NORMALIZED | AA1: Technology trends
B2: U neg norm | AA2: U | BA2: TREND Gvex
D3: A | E3: B | F3: C | G3: C19 | H3: C29 | I3: D | J3: D | K3: D | L3: E | M3: F | N3: G | O3: H | P3: I | Q3: J_R_S | R3: K | S3: L | T3: H_M_N | U3: O | V3: P | W3: Q | X3: T | AC3: A | AD3: B | AE3: C | AF3: C19 | AG3: C29 | AH3: D | AI3: D | AJ3: D | AK3: E | AL3: F | AM3: G | AN3: H | AO3: I | AP3: J_R_S | AQ3: K | AR3: L | AS3: H_M_N | AT3: O | AU3: P | AV3: Q | AW3: T
B4: Mean | C4: A | D4: -0.36180073 | E4: -0.20031867 | F4: -0.0087983014 | G4: 0.52561112 | H4: -0.26551805 | I4: 0.1611103 | J4: 0.1611103 | K4: 0.1611103 | L4: -0.19164338 | M4: -0.30970444 | N4: -0.18198881 | O4: 0.38612851 | P4: 1.4296994 | Q4: 0.15537279 | R4: 0.34912167 | S4: 0.53556681 | T4: 0.085873257 | U4: 0.1499907 | V4: 1.0359115 | W4: 0.38002154 | X4: 0 | AA4: Mean | AB4: A | AC4: -0.0039270087 | AD4: 0.0071561052 | AE4: -0.0015125974 | AF4: 0.1183522 | AG4: 0.0033771882 | AH4: 0.2479892 | AI4: 0.2479892 | AJ4: 0.2479892 | AK4: 0.06867807 | AL4: 0.0114749 | AM4: -0.0026234051 | AN4: 0.023158891 | AO4: 0.0031002053 | AP4: 0.02020897 | AQ4: 0.020362883 | AR4: 0.012557297 | AS4: 0.014923141 | AT4: 0.025255477 | AU4: 0.037691473 | AV4: 0.011283389 | AW4: -1
C5: B | D5: -0.76138171 | E5: -0.51351095 | F5: -0.81105467 | G5: -0.65191132 | H5: 0.12205429 | I5: -0.6924355 | J5: -0.6924355 | K5: -0.6924355 | L5: 0.17180891 | M5: 0.68818993 | N5: 0.07140648 | O5: 1.3151005 | P5: 0.083126646 | Q5: -0.087643563 | R5: 0.56375368 | S5: 3.6414641 | T5: 1.2766768 | U5: 2.9991308 | V5: 0.75048253 | W5: 5.9087397 | X5: 0 | AB5: B | AC5: -0.042618168 | AD5: -0.079928404 | AE5: -0.042847999 | AF5: -0.025692357 | AG5: 0.036722628 | AH5: -0.039624554 | AI5: -0.039624554 | AJ5: -0.039624554 | AK5: -0.028326763 | AL5: -0.046983265 | AM5: -0.062956601 | AN5: -0.047748453 | AO5: 0.010968224 | AP5: -0.037648975 | AQ5: -0.018248676 | AR5: -0.02782578 | AS5: -0.025267584 | AT5: -0.076384742 | AU5: 0.010355012 | AV5: 0.00074678543 | AW5: -1
C6: C | D6: -0.34168144 | E6: -0.64570129 | F6: -0.31282964 | G6: -0.38807391 | H6: -0.2953421 | I6: -0.06660404 | J6: -0.06660404 | K6: -0.06660404 | L6: -0.18506121 | M6: -0.82557571 | N6: -0.20670111 | O6: -0.45426999 | P6: -0.36083256 | Q6: -0.15574795 | R6: -0.85120689 | S6: 0.69702321 | T6: -0.4401153 | U6: -0.85565151 | V6: -0.32533711 | W6: -0.29129973 | X6: 0 | AB6: C | AC6: 0.0032237911 | AD6: -0.053750667 | AE6: 0.00075078839 | AF6: 0.022530347 | AG6: 0.0035244046 | AH6: -0.0064791638 | AI6: -0.0064791638 | AJ6: -0.0064791638 | AK6: 0.0062707382 | AL6: -0.0015776301 | AM6: 0.015619314 | AN6: -0.009877004 | AO6: -0.0056535438 | AP6: 0.0031157209 | AQ6: -0.010437469 | AR6: -0.015052726 | AS6: 0.022211592 | AT6: -0.017298719 | AU6: -0.014057129 | AV6: 0.022981473 | AW6: -1
C7: C19 | D7: -0.49069922 | E7: -0.30789716 | F7: -0.21364725 | G7: -0.41047495 | H7: -0.43558105 | I7: 0.0033509063 | J7: 0.0033509063 | K7: 0.0033509063 | L7: -0.43811302 | M7: -0.6713821 | N7: -0.30480718 | O7: -0.51955388 | P7: 0.87922617 | Q7: -0.26396752 | R7: -0.41941406 | S7: -0.61232238 | T7: -0.5270835 | U7: -0.50876769 | V7: -0.57186834 | W7: 0.99540344 | X7: 0 | AB7: C19 | AC7: -0.009468082 | AD7: -0.0056667953 | AE7: -0.010623069 | AF7: 0.0050012219 | AG7: -0.026754829 | AH7: -0.0045525283 | AI7: -0.0045525283 | AJ7: -0.0045525283 | AK7: -0.044621875 | AL7: 0.0025252535 | AM7: -0.020315265 | AN7: -0.0047039722 | AO7: -0.0058259802 | AP7: -0.029237868 | AQ7: -0.021723436 | AR7: -0.018298465 | AS7: -0.0076611685 | AT7: -0.03843406 | AU7: -0.026839326 | AV7: 0.0023984146 | AW7: -1
C8: C29 | D8: 1.6412478 | E8: -0.28139162 | F8: -0.10702184 | G8: -0.14248532 | H8: -0.053374917 | I8: -0.22053118 | J8: -0.22053118 | K8: -0.22053118 | L8: -0.036288968 | M8: -0.29006041 | N8: -0.18442488 | O8: -0.25746016 | P8: -0.95172785 | Q8: -0.035196506 | R8: -0.65330842 | S8: 1.7127769 | T8: -0.2057344 | U8: -0.69346512 | V8: -0.20478456 | W8: -0.10057535 | X8: 0 | AB8: C29 | AC8: 0.05572333 | AD8: -0.041182965 | AE8: 0.014143935 | AF8: 0.046908483 | AG8: -0.0024405503 | AH8: 0.025222733 | AI8: 0.025222733 | AJ8: 0.025222733 | AK8: 0.030426608 | AL8: 0.066583641 | AM8: 0.014232152 | AN8: -0.038245929 | AO8: 0.0038983461 | AP8: 0.0019711743 | AQ8: 0.018541729 | AR8: 0.001530054 | AS8: 0.024710649 | AT8: -0.02095803 | AU8: 0.0052597626 | AV8: 0.019473968 | AW8: -1 | AZ8: overall gov trend
C9: D | D9: 0.17098538 | E9: -0.5836582 | F9: -0.57324117 | G9: -0.35661287 | H9: 0.0028566957 | I9: -0.36100757 | J9: -0.36100757 | K9: -0.36100757 | L9: -0.2476352 | M9: -0.47573341 | N9: -0.37392908 | O9: -0.33714967 | P9: -0.59478857 | Q9: 0.10173287 | R9: -0.24865012 | S9: 1.893347 | T9: -0.17851926 | U9: -0.26246525 | V9: -0.45186569 | W9: -0.096236376 | X9: 0 | AB9: D | AC9: 0.0063812524 | AD9: -0.041509712 | AE9: -0.005972488 | AF9: 0.032491744 | AG9: -0.011573879 | AH9: 0.010289078 | AI9: 0.010289078 | AJ9: 0.010289078 | AK9: -0.0025202947 | AL9: 0.00077377465 | AM9: -0.0090177103 | AN9: 0.0035754434 | AO9: 0.00065297788 | AP9: -0.0026451604 | AQ9: 0.010222556 | AR9: -0.020211227 | AS9: 0.014042642 | AT9: -0.0046205627 | AU9: -0.0018193135 | AV9: 0.002321008 | AW9: -1 | AZ9: time | BA9: 0 | BB9: 1 | BC9: 2 | BD9: 3 | BE9: 4 | BF9: 5 | BG9: 6 | BH9: 7 | BI9: 8 | BJ9: 9 | BK9: 10 | BL9: 11 | BM9: 12
C10: D | D10: 0.17098538 | E10: -0.5836582 | F10: -0.57324117 | G10: -0.35661287 | H10: 0.0028566957 | I10: -0.36100757 | J10: -0.36100757 | K10: -0.36100757 | L10: -0.2476352 | M10: -0.47573341 | N10: -0.37392908 | O10: -0.33714967 | P10: -0.59478857 | Q10: 0.10173287 | R10: -0.24865012 | S10: 1.893347 | T10: -0.17851926 | U10: -0.26246525 | V10: -0.45186569 | W10: -0.096236376 | X10: 0 | AB10: D | AC10: 0.0063812524 | AD10: -0.041509712 | AE10: -0.005972488 | AF10: 0.032491744 | AG10: -0.011573879 | AH10: 0.010289078 | AI10: 0.010289078 | AJ10: 0.010289078 | AK10: -0.0025202947 | AL10: 0.00077377465 | AM10: -0.0090177103 | AN10: 0.0035754434 | AO10: 0.00065297788 | AP10: -0.0026451604 | AQ10: 0.010222556 | AR10: -0.020211227 | AS10: 0.014042642 | AT10: -0.0046205627 | AU10: -0.0018193135 | AV10: 0.002321008 | AW10: -1 | AZ10: A | BA10: -0.022508933 | BB10: -0.023324029 | BC10: -0.010782952 | BD10: -0.0060011705 | BE10: -0.0010477136 | BF10: 0.012645008 | BG10: 0.002787183 | BH10: -0.00019389227 | BI10: -0.0042874819 | BJ10: 0.0033942042 | BK10: 0.023136315 | BL10: 0.0064457643 | BM10: 0.019079849
C11: D | D11: 0.17098538 | E11: -0.5836582 | F11: -0.57324117 | G11: -0.35661287 | H11: 0.0028566957 | I11: -0.36100757 | J11: -0.36100757 | K11: -0.36100757 | L11: -0.2476352 | M11: -0.47573341 | N11: -0.37392908 | O11: -0.33714967 | P11: -0.59478857 | Q11: 0.10173287 | R11: -0.24865012 | S11: 1.893347 | T11: -0.17851926 | U11: -0.26246525 | V11: -0.45186569 | W11: -0.096236376 | X11: 0 | AB11: D | AC11: 0.0063812524 | AD11: -0.041509712 | AE11: -0.005972488 | AF11: 0.032491744 | AG11: -0.011573879 | AH11: 0.010289078 | AI11: 0.010289078 | AJ11: 0.010289078 | AK11: -0.0025202947 | AL11: 0.00077377465 | AM11: -0.0090177103 | AN11: 0.0035754434 | AO11: 0.00065297788 | AP11: -0.0026451604 | AQ11: 0.010222556 | AR11: -0.020211227 | AS11: 0.014042642 | AT11: -0.0046205627 | AU11: -0.0018193135 | AV11: 0.002321008 | AW11: -1 | AZ11: B | BA11: -0.022508933 | BB11: -0.023324029 | BC11: -0.010782952 | BD11: -0.0060011705 | BE11: -0.0010477136 | BF11: 0.012645008 | BG11: 0.002787183 | BH11: -0.00019389227 | BI11: -0.0042874819 | BJ11: 0.0033942042 | BK11: 0.023136315 | BL11: 0.0064457643 | BM11: 0.019079849
C12: E | D12: -0.44460548 | E12: -0.81001023 | F12: -0.20872925 | G12: 0.70375224 | H12: -0.34333722 | I12: -0.0018762579 | J12: -0.0018762579 | K12: -0.0018762579 | L12: -0.49068006 | M12: -0.072016896 | N12: -0.34172943 | O12: -0.27212654 | P12: 0.81865601 | Q12: -0.18190936 | R12: -0.52120583 | S12: 0.099500976 | T12: -0.16612585 | U12: -0.55435952 | V12: 0.034721126 | W12: 0.051646804 | X12: 0 | AB12: E | AC12: -0.0012624073 | AD12: -0.05321145 | AE12: 0.0078909267 | AF12: 0.1814128 | AG12: -0.060606302 | AH12: 0.013736906 | AI12: 0.013736906 | AJ12: 0.013736906 | AK12: -0.0076593448 | AL12: 0.021760518 | AM12: -0.0084296129 | AN12: 0.0088603907 | AO12: -0.0019682378 | AP12: 0.015276434 | AQ12: -0.010975483 | AR12: -0.0036690492 | AS12: 0.022332537 | AT12: -0.020631257 | AU12: 0.038557911 | AV12: 0.0076057013 | AW12: -1 | AZ12: C | BA12: -0.022508933 | BB12: -0.023324029 | BC12: -0.010782952 | BD12: -0.0060011705 | BE12: -0.0010477136 | BF12: 0.012645008 | BG12: 0.002787183 | BH12: -0.00019389227 | BI12: -0.0042874819 | BJ12: 0.0033942042 | BK12: 0.023136315 | BL12: 0.0064457643 | BM12: 0.019079849
C13: F | D13: -0.52631187 | E13: -0.49946344 | F13: -0.16042024 | G13: 1.2162724 | H13: 0.67953046 | I13: -0.18307655 | J13: -0.18307655 | K13: -0.18307655 | L13: -0.0093651825 | M13: -0.51085377 | N13: -0.38414897 | O13: -0.33982515 | P13: -0.29724657 | Q13: -0.3536973 | R13: -0.36147058 | S13: -0.53257677 | T13: -0.33618744 | U13: -0.77768015 | V13: -0.57248356 | W13: 0.075265053 | X13: 0 | AB13: F | AC13: 0.0011850581 | AD13: -0.016363564 | AE13: 0.0087031947 | AF13: 0.50821115 | AG13: 0.059551312 | AH13: 0.027594964 | AI13: 0.027594964 | AJ13: 0.027594964 | AK13: 0.012682707 | AL13: -0.01451837 | AM13: -0.0062656087 | AN13: -0.0064144025 | AO13: 0.016477529 | AP13: 0.0068308999 | AQ13: -0.014774803 | AR13: -0.013028286 | AS13: -0.0060294902 | AT13: -0.012100983 | AU13: -0.0032649225 | AV13: 0.023067097 | AW13: -1 | AZ13: C19 | BA13: -0.022508933 | BB13: -0.023324029 | BC13: -0.010782952 | BD13: -0.0060011705 | BE13: -0.0010477136 | BF13: 0.012645008 | BG13: 0.002787183 | BH13: -0.00019389227 | BI13: -0.0042874819 | BJ13: 0.0033942042 | BK13: 0.023136315 | BL13: 0.0064457643 | BM13: 0.019079849
C14: G | D14: -0.23538274 | E14: -0.40805197 | F14: -0.28808877 | G14: -0.33533413 | H14: -0.1071048 | I14: -0.53355382 | J14: -0.53355382 | K14: -0.53355382 | L14: -0.22124827 | M14: -0.61667655 | N14: -0.20362164 | O14: -0.39111705 | P14: 0.053535351 | Q14: -0.16345863 | R14: 0.76074169 | S14: 1.0546377 | T14: -0.28223288 | U14: -0.68380682 | V14: -0.32705329 | W14: -0.39523989 | X14: 0 | AB14: G | AC14: 0.0015853613 | AD14: -0.038092572 | AE14: -0.0026402472 | AF14: 0.026145315 | AG14: -0.013472867 | AH14: 0.0093251146 | AI14: 0.0093251146 | AJ14: 0.0093251146 | AK14: 0.0068633407 | AL14: 0.01007271 | AM14: -0.0055796206 | AN14: 0.0034179589 | AO14: 0.0025312191 | AP14: 0.0082021351 | AQ14: -0.0092782151 | AR14: 0.029592867 | AS14: 0.037148456 | AT14: -0.014108311 | AU14: -0.0073642277 | AV14: 0.0073947036 | AW14: -1 | AZ14: C29 | BA14: -0.022508933 | BB14: -0.023324029 | BC14: -0.010782952 | BD14: -0.0060011705 | BE14: -0.0010477136 | BF14: 0.012645008 | BG14: 0.002787183 | BH14: -0.00019389227 | BI14: -0.0042874819 | BJ14: 0.0033942042 | BK14: 0.023136315 | BL14: 0.0064457643 | BM14: 0.019079849
C15: H | D15: -0.17089341 | E15: -0.34160853 | F15: -0.10023204 | G15: -0.028280311 | H15: 0.30678621 | I15: -0.48713527 | J15: -0.48713527 | K15: -0.48713527 | L15: 0.0041679735 | M15: -0.36294827 | N15: -0.032149369 | O15: -0.61756182 | P15: 0.23844992 | Q15: -0.15455059 | R15: -0.62117548 | S15: -0.50862624 | T15: -0.12494787 | U15: 0.1697898 | V15: -0.3631474 | W15: 0.0037121897 | X15: 0 | AB15: H | AC15: 0.00686949 | AD15: 0.0053673577 | AE15: 0.006543993 | AF15: 0.020234909 | AG15: 0.039794056 | AH15: 0.032565327 | AI15: 0.032565327 | AJ15: 0.032565327 | AK15: 0.015400642 | AL15: 0.0020843077 | AM15: -0.014457538 | AN15: -0.011152831 | AO15: 0.0051213485 | AP15: -0.0055372995 | AQ15: -0.010886045 | AR15: -0.015706889 | AS15: -0.0016082527 | AT15: -0.042973374 | AU15: -0.014897831 | AV15: 0.0055430389 | AW15: -1 | AZ15: D1 | BA15: -0.022508933 | BB15: -0.023324029 | BC15: -0.010782952 | BD15: -0.0060011705 | BE15: -0.0010477136 | BF15: 0.012645008 | BG15: 0.002787183 | BH15: -0.00019389227 | BI15: -0.0042874819 | BJ15: 0.0033942042 | BK15: 0.023136315 | BL15: 0.0064457643 | BM15: 0.019079849
C16: I | D16: 0.024256438 | E16: -0.53176429 | F16: 0.055122405 | G16: 0.24258612 | H16: -0.15095666 | I16: -0.13513196 | J16: -0.13513196 | K16: -0.13513196 | L16: 0.46354046 | M16: -0.21349422 | N16: -0.3612109 | O16: -0.6275574 | P16: -0.56147368 | Q16: -0.29804008 | R16: -0.39976018 | S16: 0.11910074 | T16: -0.20295498 | U16: -0.52737656 | V16: 0.01234924 | W16: 0.05315367 | X16: 0 | AB16: I | AC16: 0.009149771 | AD16: -0.016293444 | AE16: 0.007668615 | AF16: 0.15564575 | AG16: -0.050495877 | AH16: 0.060451993 | AI16: 0.060451993 | AJ16: 0.060451993 | AK16: 0.082658142 | AL16: 0.030561812 | AM16: -0.013957653 | AN16: -0.012660942 | AO16: -0.012560445 | AP16: 0.0033622116 | AQ16: -0.012477723 | AR16: -0.013485327 | AS16: 0.0095727076 | AT16: -0.026927879 | AU16: 0.05095507 | AV16: -0.0097375193 | AW16: -1 | AZ16: D2 | BA16: -0.022508933 | BB16: -0.023324029 | BC16: -0.010782952 | BD16: -0.0060011705 | BE16: -0.0010477136 | BF16: 0.012645008 | BG16: 0.002787183 | BH16: -0.00019389227 | BI16: -0.0042874819 | BJ16: 0.0033942042 | BK16: 0.023136315 | BL16: 0.0064457643 | BM16: 0.019079849
C17: J_R_S | D17: -0.39336471 | E17: -0.36772688 | F17: -0.076849607 | G17: 0.33344525 | H17: 0.0056548225 | I17: 0.70370077 | J17: 0.70370077 | K17: 0.70370077 | L17: 0.40072569 | M17: -0.37085291 | N17: -0.34277587 | O17: -0.15393565 | P17: 0.64764189 | Q17: 0.037258024 | R17: -0.7625459 | S17: 0.8800543 | T17: -0.27456346 | U17: -0.38095802 | V17: 0.11417925 | W17: -0.0034693692 | X17: 0 | AB17: J_R_S | AC17: 0.00035055367 | AD17: -0.0055691809 | AE17: 0.012113002 | AF17: 0.11968852 | AG17: -0.013678056 | AH17: 0.06786039 | AI17: 0.06786039 | AJ17: 0.06786039 | AK17: 0.063512143 | AL17: 0.024589864 | AM17: -0.0023378723 | AN17: 0.0020005641 | AO17: -0.024434121 | AP17: 0.033759874 | AQ17: 0.020695755 | AR17: -0.020458816 | AS17: 0.048009405 | AT17: -0.0058441551 | AU17: 0.054426495 | AV17: 0.0058445188 | AW17: -1 | AZ17: D3 | BA17: -0.022508933 | BB17: -0.023324029 | BC17: -0.010782952 | BD17: -0.0060011705 | BE17: -0.0010477136 | BF17: 0.012645008 | BG17: 0.002787183 | BH17: -0.00019389227 | BI17: -0.0042874819 | BJ17: 0.0033942042 | BK17: 0.023136315 | BL17: 0.0064457643 | BM17: 0.019079849
C18: K | D18: 0.33283644 | E18: -0.42318642 | F18: 0.0028915401 | G18: -0.15371762 | H18: -0.080661034 | I18: -0.036098674 | J18: -0.036098674 | K18: -0.036098674 | L18: -0.040538731 | M18: -0.4608737 | N18: 0.1837216 | O18: -0.31698651 | P18: -0.2397515 | Q18: -0.25175311 | R18: -0.43345337 | S18: 0.070561064 | T18: -0.013451231 | U18: -0.41204592 | V18: 0.30114853 | W18: 0.26329341 | X18: 0 | AB18: K | AC18: 0.023388192 | AD18: 0.013958507 | AE18: 0.012253664 | AF18: 0.044430424 | AG18: 0.017757708 | AH18: 0.039949628 | AI18: 0.039949628 | AJ18: 0.039949628 | AK18: 0.01818385 | AL18: 0.014724591 | AM18: 0.028943968 | AN18: 0.038532946 | AO18: 0.022591632 | AP18: 0.0083628177 | AQ18: -0.0045757975 | AR18: 0.0049600471 | AS18: 0.0024136014 | AT18: -0.0037900688 | AU18: 0.018715809 | AV18: 0.021056157 | AW18: -1 | AZ18: E | BA18: -0.022508933 | BB18: -0.023324029 | BC18: -0.010782952 | BD18: -0.0060011705 | BE18: -0.0010477136 | BF18: 0.012645008 | BG18: 0.002787183 | BH18: -0.00019389227 | BI18: -0.0042874819 | BJ18: 0.0033942042 | BK18: 0.023136315 | BL18: 0.0064457643 | BM18: 0.019079849
C19: L | D19: -0.16055788 | E19: -0.081630063 | F19: 0.1132226 | G19: 0.17882464 | H19: -0.46252741 | I19: -0.50394645 | J19: -0.50394645 | K19: -0.50394645 | L19: 0.008810413 | M19: -0.090539123 | N19: -0.12469728 | O19: -0.071727674 | P19: 0.38705566 | Q19: -0.032539881 | R19: 0.067558654 | S19: 0.20651392 | T19: -0.020751925 | U19: -0.51328139 | V19: 0.012275062 | W19: 0.88740535 | X19: 0 | AB19: L | AC19: 0.029235276 | AD19: 0.055909785 | AE19: 0.015293187 | AF19: 0.025002617 | AG19: 0.0095963616 | AH19: 0.0082915866 | AI19: 0.0082915866 | AJ19: 0.0082915866 | AK19: 0.0047560268 | AL19: 0.033428618 | AM19: 0.0081282566 | AN19: -0.019840612 | AO19: 0.0060546046 | AP19: 0.017766116 | AQ19: 0.0032257233 | AR19: -0.0012788451 | AS19: 0.043190311 | AT19: -0.0080703275 | AU19: 0.027967697 | AV19: 0.038354672 | AW19: -1 | AZ19: F | BA19: -0.022508933 | BB19: -0.023324029 | BC19: -0.010782952 | BD19: -0.0060011705 | BE19: -0.0010477136 | BF19: 0.012645008 | BG19: 0.002787183 | BH19: -0.00019389227 | BI19: -0.0042874819 | BJ19: 0.0033942042 | BK19: 0.023136315 | BL19: 0.0064457643 | BM19: 0.019079849
C20: H_M_N | D20: -0.418023 | E20: -0.69243446 | F20: -0.15691449 | G20: 0.5135773 | H20: 0.47654708 | I20: -0.28466302 | J20: -0.28466302 | K20: -0.28466302 | L20: -0.054210672 | M20: -0.51023218 | N20: -0.60893286 | O20: -0.5291104 | P20: -0.57314743 | Q20: -0.13712604 | R20: 0.13581225 | S20: -0.85160109 | T20: -0.22240067 | U20: -0.35141235 | V20: -0.78120241 | W20: -0.030056844 | X20: 0 | AB20: H_M_N | AC20: 0.0082818077 | AD20: -0.032408179 | AE20: 0.00063825362 | AF20: 0.14255616 | AG20: 0.044051143 | AH20: 0.031442039 | AI20: 0.031442039 | AJ20: 0.031442039 | AK20: 0.020321502 | AL20: 0.007412579 | AM20: -0.012372953 | AN20: -0.0030044897 | AO20: 0.0038946527 | AP20: -0.0093418188 | AQ20: -0.025500516 | AR20: -0.022185263 | AS20: -0.021365613 | AT20: -0.034908536 | AU20: -0.0043422173 | AV20: 0.0046898334 | AW20: -1 | AZ20: G | BA20: -0.022508933 | BB20: -0.023324029 | BC20: -0.010782952 | BD20: -0.0060011705 | BE20: -0.0010477136 | BF20: 0.012645008 | BG20: 0.002787183 | BH20: -0.00019389227 | BI20: -0.0042874819 | BJ20: 0.0033942042 | BK20: 0.023136315 | BL20: 0.0064457643 | BM20: 0.019079849
... C24: T | D24: 8.1808739 | E24: -0.80274588 | F24: 2.4754161 | G24: -0.11790701 | H24: -0.26353881 | I24: 0.1876454 | J24: 0.1876454 | K24: 0.1876454 | L24: -0.067464206 | M24: 3.7690467 | N24: 2.3656454 | O24: -0.43492314 | P24: -0.028560598 | Q24: 4.1123365 | R24: 0.69084288 | S24: 4.015212 | T24: 2.1132308 | U24: 8.183416 | V24: 0.88205012 | W24: 55.177294 | X24: 0 | AB24: T | AC24: 0.19626032 | AD24: -0.014191426 | AE24: 0.036889484 | AF24: 0.18291363 | AG24: 0.064187074 | AH24: 0.42222563 | AI24: 0.42222563 | AJ24: 0.42222563 | AK24: 0.022837435 | AL24: 0.13660403 | AM24: 0.025268541 | AN24: 0.024531668 | AO24: 0.045042197 | AP24: 0.033309658 | AQ24: 0.17336437 | AR24: 0.039482721 | AS24: 0.0497132 | AT24: 0.0018437196 | AU24: 0.015786263 | AV24: 0.34257362 | AW24: -1 | AZ24: K | BA24: -0.022508933 | BB24: -0.023324029 | BC24: -0.010782952 | BD24: -0.0060011705 | BE24: -0.0010477136 | BF24: 0.012645008 | BG24: 0.002787183 | BH24: -0.00019389227 | BI24: -0.0042874819 | BJ24: 0.0033942042 | BK24: 0.023136315 | BL24: 0.0064457643 | BM24: 0.019079849
B25: Median | C25: A | D25: -0.35696213 | E25: -0.97448112 | F25: -0.031693318 | G25: 0.82716826 | H25: -0.29576676 | I25: -0.29570135 | J25: -0.29570135 | K25: -0.29570135 | L25: -0.27257076 | M25: -0.1064103 | N25: -0.20418033 | O25: -0.071779054 | P25: -0.026805927 | Q25: 1.8438509 | R25: 0.23270294 | S25: 0.22473277 | T25: -0.78791752 | U25: -0.51907473 | V25: 0.34500901 | W25: 0.38709822 | X25: 0 | AZ25: L | BA25: -0.022508933 | BB25: -0.023324029 | BC25: -0.010782952 | BD25: -0.0060011705 | BE25: -0.0010477136 | BF25: 0.012645008 | BG25: 0.002787183 | BH25: -0.00019389227 | BI25: -0.0042874819 | BJ25: 0.0033942042 | BK25: 0.023136315 | BL25: 0.0064457643 | BM25: 0.019079849
C26: B | D26: -0.82726957 | E26: -0.95226018 | F26: -0.93461062 | G26: -0.65098555 | H26: -0.75159081 | I26: -0.71820482 | J26: -0.71820482 | K26: -0.71820482 | L26: -0.80595169 | M26: -1.4033272 | N26: -1.2685517 | O26: 1.1444541 | P26: -0.060093927 | Q26: 1.4751077 | R26: -0.082676688 | S26: -0.64908146 | T26: -2.9551734 | U26: -2.3143145 | V26: 0.067041302 | W26: 1.8523204 | X26: 0 | AA26: Median | AB26: A | AC26: 0.0030471799 | AD26: -0.0088251499 | AE26: -0.0038833045 | AF26: 0.071845842 | AG26: -0.01260689 | AH26: 0.023861747 | AI26: 0.023861747 | AJ26: 0.023861747 | AK26: 0.014121348 | AL26: -0.017109879 | AM26: -0.0111622 | AN26: 0.0086831287 | AO26: -0.014368673 | AP26: 0.0060449305 | AQ26: -0.0080772596 | AR26: 0.010045188 | AS26: -0.0028531294 | AT26: -0.015339683 | AU26: 0.026036047 | AV26: 0.016075449 | AW26: -1 | AZ26: H_M_N | BA26: -0.022508933 | BB26: -0.023324029 | BC26: -0.010782952 | BD26: -0.0060011705 | BE26: -0.0010477136 | BF26: 0.012645008 | BG26: 0.002787183 | BH26: -0.00019389227 | BI26: -0.0042874819 | BJ26: 0.0033942042 | BK26: 0.023136315 | BL26: 0.0064457643 | BM26: 0.019079849
C27: C | D27: -0.27402039 | E27: -0.77592554 | F27: -0.14938009 | G27: -0.099015072 | H27: -0.17947257 | I27: -0.16230445 | J27: -0.16230445 | K27: -0.16230445 | L27: -0.24887669 | M27: -0.63443343 | N27: -0.074895156 | O27: -0.86383699 | P27: -0.1708911 | Q27: -0.33170678 | R27: -0.13018965 | S27: -0.97455994 | T27: 0.25672529 | U27: -0.95707491 | V27: -0.27005711 | W27: -0.26648652 | X27: 0 | AB27: B | AC27: -0.033267579 | AD27: -0.040464993 | AE27: -0.026897525 | AF27: -0.013592291 | AG27: -0.035022861 | AH27: -0.037836713 | AI27: -0.037836713 | AJ27: -0.037836713 | AK27: -0.04379875 | AL27: -0.050332699 | AM27: -0.05661487 | AN27: -0.055414291 | AO27: -0.030527137 | AP27: -0.04703564 | AQ27: -0.043683473 | AR27: -0.036661777 | AS27: -0.038754222 | AT27: -0.077098055 | AU27: -0.02618251 | AV27: -0.040642782 | AW27: -1 | AZ27: O | BA27: -0.022508933 | BB27: -0.023324029 | BC27: -0.010782952 | BD27: -0.0060011705 | BE27: -0.0010477136 | BF27: 0.012645008 | BG27: 0.002787183 | BH27: -0.00019389227 | BI27: -0.0042874819 | BJ27: 0.0033942042 | BK27: 0.023136315 | BL27: 0.0064457643 | BM27: 0.019079849
C28: C19 | D28: -0.54547761 | E28: -0.93089165 | F28: -0.23394231 | G28: -0.48905982 | H28: -0.46151118 | I28: -0.053311023 | J28: -0.053311023 | K28: -0.053311023 | L28: -0.5891059 | M28: -0.86182133 | N28: -0.4049583 | O28: -0.31409573 | P28: -0.4265157 | Q28: -1.6075974 | R28: -0.14391536 | S28: -0.45956116 | T28: -1.7934981 | U28: -1.0692186 | V28: -0.74186787 | W28: -0.015153037 | X28: 0 | AB28: C | AC28: 0.0064561284 | AD28: -0.010942095 | AE28: 0.0060542493 | AF28: 0.013599129 | AG28: 0.0068616264 | AH28: 0.001662593 | AI28: 0.001662593 | AJ28: 0.001662593 | AK28: 0.0079802471 | AL28: -0.0062146013 | AM28: 0.0084402223 | AN28: 0.0012630933 | AO28: -0.0056248745 | AP28: -0.00096853362 | AQ28: -0.0096381103 | AR28: -0.016461755 | AS28: 0.008699017 | AT28: -0.019107355 | AU28: 0.0016223732 | AV28: 0.022322426 | AW28: -1 | AZ28: P | BA28: -0.022508933 | BB28: -0.023324029 | BC28: -0.010782952 | BD28: -0.0060011705 | BE28: -0.0010477136 | BF28: 0.012645008 | BG28: 0.002787183 | BH28: -0.00019389227 | BI28: -0.0042874819 | BJ28: 0.0033942042 | BK28: 0.023136315 | BL28: 0.0064457643 | BM28: 0.019079849
C29: C29 | D29: 0.31160657 | E29: -1.0236792 | F29: -0.11657224 | G29: -0.32782975 | H29: -0.21565562 | I29: -0.53833951 | J29: -0.53833951 | K29: -0.53833951 | L29: 0.087106371 | M29: -0.44507185 | N29: -0.077875037 | O29: -2.0399261 | P29: -0.31734207 | Q29: -1.2618671 | R29: -0.088002653 | S29: -1.4287125 | T29: 0.91317964 | U29: -1.2092584 | V29: -0.26930486 | W29: -0.10023294 | X29: 0 | AB29: C19 | AC29: -0.017128575 | AD29: -0.020092589 | AE29: -0.013211775 | AF29: 0.0027331764 | AG29: -0.021379188 | AH29: -0.013567178 | AI29: -0.013567178 | AJ29: -0.013567178 | AK29: -0.010430843 | AL29: -0.0068426227 | AM29: -0.018677266 | AN29: -0.018779934 | AO29: -0.017988132 | AP29: -0.016880438 | AQ29: -0.017097179 | AR29: -0.022139986 | AS29: -0.019242239 | AT29: -0.02334372 | AU29: -0.026870275 | AV29: 0.0045752792 | AW29: -1 | AZ29: Q | BA29: -0.022508933 | BB29: -0.023324029 | BC29: -0.010782952 | BD29: -0.0060011705 | BE29: -0.0010477136 | BF29: 0.012645008 | BG29: 0.002787183 | BH29: -0.00019389227 | BI29: -0.0042874819 | BJ29: 0.0033942042 | BK29: 0.023136315 | BL29: 0.0064457643 | BM29: 0.019079849
C30: D | D30: 0.14619646 | E30: -0.69382932 | F30: -0.59268193 | G30: -0.62252132 | H30: -0.067537605 | I30: -0.61406322 | J30: -0.61406322 | K30: -0.61406322 | L30: -0.27669831 | M30: -0.50448059 | N30: -0.48920778 | O30: -0.24493348 | P30: -0.12948699 | Q30: -0.59363236 | R30: 0.18441659 | S30: -0.54790076 | T30: -1.5384863 | U30: -0.88045133 | V30: -0.24999775 | W30: -0.085576957 | X30: 0 | AB30: C29 | AC30: -0.015725754 | AD30: -0.012222061 | AE30: 0.011296785 | AF30: 0.064452374 | AG30: 0.0035822049 | AH30: 0.020032677 | AI30: 0.020032677 | AJ30: 0.020032677 | AK30: 0.014067896 | AL30: 0.0012504297 | AM30: 0.023109522 | AN30: -0.015738251 | AO30: 0.011195873 | AP30: 0.0029260223 | AQ30: -0.0030531966 | AR30: -0.0071401254 | AS30: 0.021029317 | AT30: -0.04332697 | AU30: -0.0036613419 | AV30: 0.005442074 | AW30: -1 | AZ30: T | BA30: -0.022508933 | BB30: -0.023324029 | BC30: -0.010782952 | BD30: -0.0060011705 | BE30: -0.0010477136 | BF30: 0.012645008 | BG30: 0.002787183 | BH30: -0.00019389227 | BI30: -0.0042874819 | BJ30: 0.0033942042 | BK30: 0.023136315 | BL30: 0.0064457643 | BM30: 0.019079849
C31: D | D31: 0.14619646 | E31: -0.69382932 | F31: -0.59268193 | G31: -0.62252132 | H31: -0.067537605 | I31: -0.61406322 | J31: -0.61406322 | K31: -0.61406322 | L31: -0.27669831 | M31: -0.50448059 | N31: -0.48920778 | O31: -0.24493348 | P31: -0.12948699 | Q31: -0.59363236 | R31: 0.18441659 | S31: -0.54790076 | T31: -1.5384863 | U31: -0.88045133 | V31: -0.24999775 | W31: -0.085576957 | X31: 0 | AB31: D | AC31: 0.00700944 | AD31: 0.0022897769 | AE31: -2.0849536e-05 | AF31: 0.045776453 | AG31: -0.010498917 | AH31: 0.026978071 | AI31: 0.026978071 | AJ31: 0.026978071 | AK31: -0.0089253982 | AL31: 0.01088096 | AM31: -0.010557897 | AN31: 0.0070740744 | AO31: 0.0025366889 | AP31: 0.0069350125 | AQ31: 0.00018865088 | AR31: -0.0031128755 | AS31: 0.0277829 | AT31: -0.0082365135 | AU31: -0.0023698492 | AV31: 0.0067608585 | AW31: -1
C32: D | D32: 0.14619646 | E32: -0.69382932 | F32: -0.59268193 | G32: -0.62252132 | H32: -0.067537605 | I32: -0.61406322 | J32: -0.61406322 | K32: -0.61406322 | L32: -0.27669831 | M32: -0.50448059 | N32: -0.48920778 | O32: -0.24493348 | P32: -0.12948699 | Q32: -0.59363236 | R32: 0.18441659 | S32: -0.54790076 | T32: -1.5384863 | U32: -0.88045133 | V32: -0.24999775 | W32: -0.085576957 | X32: 0 | AB32: D | AC32: 0.00700944 | AD32: 0.0022897769 | AE32: -2.0849536e-05 | AF32: 0.045776453 | AG32: -0.010498917 | AH32: 0.026978071 | AI32: 0.026978071 | AJ32: 0.026978071 | AK32: -0.0089253982 | AL32: 0.01088096 | AM32: -0.010557897 | AN32: 0.0070740744 | AO32: 0.0025366889 | AP32: 0.0069350125 | AQ32: 0.00018865088 | AR32: -0.0031128755 | AS32: 0.0277829 | AT32: -0.0082365135 | AU32: -0.0023698492 | AV32: 0.0067608585 | AW32: -1 | AZ32: overall exp trend
C33: E | D33: -0.41087284 | E33: -0.95029899 | F33: -0.15194492 | G33: -0.61386217 | H33: -0.43313266 | I33: -0.059020509 | J33: -0.059020509 | K33: -0.059020509 | L33: -0.47568193 | M33: 0.012980468 | N33: -0.15822889 | O33: 0.12496433 | P33: 0.00055331806 | Q33: 0.83409049 | R33: -0.10072009 | S33: -0.58543602 | T33: -0.16313854 | U33: -0.68211335 | V33: 0.14368263 | W33: 0.066066063 | X33: 0 | AB33: D | AC33: 0.00700944 | AD33: 0.0022897769 | AE33: -2.0849536e-05 | AF33: 0.045776453 | AG33: -0.010498917 | AH33: 0.026978071 | AI33: 0.026978071 | AJ33: 0.026978071 | AK33: -0.0089253982 | AL33: 0.01088096 | AM33: -0.010557897 | AN33: 0.0070740744 | AO33: 0.0025366889 | AP33: 0.0069350125 | AQ33: 0.00018865088 | AR33: -0.0031128755 | AS33: 0.0277829 | AT33: -0.0082365135 | AU33: -0.0023698492 | AV33: 0.0067608585 | AW33: -1 | AZ33: time | BA33: 0 | BB33: 1 | BC33: 2 | BD33: 3 | BE33: 4 | BF33: 5 | BG33: 6 | BH33: 7 | BI33: 8 | BJ33: 9 | BK33: 10 | BL33: 11 | BM33: 12
C34: F | D34: -0.33192166 | E34: -0.80036838 | F34: 0.013847865 | G34: -0.61615044 | H34: 0.15269654 | I34: -0.53608407 | J34: -0.53608407 | K34: -0.53608407 | L34: -0.10135193 | M34: -0.79556298 | N34: -0.34442393 | O34: -0.4933889 | P34: 0.082065513 | Q34: -0.28258352 | R34: -0.17734606 | S34: -0.65519761 | T34: -2.0356434 | U34: -1.1247756 | V34: -0.30791392 | W34: 0.33357969 | X34: 0 | AB34: E | AC34: 0.0012203436 | AD34: -0.012545548 | AE34: 0.0059319115 | AF34: -0.021422963 | AG34: -0.013493049 | AH34: 0.0046124167 | AI34: 0.0046124167 | AJ34: 0.0046124167 | AK34: -0.0018086716 | AL34: 0.0071792883 | AM34: -0.015161863 | AN34: -0.011313444 | AO34: -0.0049823355 | AP34: 0.0057665976 | AQ34: -0.016738724 | AR34: -0.021184104 | AS34: -3.835569e-05 | AT34: -0.013106296 | AU34: 0.028450752 | AV34: 0.0033826745 | AW34: -1 | AZ34: A | BA34: 0.049328571 | BB34: 0.018330119 | BC34: 0.0024781082 | BD34: 0.025404968 | BE34: 0.039856656 | BF34: 0.023380541 | BG34: 0.053675456 | BH34: 0.021295903 | BI34: 0.012260525 | BJ34: -0.13709371 | BK34: 0.14085505 | BL34: 0.097877736 | BM34: 0.0082102889
C35: G | D35: -0.25716999 | E35: -0.72986036 | F35: -0.24373605 | G35: -0.55181618 | H35: -0.17699719 | I35: -0.52404985 | J35: -0.52404985 | K35: -0.52404985 | L35: -0.21626915 | M35: -0.28123746 | N35: -0.048005067 | O35: -0.43557446 | P35: -0.045503468 | Q35: 0.069528056 | R35: -0.048967658 | S35: 0.06810356 | T35: -0.033719987 | U35: -0.99387772 | V35: -0.2396803 | W35: -0.35792464 | X35: 0 | AB35: F | AC35: -0.00014427066 | AD35: -0.0083418468 | AE35: 0.010585958 | AF35: 0.034196696 | AG35: 0.002723823 | AH35: 0.015680163 | AI35: 0.015680163 | AJ35: 0.015680163 | AK35: -0.00094644713 | AL35: -0.0036428959 | AM35: -0.0023446709 | AN35: 0.00075972554 | AO35: 0.023704811 | AP35: -0.0060958183 | AQ35: -0.013314806 | AR35: -0.0083675223 | AS35: 0.0062081238 | AT35: -0.02814641 | AU35: -0.0030128301 | AV35: 0.025813185 | AW35: -1 | AZ35: B | BA35: 0.049328571 | BB35: 0.018330119 | BC35: 0.0024781082 | BD35: 0.025404968 | BE35: 0.039856656 | BF35: 0.023380541 | BG35: 0.053675456 | BH35: 0.021295903 | BI35: 0.012260525 | BJ35: -0.13709371 | BK35: 0.14085505 | BL35: 0.097877736 | BM35: 0.0082102889 | BO35: overall_initial_exp_trend
C36: H | D36: -0.13157445 | E36: -0.46279055 | F36: -0.13427887 | G36: -0.36922325 | H36: -0.014851193 | I36: -0.73921449 | J36: -0.73921449 | K36: -0.73921449 | L36: -0.080679561 | M36: -0.54788756 | N36: -0.021798861 | O36: -0.59023323 | P36: -0.094408333 | Q36: -1.2045095 | R36: -0.0082923452 | S36: -0.44132336 | T36: -1.0038439 | U36: -2.0690099 | V36: -0.34462229 | W36: 0.057678495 | X36: 0 | AB36: G | AC36: 0.013990736 | AD36: -0.001453353 | AE36: 0.0022874298 | AF36: 0.040383958 | AG36: 0.00065219073 | AH36: 0.0081683158 | AI36: 0.0081683158 | AJ36: 0.0081683158 | AK36: 0.00043157551 | AL36: -0.0014929304 | AM36: 0.0032361611 | AN36: 0.0033350724 | AO36: 0.0050287026 | AP36: 0.0037284794 | AQ36: -0.010068084 | AR36: 0.0029329584 | AS36: 0.010438339 | AT36: -0.021302134 | AU36: -0.0014491037 | AV36: 0.0086355963 | AW36: -1 | AZ36: C | BA36: 0.049328571 | BB36: 0.018330119 | BC36: 0.0024781082 | BD36: 0.025404968 | BE36: 0.039856656 | BF36: 0.023380541 | BG36: 0.053675456 | BH36: 0.021295903 | BI36: 0.012260525 | BJ36: -0.13709371 | BK36: 0.14085505 | BL36: 0.097877736 | BM36: 0.0082102889 | BO36: overall_initial_gov_c_trend
C37: I | D37: 0.042575444 | E37: -0.63720307 | F37: 0.061856896 | G37: -0.084223144 | H37: -0.15978125 | I37: -0.012445345 | J37: -0.012445345 | K37: -0.012445345 | L37: 0.10825052 | M37: -0.30453026 | N37: -0.52663657 | O37: -0.75751865 | P37: -0.14149154 | Q37: -0.54461298 | R37: -0.074100205 | S37: -0.69353692 | T37: -0.73852775 | U37: -0.91425233 | V37: -0.075217831 | W37: -1.2035562 | X37: 0 | AB37: H | AC37: 0.0017024574 | AD37: -0.0055632253 | AE37: 0.0021654592 | AF37: 0.036860447 | AG37: 0.020977877 | AH37: 0.045689723 | AI37: 0.045689723 | AJ37: 0.045689723 | AK37: 0.019401815 | AL37: -0.0076697299 | AM37: -0.0020849911 | AN37: 0.010191997 | AO37: 0.014430146 | AP37: -0.00034371588 | AQ37: -0.0098658583 | AR37: -0.015079928 | AS37: -0.011759178 | AT37: -0.030679018 | AU37: 0.0092485318 | AV37: 0.00093341568 | AW37: -1 | AZ37: C19 | BA37: 0.049328571 | BB37: 0.018330119 | BC37: 0.0024781082 | BD37: 0.025404968 | BE37: 0.039856656 | BF37: 0.023380541 | BG37: 0.053675456 | BH37: 0.021295903 | BI37: 0.012260525 | BJ37: -0.13709371 | BK37: 0.14085505 | BL37: 0.097877736 | BM37: 0.0082102889 | BO37: timet
C38: J_R_S | D38: -0.52811736 | E38: -0.45092013 | F38: -0.060520358 | G38: 0.26235767 | H38: -0.28097687 | I38: 0.31240537 | J38: 0.31240537 | K38: 0.31240537 | L38: -0.091190138 | M38: -0.29164754 | N38: -0.40894429 | O38: -0.21741376 | P38: -0.22524079 | Q38: 1.1159978 | R38: -0.067769523 | S38: -0.90299292 | T38: 0.045067357 | U38: -1.0427052 | V38: -0.080776099 | W38: -0.62607855 | X38: 0 | AB38: I | AC38: 0.018413712 | AD38: 0.004032471 | AE38: 0.0048806252 | AF38: 0.068328046 | AG38: 0.0042953657 | AH38: 0.038785777 | AI38: 0.038785777 | AJ38: 0.038785777 | AK38: 0.017622886 | AL38: 0.0014478122 | AM38: -0.0036465407 | AN38: 0.0060327747 | AO38: -0.0023995681 | AP38: 0.006701301 | AQ38: -0.00598246 | AR38: -0.0031024135 | AS38: 0.002348913 | AT38: -0.012012269 | AU38: 0.0056733236 | AV38: 0.0099284677 | AW38: -1 | AZ38: C29 | BA38: 0.049328571 | BB38: 0.018330119 | BC38: 0.0024781082 | BD38: 0.025404968 | BE38: 0.039856656 | BF38: 0.023380541 | BG38: 0.053675456 | BH38: 0.021295903 | BI38: 0.012260525 | BJ38: -0.13709371 | BK38: 0.14085505 | BL38: 0.097877736 | BM38: 0.0082102889
C39: K | D39: 0.34446373 | E39: -0.42545085 | F39: 0.06254216 | G39: -0.11038874 | H39: -0.092572205 | I39: 0.1311056 | J39: 0.1311056 | K39: 0.1311056 | L39: 0.12362102 | M39: -0.47823933 | N39: 0.003481333 | O39: -0.58032641 | P39: 0.044244291 | Q39: -0.68643337 | R39: -0.10376767 | S39: -0.47527609 | T39: -0.85763946 | U39: -0.63888199 | V39: 0.30629052 | W39: 0.26378757 | X39: 0 | AB39: J_R_S | AC39: 0.00082723748 | AD39: 0.014074248 | AE39: 0.0019574112 | AF39: 0.07454877 | AG39: 0.0036768053 | AH39: 0.048227031 | AI39: 0.048227031 | AJ39: 0.048227031 | AK39: 0.022524047 | AL39: 0.019933002 | AM39: 0.0014691692 | AN39: 0.0065045293 | AO39: 0.0034276443 | AP39: 0.0093707845 | AQ39: 0.0060038299 | AR39: -0.020043974 | AS39: 0.016681515 | AT39: -0.005266177 | AU39: 0.013404195 | AV39: 0.015530564 | AW39: -1 | AZ39: D1 | BA39: 0.049328571 | BB39: 0.018330119 | BC39: 0.0024781082 | BD39: 0.025404968 | BE39: 0.039856656 | BF39: 0.023380541 | BG39: 0.053675456 | BH39: 0.021295903 | BI39: 0.012260525 | BJ39: -0.13709371 | BK39: 0.14085505 | BL39: 0.097877736 | BM39: 0.0082102889
C40: L | D40: 0.013767255 | E40: -0.4098072 | F40: 0.032451361 | G40: 0.21121372 | H40: -0.032671532 | I40: -0.18038788 | J40: -0.18038788 | K40: -0.18038788 | L40: 0.054911822 | M40: 0.030886579 | N40: -0.02680416 | O40: -0.0826068 | P40: -0.092595313 | Q40: 0.38788586 | R40: 0.041196354 | S40: -0.11650819 | T40: -0.27310023 | U40: -0.81788434 | V40: 0.082013665 | W40: 1.1553253 | X40: 0 | AB40: K | AC40: 0.031607916 | AD40: 0.0061573232 | AE40: 0.010029806 | AF40: 0.086045347 | AG40: 0.010824767 | AH40: 0.054804724 | AI40: 0.054804724 | AJ40: 0.054804724 | AK40: 0.019978874 | AL40: 0.03097493 | AM40: 0.0015950209 | AN40: 0.027689298 | AO40: 0.021034862 | AP40: 0.0071363223 | AQ40: 0.0019011777 | AR40: 0.0051314456 | AS40: 0.021823855 | AT40: 0.0096604505 | AU40: 0.016697774 | AV40: 0.021105326 | AW40: -1 | AZ40: D2 | BA40: 0.049328571 | BB40: 0.018330119 | BC40: 0.0024781082 | BD40: 0.025404968 | BE40: 0.039856656 | BF40: 0.023380541 | BG40: 0.053675456 | BH40: 0.021295903 | BI40: 0.012260525 | BJ40: -0.13709371 | BK40: 0.14085505 | BL40: 0.097877736 | BM40: 0.0082102889
